Workbook

Sheet отчет
A1: Отчет по выполнению вех
H3: № | I3: Название проекта | J3: D | K3: Выполнение на текущий недельный спринт
B4: Значения | K4: кол-во выполненных вех | M4: кол-во выполненных задач
A5: Названия строк | B5: Количество по полю Задача | C5: Сумма по полю Выполнена | D5: =GETPIVOTDATA("Сумма по полю Выполнена",$A$3,"Теги","страт-п-с-26-09, Операционный директор, Старт вехи Pre")/GETPIVOTDATA("Количество по полю Задача",$A$3,"Теги","страт-п-с-26-09, Операционный директор, Старт вехи Pre") -> 0
A6: Лично сентябрь 2026 | B6: 3 | C6: 0 | D6: =GETPIVOTDATA("Сумма по полю Выполнена",$A$3,"Теги","страт-п-с-26-09, Операционный директор, Старт вехи Pre")/GETPIVOTDATA("Количество по полю Задача",$A$3,"Теги","страт-п-с-26-09, Операционный директор, Старт вехи Pre") -> 0 | K6: план | L6: факт | M6: план | N6: факт
A7: страт-п-с-26-09, Операционный директор, Старт вехи Pre | B7: 1 | C7: 0 | D7: =GETPIVOTDATA("Сумма по полю Выполнена",$A$3,"Теги","страт-п-с-26-09, Операционный директор, Старт вехи Pre")/GETPIVOTDATA("Количество по полю Задача",$A$3,"Теги","страт-п-с-26-09, Операционный директор, Старт вехи Pre") -> 0 | H7: 1 | I7: Лично семинар | J7: 46289 | K7: =SUM(GETPIVOTDATA("Количество по полю Задача",$A$3,"Теги","страт-п-с-26-09, Операционный директор, Старт вехи Pre"),GETPIVOTDATA("Количество по полю Задача",$A$3,"Теги","страт-п-с-26-09, Операционный директор, старт вехи Pro")+GETPIVOTDATA("Количество по полю Задача",$A$3,"Теги","страт-п-с-26-09, Операционный директор, финиш вехи Post")) -> 3 | L7: =SUM(GETPIVOTDATA("Сумма по полю Выполнена",$A$3,"Теги","страт-п-с-26-09, Операционный директор, Старт вехи Pre")+GETPIVOTDATA("Сумма по полю Выполнена",$A$3,"Теги","страт-п-с-26-09, Операционный директор, старт вехи Pro")+GETPIVOTDATA("Сумма по полю Выполнена",$A$3,"Теги","страт-п-с-26-09, Операционный директор, финиш вехи Post")) -> 0 | M7: =GETPIVOTDATA("Количество по полю Задача",$A$3) -> 3 | N7: =GETPIVOTDATA("Сумма по полю Выполнена",$A$3) -> 0
A8: страт-п-с-26-09, Операционный директор, старт вехи Pro | B8: 1 | C8: 0 | H8: 2 | J8: дата 2
A9: страт-п-с-26-09, Операционный директор, финиш вехи Post | B9: 1 | C9: 0 | H9: 3 | J9: дата 3
A10: Общий итог | B10: 3 | C10: 0 | H10: N | I10: Проект N | J10: дата N | K10: x | L10: x | M10: х | N10: Х (Y%)
A12: Отчет по выполнению задач
H13: № | I13: Название проекта | J13: D | K13: Выполнение на текущий недельный спринт
K14: кол-во выполненных вех | M14: кол-во выполненных задач
B15: Значения
A16: Названия строк | B16: Количество по полю Задача | C16: Сумма по полю Выполнена | K16: план | L16: факт | M16: план | N16: факт
A17: Лично сентябрь 2026 | B17: 227 | C17: 0 | D17: =GETPIVOTDATA("Сумма по полю Выполнена",$A$15,"название мероприятия","Лично сентябрь 2026")/GETPIVOTDATA("Количество по полю Задача",$A$15,"название мероприятия","Лично сентябрь 2026") -> 0 | H17: 1 | I17: Здраво | J17: дата 1 | K17: 2 | L17: 2 | M17: 41 | N17: 33 (80%)
A18: координатор | B18: 61 | C18: 0 | D18: =GETPIVOTDATA("Сумма по полю Выполнена",$A$15,"название мероприятия","Лично сентябрь 2026")/GETPIVOTDATA("Количество по полю Задача",$A$15,"название мероприятия","Лично сентябрь 2026") -> 0 | H18: 1.1. | I18: Руководитель Дивизиона | M18: 9 | N18: 9 (100%)
A19: лидген | B19: 21 | C19: 0 | D19: =GETPIVOTDATA("Сумма по полю Выполнена",$A$15,"название мероприятия","Лично сентябрь 2026")/GETPIVOTDATA("Количество по полю Задача",$A$15,"название мероприятия","Лично сентябрь 2026") -> 0 | H19: 1.2. | I19: Продюсер | M19: 12 | N19: 12 (100%)
A20: Операцоинный директор | B20: 3 | C20: 0 | D20: =GETPIVOTDATA("Сумма по полю Выполнена",$A$15,"название мероприятия","Лично сентябрь 2026")/GETPIVOTDATA("Количество по полю Задача",$A$15,"название мероприятия","Лично сентябрь 2026") -> 0 | H20: 1.3. | I20: Координатор | M20: 9 | N20: 9 (100%)
A21: продюсер | B21: 66 | C21: 0 | D21: =GETPIVOTDATA("Сумма по полю Выполнена",$A$15,"название мероприятия","Лично сентябрь 2026")/GETPIVOTDATA("Количество по полю Задача",$A$15,"название мероприятия","Лично сентябрь 2026") -> 0 | H21: 1.4. | I21: Лидген | M21: 8 | N21: 8 (100%)
A22: РГП | B22: 41 | C22: 0 | D22: =GETPIVOTDATA("Сумма по полю Выполнена",$A$15,"название мероприятия","Лично сентябрь 2026")/GETPIVOTDATA("Количество по полю Задача",$A$15,"название мероприятия","Лично сентябрь 2026") -> 0 | H22: 1.5. | I22: Руководитель группы продаж | M22: 3 | N22: 3 (100%)
A23: ШП | B23: 35 | C23: 0 | D23: =GETPIVOTDATA("Сумма по полю Выполнена",$A$15,"название мероприятия","Лично сентябрь 2026")/GETPIVOTDATA("Количество по полю Задача",$A$15,"название мероприятия","Лично сентябрь 2026") -> 0 | H23: 2 | I23: Стратегия | J23: дата 2 | K23: 2 | L23: 1 | M23: 34 | N23: 25 (73%)
A24: Общий итог | B24: 227 | C24: 0 | H24: 2.1. | I24: Руководитель Дивизиона | M24: 9 | N24: 4 (44%)
H25: 2.2. | I25: Продюсер | M25: 8 | N25: 8 (100%)
H26: 2.3. | I26: Координатор | M26: 7 | N26: 7 (100%)
H27: 2.4. | I27: Лидген | M27: 4 | N27: 4 (100%)
H28: 2.5. | I28: Руководитель группы продаж | M28: 3 | N28: 2 (66%)
H29: 3 | I29: Реклама | J29: дата 3 | K29: 2 | L29: 1 | M29: 30 | N29: 15 (50%)
H30: 3.1. | I30: Руководитель Дивизиона | M30: 9 | N30: 6 (66%)
H31: 3.2. | I31: Продюсер | M31: 6 | N31: 3 (50%)
H32: 3.3. | I32: Координатор | M32: 5 | N32: 4 (80%)
H33: 3.4. | I33: Лидген | M33: 7 | N33: 1 (14%)
H34: 3.5. | I34: Руководитель группы продаж | M34: 3 | N34: 1 (33%)
H35: N | I35: Проект N | J35: дата N | K35: x | L35: x | M35: х | N35: Х (Y%)

Sheet Worksheet
A1: ID | B1: Проект | C1: Доска | D1: Колонка | E1: Корневая задача | F1: Родительская задача | G1: Автор | H1: Задача | I1: Дата начала | J1: Дедлайн | K1: Оценка времени | L1: Тип | M1: Приоритет | N1: Выполнена | O1: Дата выполнения | P1: Дата создания | Q1: Просроченные дни | R1: Исполнители | S1: Подписчики | T1: Сделка | U1: Изображение | V1: Приватная | W1: Повторяемая | X1: Описание | Y1: Теги | Z1: Потраченное время | AA1: История | AB1: название мероприятия | AC1: роль и мероприятие | AD1: роль
A2: 903 | B2: ЛИЧНО сентябрь 24.09.2026 | C2: Дивизион Конференции | D2: К работе | G2: Екатерина | H2: 3.61. Оплатить оборудование и доп.питание | I2: 28.09.2026 03:00 | J2: 01.10.2026 | L2: Действие | M2: Низкий | N2: N | P2: 29.04.2026 14:01:16 | S2: Екатерина | V2: N | W2: N | Y2: POST, координатор, страт-п-с-26-09 | AA2: 2026-04-29 14:01:17: Екатерина создал(-а) задачу; 2026-04-29 15:01:30: Екатерина изменил(-а) дату на 28.09.2026; 2026-04-29 15:01:32: Екатерина изменил(-а) дату на 28.09.2026 - 28.09.2026; 2026-04-29 15:01:33: Екатерина изменил(-а) дату на 28.09.2026 - 01.10.2026; 2026-04-29 15:01:45: Екатерина добавил(-а) тег POST; 2026-04-29 15:01:47: Екатерина добавил(-а) тег страт-п-с-26-09; 2026-04-29 15:01:50: Екатерина добавил(-а) тег Лидген; 2026-04-29 15:56:05: Екатерина изменил(-а) название на 3.62. Оплатить оборудование и доп.питание; 2026-04-30 10:43:39: Екатерина изменил(-а) название на 3.61. Оплатить оборудование и доп.питание; 2026-04-30 14:43:14: Екатерина убрал(-а) тег страт-п-с-26-09; 2026-04-30 14:43:17: Екатерина убрал(-а) тег Лидген; 2026-04-30 14:43:23: Екатерина добавил(-а) тег координатор; 2026-04-30 14:43:24: Екатерина добавил(-а) тег страт-п-с-26-09 | AB2: Лично сентябрь 2026 | AC2: =VLOOKUP(Y2,'впр данные'!A:B,2,1) -> координатор, страт-п-с-26-09 | AD2: =VLOOKUP(Y2,'впр данные'!A:C,3,1) -> координатор
A3: 459 | B3: ЛИЧНО сентябрь 24.09.2026 | C3: Дивизион Конференции | D3: К работе | G3: Екатерина | H3: 4.05. Проанализировать полученные от продюсеров результаты глубинного исследования | I3: 01.06.2026 03:00 | J3: 04.06.2026 | L3: Действие | M3: Низкий | N3: N | P3: 28.04.2026 18:39:45 | S3: Екатерина | V3: N | W3: N | Y3: PRE, Лидген, страт-п-с-26-09 | AA3: 2026-04-28 18:39:45: Екатерина создал(-а) задачу; 2026-04-29 11:31:52: Екатерина изменил(-а) дату на 02.06.2026; 2026-04-29 11:31:53: Екатерина изменил(-а) дату на 01.06.2026 - 02.06.2026; 2026-04-29 11:31:56: Екатерина изменил(-а) дату на 01.06.2026 - 04.06.2026; 2026-04-29 13:23:39: Екатерина добавил(-а) тег PRE; 2026-04-29 13:23:42: Екатерина добавил(-а) тег лидген; 2026-04-29 13:23:43: Екатерина добавил(-а) тег страт-п-с-26-09; 2026-04-29 13:24:54: Екатерина убрал(-а) тег лидген; 2026-04-29 13:25:03: Екатерина добавил(-а) тег Лидген; 2026-04-30 14:42:56: Екатерина убрал(-а) тег страт-п-с-26-09; 2026-04-30 14:42:59: Екатерина добавил(-а) тег страт-п-с-26-09 | AB3: Лично сентябрь 2026 | AC3: =VLOOKUP(Y3,'впр данные'!A:B,2,1) -> лидген, страт-п-с-26-09 | AD3: =VLOOKUP(Y3,'впр данные'!A:C,3,1) -> лидген
A4: 456 | E4: 4.06. Получить от продюсеров и проанализировать Концепцию и Программу | F4: 4.06. Получить от продюсеров и проанализировать Концепцию и Программу | G4: Екатерина | H4: 4.06.1. Получить от продюсеров и проанализировать Концепцию и Программу | L4: Действие | M4: Низкий | N4: N | P4: 28.04.2026 18:22:41 | S4: Екатерина | V4: N | W4: N | AA4: 2026-04-28 18:22:41: Екатерина создал(-а) задачу | AB4: Лично сентябрь 2026 | AC4: =VLOOKUP(Y4,'впр данные'!A:B,2,1) -> #N/A | AD4: =VLOOKUP(Y4,'впр данные'!A:C,3,1) -> #N/A
A5: 454 | E5: 4.03. Подготовить семантическое ядро | F5: 4.03. Подготовить семантическое ядро | G5: Екатерина | H5: 4.03.1. Для проведение маркетингового анализа и разработки семантического ядра изучить полученные от продюсеров результаты кабинетного исследования | L5: Действие | M5: Низкий | N5: N | P5: 28.04.2026 18:18:38 | S5: Екатерина | V5: N | W5: N | AA5: 2026-04-28 18:18:38: Екатерина создал(-а) задачу; 2026-04-28 19:08:26: Екатерина изменил(-а) название на 4/Для проведение маркетингового анализа и разработки семантического ядра изучить полученные от продюсеров результаты кабинетного исследования; 2026-04-28 19:08:28: Екатерина изменил(-а) название на 4.03Для проведение маркетингового анализа и разработки семантического ядра изучить полученные от продюсеров результаты кабинетного исследования; 2026-04-28 19:08:29: Екатерина изменил(-а) название на 4.03.Для проведение маркетингового анализа и разработки семантического ядра изучить полученные от продюсеров результаты кабинетного исследования; 2026-04-28 19:08:30: Екатерина изменил(-а) название на 4.03.1.Для проведение маркетингового анализа и разработки семантического ядра изучить полученные от продюсеров результаты кабинетного исследования; 2026-04-28 19:08:33: Екатерина изменил(-а) название на 4.03.1. Для проведение маркетингового анализа и разработки семантического ядра изучить полученные от продюсеров результаты кабинетного исследования | AB5: Лично сентябрь 2026 | AC5: =VLOOKUP(Y5,'впр данные'!A:B,2,1) -> #N/A | AD5: =VLOOKUP(Y5,'впр данные'!A:C,3,1) -> #N/A
A6: 453 | E6: 4.01. Подготовиться к Первичному совещанию | F6: 4.01. Подготовиться к Первичному совещанию | G6: Екатерина | H6: 4.01.3. Подготовить базу на основе анализа емкости рынка | L6: Действие | M6: Низкий | N6: N | P6: 28.04.2026 18:12:33 | S6: Екатерина | V6: N | W6: N | AA6: 2026-04-28 18:12:33: Екатерина создал(-а) задачу | AB6: Лично сентябрь 2026 | AC6: =VLOOKUP(Y6,'впр данные'!A:B,2,1) -> #N/A | AD6: =VLOOKUP(Y6,'впр данные'!A:C,3,1) -> #N/A
A7: 452 | E7: 4.01. Подготовиться к Первичному совещанию | F7: 4.01. Подготовиться к Первичному совещанию | G7: Екатерина | H7: 4.01.2. Посчитать емкость рынка | L7: Действие | M7: Низкий | N7: N | P7: 28.04.2026 18:12:14 | S7: Екатерина | V7: N | W7: N | AA7: 2026-04-28 18:12:15: Екатерина создал(-а) задачу | AB7: Лично сентябрь 2026 | AC7: =VLOOKUP(Y7,'впр данные'!A:B,2,1) -> #N/A | AD7: =VLOOKUP(Y7,'впр данные'!A:C,3,1) -> #N/A
A8: 451 | E8: 4.01. Подготовиться к Первичному совещанию | F8: 4.01. Подготовиться к Первичному совещанию | G8: Екатерина | H8: 4.01.1. Презентовать анализ рекламной кампании прошлого мероприятия с декомпозицией каналов | L8: Действие | M8: Низкий | N8: N | P8: 28.04.2026 18:10:33 | S8: Екатерина | V8: N | W8: N | AA8: 2026-04-28 18:10:34: Екатерина создал(-а) задачу; 2026-04-28 18:11:05: Екатерина изменил(-а) название на 4.01.1. Презентовать анализ рекламной кампании прошлого мероприятия с декомпозицией каналов; 2026-04-29 13:22:52: Екатерина добавил(-а) тег PRE; 2026-04-29 13:22:56: Екатерина добавил(-а) тег лидген; 2026-04-29 13:22:58: Екатерина добавил(-а) тег страт-п-с-26-09; 2026-04-29 13:23:10: Екатерина убрал(-а) тег PRE; 2026-04-29 13:23:11: Екатерина убрал(-а) тег лидген; 2026-04-29 13:23:13: Екатерина убрал(-а) тег страт-п-с-26-09 | AB8: Лично сентябрь 2026 | AC8: =VLOOKUP(Y8,'впр данные'!A:B,2,1) -> #N/A | AD8: =VLOOKUP(Y8,'впр данные'!A:C,3,1) -> #N/A
A9: 428 | B9: ЛИЧНО сентябрь 24.09.2026 | C9: Дивизион Конференции | D9: К работе | G9: Екатерина | H9: 4.01. Подготовиться к Первичному совещанию | I9: 18.05.2026 03:00 | J9: 19.05.2026 | L9: Действие | M9: Низкий | N9: N | P9: 28.04.2026 17:29:49 | S9: Екатерина | V9: N | W9: N | Y9: PRE, Лидген, страт-п-с-26-09 | AA9: 2026-04-28 17:29:49: Екатерина скопировал(-а) задачу #212 4.1. Для подготовки к Первичному совещанию Лидгеном презентовать анализ рекламной кампании прошлого мероприятия с декомпозицией каналов и посчитать емкость рынка - на основе нее подготовить базу, а по ней составить план по лидам; 2026-04-28 17:35:18: Екатерина изменил(-а) название на 4.01. Для подготовки к Первичному совещанию Лидгеном презентовать анализ рекламной кампании прошлого мероприятия с декомпозицией каналов и посчитать емкость рынка - на основе нее подготовить базу, а по ней составить план по лидам - Копия; 2026-04-28 18:10:34: Екатерина добавил(-а) подзадачу #451 4.01.1. Презентовать анализ рекламной кампании прошлого мероприятия с декомпозицией каналов; 2026-04-28 18:12:15: Екатерина добавил(-а) подзадачу #452 4.01.2. Посчитать емкость рынка; 2026-04-28 18:12:34: Екатерина добавил(-а) подзадачу #453 4.01.3. Подготовить базу на основе анализа емкости рынка; 2026-04-28 18:13:11: Екатерина изменил(-а) название на 4.01. Подготовиться к; 2026-04-28 18:13:16: Екатерина изменил(-а) название на 4.01. Подготовиться к Первичному совещанию; 2026-04-29 10:00:22: Екатерина добавил(-а) тег лидген; 2026-04-29 11:30:19: Екатерина изменил(-а) дату на 10.05.2026 - 06.07.2026; 2026-04-29 11:30:20: Екатерина изменил(-а) дату на 10.05.2026 - 11.05.2026; 2026-04-29 11:30:30: Екатерина изменил(-а) дату на 10.05.2026 - 19.05.2026; 2026-04-29 11:30:34: Екатерина изменил(-а) дату на 18.05.2026 - 19.05.2026; 2026-04-29 13:22:48: Екатерина добавил(-а) тег PRE; 2026-04-29 13:23:02: Екатерина добавил(-а) тег страт-п-с-26-09; 2026-04-30 14:37:49: Екатерина убрал(-а) тег лидген; 2026-04-30 14:37:51: Екатерина убрал(-а) тег страт-п-с-26-09; 2026-04-30 14:37:58: Екатерина добавил(-а) тег лидген; 2026-04-30 14:38:02: Екатерина добавил(-а) тег страт-п-с-26-09; 2026-04-30 14:43:35: Екатерина убрал(-а) тег лидген; 2026-04-30 14:43:37: Екатерина убрал(-а) тег страт-п-с-26-09; 2026-04-30 14:43:41: Екатерина добавил(-а) тег Лидген; 2026-04-30 14:43:43: Екатерина добавил(-а) тег страт-п-с-26-09 | AB9: Лично сентябрь 2026 | AC9: =VLOOKUP(Y9,'впр данные'!A:B,2,1) -> лидген, страт-п-с-26-09 | AD9: =VLOOKUP(Y9,'впр данные'!A:C,3,1) -> лидген
A10: 427 | B10: ЛИЧНО сентябрь 24.09.2026 | C10: Дивизион Конференции | D10: К работе | G10: Екатерина | H10: 3.60. Проведено итоговое совещание по проекту | I10: 28.09.2026 03:00 | J10: 01.10.2026 | L10: Действие | M10: Низкий | N10: N | P10: 28.04.2026 17:00:20 | S10: Екатерина | V10: N | W10: N | Y10: POST, координатор, страт-п-с-26-09 | AA10: 2026-04-28 17:00:20: Екатерина создал(-а) задачу; 2026-04-29 11:28:33: Екатерина изменил(-а) дату на 29.09.2026; 2026-04-29 11:28:34: Екатерина изменил(-а) дату на 28.09.2026 - 29.09.2026; 2026-04-29 11:28:37: Екатерина изменил(-а) дату на 28.09.2026 - 01.10.2026; 2026-04-29 13:22:18: Екатерина добавил(-а) тег POST; 2026-04-29 13:22:40: Екатерина добавил(-а) тег координатор; 2026-04-29 13:22:41: Екатерина добавил(-а) тег страт-п-с-26-09; 2026-04-29 15:56:02: Екатерина изменил(-а) название на 3.61. Проведено итоговое совещание по проекту; 2026-04-30 10:43:36: Екатерина изменил(-а) название на 3.60. Проведено итоговое совещание по проекту | AB10: Лично сентябрь 2026 | AC10: =VLOOKUP(Y10,'впр данные'!A:B,2,1) -> координатор, страт-п-с-26-09 | AD10: =VLOOKUP(Y10,'впр данные'!A:C,3,1) -> координатор
A11: 426 | B11: ЛИЧНО сентябрь 24.09.2026 | C11: Дивизион Конференции | D11: К работе | G11: Екатерина | H11: 3.59. Отправлены благодарности, презентации, фотографии участникам | I11: 28.09.2026 03:00 | J11: 01.10.2026 | L11: Действие | M11: Низкий | N11: N | P11: 28.04.2026 16:59:49 | S11: Екатерина | V11: N | W11: N | Y11: POST, координатор, страт-п-с-26-09 | AA11: 2026-04-28 16:59:49: Екатерина создал(-а) задачу; 2026-04-29 11:28:49: Екатерина изменил(-а) дату на 29.09.2026; 2026-04-29 11:28:50: Екатерина изменил(-а) дату на 27.09.2026 - 29.09.2026; 2026-04-29 11:28:52: Екатерина изменил(-а) дату на 27.09.2026 - 02.10.2026; 2026-04-29 11:28:53: Екатерина изменил(-а) дату на 28.09.2026 - 02.10.2026; 2026-04-29 11:28:55: Екатерина изменил(-а) дату на 28.09.2026 - 01.10.2026; 2026-04-29 13:22:14: Екатерина добавил(-а) тег POST; 2026-04-29 13:22:28: Екатерина добавил(-а) тег координатор; 2026-04-29 13:22:29: Екатерина добавил(-а) тег страт-п-с-26-09; 2026-04-29 15:55:58: Екатерина изменил(-а) название на 3.60. Отправлены благодарности, презентации, фотографии участникам; 2026-04-30 10:43:31: Екатерина изменил(-а) название на 3.59. Отправлены благодарности, презентации, фотографии участникам | AB11: Лично сентябрь 2026 | AC11: =VLOOKUP(Y11,'впр данные'!A:B,2,1) -> координатор, страт-п-с-26-09 | AD11: =VLOOKUP(Y11,'впр данные'!A:C,3,1) -> координатор
A12: 425 | B12: ЛИЧНО сентябрь 24.09.2026 | C12: Дивизион Конференции | D12: К работе | G12: Екатерина | H12: 3.58. Подготовлен отчет + и - мероприятия | I12: 28.09.2026 03:00 | J12: 01.10.2026 | L12: Действие | M12: Низкий | N12: N | P12: 28.04.2026 16:59:37 | S12: Екатерина | V12: N | W12: N | Y12: POST, координатор, страт-п-с-26-09 | AA12: 2026-04-28 16:59:37: Екатерина создал(-а) задачу; 2026-04-28 17:00:05: Екатерина изменил(-а) название на 3.62. Подготовлен отчет + и +- мероприятия; 2026-04-28 17:00:07: Екатерина изменил(-а) название на 3.62. Подготовлен отчет + и - мероприятия; 2026-04-29 11:28:39: Екатерина изменил(-а) дату на 29.09.2026; 2026-04-29 11:28:41: Екатерина изменил(-а) дату на 27.09.2026 - 29.09.2026; 2026-04-29 11:28:43: Екатерина изменил(-а) дату на 27.09.2026 - 02.10.2026; 2026-04-29 11:28:46: Екатерина изменил(-а) дату на 28.09.2026 - 02.10.2026; 2026-04-29 11:28:49: Екатерина изменил(-а) дату на 28.09.2026 - 01.10.2026; 2026-04-29 13:22:10: Екатерина добавил(-а) тег POST; 2026-04-29 13:22:22: Екатерина добавил(-а) тег координатор; 2026-04-29 13:22:23: Екатерина добавил(-а) тег страт-п-с-26-09; 2026-04-29 15:55:51: Екатерина изменил(-а) название на 3.59. Подготовлен отчет + и - мероприятия; 2026-04-30 10:43:26: Екатерина изменил(-а) название на 3.58. Подготовлен отчет + и - мероприятия | AB12: Лично сентябрь 2026 | AC12: =VLOOKUP(Y12,'впр данные'!A:B,2,1) -> координатор, страт-п-с-26-09 | AD12: =VLOOKUP(Y12,'впр данные'!A:C,3,1) -> координатор
A13: 424 | B13: ЛИЧНО сентябрь 24.09.2026 | C13: Дивизион Конференции | D13: К работе | G13: Екатерина | H13: 3.57. Подготовлен отчет по подотчетным | I13: 28.09.2026 03:00 | J13: 01.10.2026 | L13: Действие | M13: Низкий | N13: N | P13: 28.04.2026 16:59:26 | S13: Екатерина | V13: N | W13: N | Y13: POST, координатор, страт-п-с-26-09 | AA13: 2026-04-28 16:59:26: Екатерина создал(-а) задачу; 2026-04-29 11:11:02: Екатерина добавил(-а) тег POST; 2026-04-29 11:28:15: Екатерина изменил(-а) дату на 26.09.2026; 2026-04-29 11:28:18: Екатерина изменил(-а) дату на 26.09.2026 - 29.09.2026; 2026-04-29 11:28:22: Екатерина изменил(-а) дату на 28.09.2026 - 29.09.2026; 2026-04-29 11:28:26: Екатерина изменил(-а) дату на 28.09.2026 - 01.10.2026; 2026-04-29 13:22:04: Екатерина добавил(-а) тег координатор; 2026-04-29 13:22:06: Екатерина добавил(-а) тег страт-п-с-26-09; 2026-04-29 15:55:46: Екатерина изменил(-а) название на 3.58. Подготовлен отчет по подотчетным; 2026-04-30 10:43:22: Екатерина изменил(-а) название на 3.57. Подготовлен отчет по подотчетным | AB13: Лично сентябрь 2026 | AC13: =VLOOKUP(Y13,'впр данные'!A:B,2,1) -> координатор, страт-п-с-26-09 | AD13: =VLOOKUP(Y13,'впр данные'!A:C,3,1) -> координатор
A14: 423 | B14: ЛИЧНО сентябрь 24.09.2026 | C14: Дивизион Конференции | D14: К работе | G14: Екатерина | H14: 3.56. Сверка на предмет участие, все ли оплатившие пришли, чтобы исключить претензии | J14: 24.09.2026 | L14: Действие | M14: Низкий | N14: N | P14: 28.04.2026 16:59:17 | S14: Екатерина | V14: N | W14: N | Y14: D, координатор, страт-п-с-26-09 | AA14: 2026-04-28 16:59:17: Екатерина создал(-а) задачу; 2026-04-29 11:28:08: Екатерина изменил(-а) дату на 24.09.2026; 2026-04-29 11:28:09: Екатерина изменил(-а) дату на 24.09.2026 - 25.09.2026; 2026-04-29 11:28:13: Екатерина изменил(-а) дату на 24.09.2026; 2026-04-29 13:21:34: Екатерина добавил(-а) тег D; 2026-04-29 13:21:58: Екатерина добавил(-а) тег координатор; 2026-04-29 13:21:59: Екатерина добавил(-а) тег страт-п-с-26-09; 2026-04-29 15:55:10: Екатерина изменил(-а) название на 3.57. Сверка на предмет участие, все ли оплатившие пришли, чтобы исключить претензии; 2026-04-30 10:43:17: Екатерина изменил(-а) название на 3.55. Сверка на предмет участие, все ли оплатившие пришли, чтобы исключить претензии; 2026-04-30 10:43:17: Екатерина изменил(-а) название на 3.5. Сверка на предмет участие, все ли оплатившие пришли, чтобы исключить претензии; 2026-04-30 10:43:18: Екатерина изменил(-а) название на 3.56. Сверка на предмет участие, все ли оплатившие пришли, чтобы исключить претензии | AB14: Лично сентябрь 2026 | AC14: =VLOOKUP(Y14,'впр данные'!A:B,2,1) -> координатор, страт-п-с-26-09 | AD14: =VLOOKUP(Y14,'впр данные'!A:C,3,1) -> координатор
A15: 422 | B15: ЛИЧНО сентябрь 24.09.2026 | C15: Дивизион Конференции | D15: К работе | G15: Екатерина | H15: 3.55. День мероприятия: Меропритиятие проведено | J15: 24.09.2026 | L15: Действие | M15: Низкий | N15: N | P15: 28.04.2026 16:59:03 | S15: Екатерина | V15: N | W15: N | Y15: D, координатор, страт-п-с-26-09 | AA15: 2026-04-28 16:59:03: Екатерина создал(-а) задачу; 2026-04-29 11:27:51: Екатерина изменил(-а) дату на 25.09.2026; 2026-04-29 11:27:54: Екатерина изменил(-а) дату на 24.09.2026 - 25.09.2026; 2026-04-29 11:27:56: Екатерина изменил(-а) дату на 24.09.2026; 2026-04-29 13:21:32: Екатерина добавил(-а) тег D; 2026-04-29 13:21:52: Екатерина добавил(-а) тег координатор; 2026-04-29 13:21:54: Екатерина добавил(-а) тег страт-п-с-26-09; 2026-04-29 15:53:22: Екатерина изменил(-а) название на 3.56. День мероприятия: Меропритиятие проведено; 2026-04-30 10:43:10: Екатерина изменил(-а) название на 3.55. День мероприятия: Меропритиятие проведено | AB15: Лично сентябрь 2026 | AC15: =VLOOKUP(Y15,'впр данные'!A:B,2,1) -> координатор, страт-п-с-26-09 | AD15: =VLOOKUP(Y15,'впр данные'!A:C,3,1) -> координатор
A16: 421 | B16: ЛИЧНО сентябрь 24.09.2026 | C16: Дивизион Конференции | D16: К работе | G16: Екатерина | H16: 3.54. День монтажа: площадка подготовлена: заезд, накрытие зала, накрытие регистрации, заезд и контроль подрядчиков: питание, оборудование, полиграфия и т.д. | J16: 23.09.2026 | L16: Действие | M16: Низкий | N16: N | P16: 28.04.2026 16:58:51 | S16: Екатерина | V16: N | W16: N | Y16: D, координатор, страт-п-с-26-09 | AA16: 2026-04-28 16:58:51: Екатерина создал(-а) задачу; 2026-04-29 11:10:53: Екатерина добавил(-а) тег D; 2026-04-29 11:27:41: Екатерина изменил(-а) дату на 20.09.2026; 2026-04-29 11:27:44: Екатерина изменил(-а) дату на 20.09.2026 - 23.09.2026; 2026-04-29 11:27:49: Екатерина изменил(-а) дату на 23.09.2026; 2026-04-29 13:21:44: Екатерина добавил(-а) тег координатор; 2026-04-29 13:21:46: Екатерина добавил(-а) тег страт-п-с-26-09; 2026-04-29 15:53:17: Екатерина изменил(-а) название на 3.55. День монтажа: площадка подготовлена: заезд, накрытие зала, накрытие регистрации, заезд и контроль подрядчиков: питание, оборудование, полиграфия и т.д.; 2026-04-30 10:43:06: Екатерина изменил(-а) название на 3.54. День монтажа: площадка подготовлена: заезд, накрытие зала, накрытие регистрации, заезд и контроль подрядчиков: питание, оборудование, полиграфия и т.д. | AB16: Лично сентябрь 2026 | AC16: =VLOOKUP(Y16,'впр данные'!A:B,2,1) -> координатор, страт-п-с-26-09 | AD16: =VLOOKUP(Y16,'впр данные'!A:C,3,1) -> координатор
A17: 420 | B17: ЛИЧНО сентябрь 24.09.2026 | C17: Дивизион Конференции | D17: К работе | G17: Екатерина | H17: 3.53. Произведена проверка битрикса-списка участников с бухреестром | I17: 14.09.2026 03:00 | J17: 17.09.2026 | L17: Действие | M17: Низкий | N17: N | P17: 28.04.2026 16:58:37 | S17: Екатерина | V17: N | W17: N | Y17: PRO, координатор, страт-п-с-26-09 | AA17: 2026-04-28 16:58:37: Екатерина создал(-а) задачу; 2026-04-29 11:26:30: Екатерина изменил(-а) дату на 14.09.2026; 2026-04-29 11:26:31: Екатерина изменил(-а) дату на 13.09.2026 - 14.09.2026; 2026-04-29 11:26:36: Екатерина изменил(-а) дату на 13.09.2026 - 16.09.2026; 2026-04-29 11:26:39: Екатерина изменил(-а) дату на 14.09.2026 - 16.09.2026; 2026-04-29 11:26:41: Екатерина изменил(-а) дату на 14.09.2026 - 17.09.2026; 2026-04-29 13:21:21: Екатерина добавил(-а) тег PRO; 2026-04-29 13:21:23: Екатерина добавил(-а) тег координатор; 2026-04-29 13:21:25: Екатерина добавил(-а) тег страт-п-с-26-09; 2026-04-29 15:53:09: Екатерина изменил(-а) название на 3.54. Произведена проверка битрикса-списка участников с бухреестром; 2026-04-30 10:43:00: Екатерина изменил(-а) название на 3.53. Произведена проверка битрикса-списка участников с бухреестром | AB17: Лично сентябрь 2026 | AC17: =VLOOKUP(Y17,'впр данные'!A:B,2,1) -> координатор, страт-п-с-26-09 | AD17: =VLOOKUP(Y17,'впр данные'!A:C,3,1) -> координатор
A18: 419 | B18: ЛИЧНО сентябрь 24.09.2026 | C18: Дивизион Конференции | D18: К работе | G18: Екатерина | H18: 3.52. Куплены подарки спикерам при необходимости | I18: 14.09.2026 03:00 | J18: 17.09.2026 | L18: Действие | M18: Низкий | N18: N | P18: 28.04.2026 16:58:26 | S18: Екатерина | V18: N | W18: N | Y18: PRO, координатор, страт-п-с-26-09 | AA18: 2026-04-28 16:58:27: Екатерина создал(-а) задачу; 2026-04-29 11:27:27: Екатерина изменил(-а) дату на 15.09.2026; 2026-04-29 11:27:29: Екатерина изменил(-а) дату на 14.09.2026 - 15.09.2026; 2026-04-29 11:27:32: Екатерина изменил(-а) дату на 14.09.2026 - 17.09.2026; 2026-04-29 13:21:14: Екатерина добавил(-а) тег PRO; 2026-04-29 13:21:17: Екатерина добавил(-а) тег координатор; 2026-04-29 13:21:18: Екатерина добавил(-а) тег страт-п-с-26-09; 2026-04-29 15:16:38: Екатерина изменил(-а) название на 3.53. Куплены подарки спикерам при необходимости; 2026-04-30 10:42:56: Екатерина изменил(-а) название на 3.52. Куплены подарки спикерам при необходимости | AB18: Лично сентябрь 2026 | AC18: =VLOOKUP(Y18,'впр данные'!A:B,2,1) -> координатор, страт-п-с-26-09 | AD18: =VLOOKUP(Y18,'впр данные'!A:C,3,1) -> координатор
A19: 418 | B19: ЛИЧНО сентябрь 24.09.2026 | C19: Дивизион Конференции | D19: К работе | G19: Екатерина | H19: 3.51. Получены деньги подотчет для мероприятия | I19: 14.09.2026 03:00 | J19: 17.09.2026 | L19: Действие | M19: Низкий | N19: N | P19: 28.04.2026 16:58:14 | S19: Екатерина | V19: N | W19: N | Y19: PRO, координатор, страт-п-с-26-09 | AA19: 2026-04-28 16:58:14: Екатерина создал(-а) задачу; 2026-04-29 11:27:23: Екатерина изменил(-а) дату на 15.09.2026; 2026-04-29 11:27:25: Екатерина изменил(-а) дату на 14.09.2026 - 15.09.2026; 2026-04-29 11:27:26: Екатерина изменил(-а) дату на 14.09.2026 - 17.09.2026; 2026-04-29 13:21:06: Екатерина добавил(-а) тег PRO; 2026-04-29 13:21:09: Екатерина добавил(-а) тег координатор; 2026-04-29 13:21:10: Екатерина добавил(-а) тег страт-п-с-26-09; 2026-04-29 15:16:35: Екатерина изменил(-а) название на 3.52. Получены деньги подотчет для мероприятия; 2026-04-30 10:42:52: Екатерина изменил(-а) название на 3.51. Получены деньги подотчет для мероприятия | AB19: Лично сентябрь 2026 | AC19: =VLOOKUP(Y19,'впр данные'!A:B,2,1) -> координатор, страт-п-с-26-09 | AD19: =VLOOKUP(Y19,'впр данные'!A:C,3,1) -> координатор
A20: 417 | B20: ЛИЧНО сентябрь 24.09.2026 | C20: Дивизион Конференции | D20: К работе | G20: Екатерина | H20: 3.50. На площадку сдана вся информация: рассадка, расстановка, списки, машины, картинки, тайминг и т.д. | I20: 14.09.2026 03:00 | J20: 17.09.2026 | L20: Действие | M20: Низкий | N20: N | P20: 28.04.2026 16:58:02 | S20: Екатерина | V20: N | W20: N | Y20: PRO, координатор, страт-п-с-26-09 | AA20: 2026-04-28 16:58:02: Екатерина создал(-а) задачу; 2026-04-29 11:27:20: Екатерина изменил(-а) дату на 15.09.2026; 2026-04-29 11:27:21: Екатерина изменил(-а) дату на 14.09.2026 - 15.09.2026; 2026-04-29 11:27:22: Екатерина изменил(-а) дату на 14.09.2026 - 17.09.2026; 2026-04-29 13:20:59: Екатерина добавил(-а) тег PRO; 2026-04-29 13:21:03: Екатерина добавил(-а) тег координатор; 2026-04-29 13:21:03: Екатерина добавил(-а) тег страт-п-с-26-09; 2026-04-29 15:16:32: Екатерина изменил(-а) название на 3.51. На площадку сдана вся информация: рассадка, расстановка, списки, машины, картинки, тайминг и т.д.; 2026-04-30 10:42:49: Екатерина изменил(-а) название на 3.50. На площадку сдана вся информация: рассадка, расстановка, списки, машины, картинки, тайминг и т.д. | AB20: Лично сентябрь 2026 | AC20: =VLOOKUP(Y20,'впр данные'!A:B,2,1) -> координатор, страт-п-с-26-09 | AD20: =VLOOKUP(Y20,'впр данные'!A:C,3,1) -> координатор
A21: 416 | B21: ЛИЧНО сентябрь 24.09.2026 | C21: Дивизион Конференции | D21: К работе | G21: Екатерина | H21: 3.49. Получено подтверждение по доставке и заезду | I21: 14.09.2026 03:00 | J21: 17.09.2026 | L21: Действие | M21: Низкий | N21: N | P21: 28.04.2026 16:57:50 | S21: Екатерина | V21: N | W21: N | Y21: PRO, координатор, страт-п-с-26-09 | AA21: 2026-04-28 16:57:51: Екатерина создал(-а) задачу; 2026-04-29 11:27:15: Екатерина изменил(-а) дату на 15.09.2026; 2026-04-29 11:27:16: Екатерина изменил(-а) дату на 14.09.2026 - 15.09.2026; 2026-04-29 11:27:18: Екатерина изменил(-а) дату на 14.09.2026 - 17.09.2026; 2026-04-29 13:20:52: Екатерина добавил(-а) тег PRO; 2026-04-29 13:20:55: Екатерина добавил(-а) тег координатор; 2026-04-29 13:20:56: Екатерина добавил(-а) тег страт-п-с-26-09; 2026-04-29 15:16:24: Екатерина изменил(-а) название на 3.50. Получено подтверждение по доставке и заезду; 2026-04-30 10:42:46: Екатерина изменил(-а) название на 3.49. Получено подтверждение по доставке и заезду | AB21: Лично сентябрь 2026 | AC21: =VLOOKUP(Y21,'впр данные'!A:B,2,1) -> координатор, страт-п-с-26-09 | AD21: =VLOOKUP(Y21,'впр данные'!A:C,3,1) -> координатор
A22: 415 | B22: ЛИЧНО сентябрь 24.09.2026 | C22: Дивизион Конференции | D22: К работе | G22: Екатерина | H22: 3.48. Рабочая тетрадь, оформление сдано в типографию | I22: 14.09.2026 03:00 | J22: 17.09.2026 | L22: Действие | M22: Низкий | N22: N | P22: 28.04.2026 16:57:41 | S22: Екатерина | V22: N | W22: N | Y22: PRO, координатор, страт-п-с-26-09 | AA22: 2026-04-28 16:57:41: Екатерина создал(-а) задачу; 2026-04-29 11:27:08: Екатерина изменил(-а) дату на 15.09.2026; 2026-04-29 11:27:10: Екатерина изменил(-а) дату на 14.09.2026 - 15.09.2026; 2026-04-29 11:27:11: Екатерина изменил(-а) дату на 14.09.2026 - 17.09.2026; 2026-04-29 13:19:58: Екатерина добавил(-а) тег PRO; 2026-04-29 13:20:02: Екатерина добавил(-а) тег координатор; 2026-04-29 13:20:03: Екатерина добавил(-а) тег страт-п-с-26-09; 2026-04-29 15:16:17: Екатерина изменил(-а) название на 3.49. Рабочая тетрадь, оформление сдано в типографию; 2026-04-30 10:42:39: Екатерина изменил(-а) название на 3.48. Рабочая тетрадь, оформление сдано в типографию | AB22: Лично сентябрь 2026 | AC22: =VLOOKUP(Y22,'впр данные'!A:B,2,1) -> координатор, страт-п-с-26-09 | AD22: =VLOOKUP(Y22,'впр данные'!A:C,3,1) -> координатор
A23: 414 | B23: ЛИЧНО сентябрь 24.09.2026 | C23: Дивизион Конференции | D23: К работе | G23: Екатерина | H23: 3.47. Проведена совещание-распределение с рабочей группой, кто едет на меропритие | I23: 14.09.2026 03:00 | J23: 17.09.2026 | L23: Действие | M23: Низкий | N23: N | P23: 28.04.2026 16:57:27 | S23: Екатерина | V23: N | W23: N | Y23: PRO, координатор, страт-п-с-26-09 | AA23: 2026-04-28 16:57:28: Екатерина создал(-а) задачу; 2026-04-29 11:27:04: Екатерина изменил(-а) дату на 15.09.2026; 2026-04-29 11:27:05: Екатерина изменил(-а) дату на 14.09.2026 - 15.09.2026; 2026-04-29 11:27:07: Екатерина изменил(-а) дату на 14.09.2026 - 17.09.2026; 2026-04-29 13:19:50: Екатерина добавил(-а) тег PRO; 2026-04-29 13:19:55: Екатерина добавил(-а) тег координатор; 2026-04-29 13:19:55: Екатерина добавил(-а) тег страт-п-с-26-09; 2026-04-29 15:16:12: Екатерина изменил(-а) название на 3.48. Проведена совещание-распределение с рабочей группой, кто едет на меропритие; 2026-04-30 10:42:36: Екатерина изменил(-а) название на 3.47. Проведена совещание-распределение с рабочей группой, кто едет на меропритие | AB23: Лично сентябрь 2026 | AC23: =VLOOKUP(Y23,'впр данные'!A:B,2,1) -> координатор, страт-п-с-26-09 | AD23: =VLOOKUP(Y23,'впр данные'!A:C,3,1) -> координатор
A24: 413 | B24: ЛИЧНО сентябрь 24.09.2026 | C24: Дивизион Конференции | D24: К работе | G24: Екатерина | H24: 3.46. Сформирована папка координатора | I24: 14.09.2026 03:00 | J24: 17.09.2026 | L24: Действие | M24: Низкий | N24: N | P24: 28.04.2026 16:57:16 | S24: Екатерина | V24: N | W24: N | Y24: PRO, координатор, страт-п-с-26-09 | AA24: 2026-04-28 16:57:16: Екатерина создал(-а) задачу; 2026-04-29 11:26:59: Екатерина изменил(-а) дату на 15.09.2026; 2026-04-29 11:27:01: Екатерина изменил(-а) дату на 14.09.2026 - 15.09.2026; 2026-04-29 11:27:02: Екатерина изменил(-а) дату на 14.09.2026 - 17.09.2026; 2026-04-29 13:19:43: Екатерина добавил(-а) тег PRO; 2026-04-29 13:19:47: Екатерина добавил(-а) тег координатор; 2026-04-29 13:19:47: Екатерина добавил(-а) тег страт-п-с-26-09; 2026-04-29 15:16:08: Екатерина изменил(-а) название на 3.47. Сформирована папка координатора; 2026-04-30 10:42:33: Екатерина изменил(-а) название на 3.46. Сформирована папка координатора | AB24: Лично сентябрь 2026 | AC24: =VLOOKUP(Y24,'впр данные'!A:B,2,1) -> координатор, страт-п-с-26-09 | AD24: =VLOOKUP(Y24,'впр данные'!A:C,3,1) -> координатор
A25: 412 | B25: ЛИЧНО сентябрь 24.09.2026 | C25: Дивизион Конференции | D25: К работе | G25: Екатерина | H25: 3.45. Сформирована папка участников мероприятия: бейджи, бух документы | I25: 14.09.2026 03:00 | J25: 17.09.2026 | L25: Действие | M25: Низкий | N25: N | P25: 28.04.2026 16:57:03 | S25: Екатерина | V25: N | W25: N | Y25: PRO, координатор, страт-п-с-26-09 | AA25: 2026-04-28 16:57:04: Екатерина создал(-а) задачу; 2026-04-29 11:26:53: Екатерина изменил(-а) дату на 15.09.2026; 2026-04-29 11:26:55: Екатерина изменил(-а) дату на 14.09.2026 - 15.09.2026; 2026-04-29 11:26:57: Екатерина изменил(-а) дату на 14.09.2026 - 17.09.2026; 2026-04-29 13:19:36: Екатерина добавил(-а) тег PRO; 2026-04-29 13:19:38: Екатерина добавил(-а) тег координатор; 2026-04-29 13:19:40: Екатерина добавил(-а) тег страт-п-с-26-09; 2026-04-29 15:16:03: Екатерина изменил(-а) название на 3.46. Сформирована папка участников мероприятия: бейджи, бух документы; 2026-04-30 10:42:28: Екатерина изменил(-а) название на 3.45. Сформирована папка участников мероприятия: бейджи, бух документы | AB25: Лично сентябрь 2026 | AC25: =VLOOKUP(Y25,'впр данные'!A:B,2,1) -> координатор, страт-п-с-26-09 | AD25: =VLOOKUP(Y25,'впр данные'!A:C,3,1) -> координатор
A26: 411 | B26: ЛИЧНО сентябрь 24.09.2026 | C26: Дивизион Конференции | D26: К работе | G26: Екатерина | H26: 3.44. Памятки отправлены всем | I26: 14.09.2026 03:00 | J26: 17.09.2026 | L26: Действие | M26: Низкий | N26: N | P26: 28.04.2026 16:56:52 | S26: Екатерина | V26: N | W26: N | Y26: PRO, координатор, страт-п-с-26-09 | AA26: 2026-04-28 16:56:52: Екатерина создал(-а) задачу; 2026-04-29 11:26:49: Екатерина изменил(-а) дату на 15.09.2026; 2026-04-29 11:26:50: Екатерина изменил(-а) дату на 14.09.2026 - 15.09.2026; 2026-04-29 11:26:52: Екатерина изменил(-а) дату на 14.09.2026 - 17.09.2026; 2026-04-29 13:19:29: Екатерина добавил(-а) тег PRO; 2026-04-29 13:19:32: Екатерина добавил(-а) тег координатор; 2026-04-29 13:19:33: Екатерина добавил(-а) тег страт-п-с-26-09; 2026-04-29 15:15:59: Екатерина изменил(-а) название на 3.45. Памятки отправлены всем; 2026-04-30 10:42:24: Екатерина изменил(-а) название на 3.44. Памятки отправлены всем | AB26: Лично сентябрь 2026 | AC26: =VLOOKUP(Y26,'впр данные'!A:B,2,1) -> координатор, страт-п-с-26-09 | AD26: =VLOOKUP(Y26,'впр данные'!A:C,3,1) -> координатор
A27: 410 | B27: ЛИЧНО сентябрь 24.09.2026 | C27: Дивизион Конференции | D27: К работе | G27: Екатерина | H27: 3.43. Сформирован и оплачен окончательный заказ по площадке и подрядчикам, ВСЕМУ | I27: 14.09.2026 03:00 | J27: 17.09.2026 | L27: Действие | M27: Низкий | N27: N | P27: 28.04.2026 16:56:39 | S27: Екатерина | V27: N | W27: N | Y27: PRO, координатор, страт-п-с-26-09 | AA27: 2026-04-28 16:56:40: Екатерина создал(-а) задачу; 2026-04-29 11:26:43: Екатерина изменил(-а) дату на 15.09.2026; 2026-04-29 11:26:46: Екатерина изменил(-а) дату на 15.09.2026 - 17.09.2026; 2026-04-29 11:26:48: Екатерина изменил(-а) дату на 14.09.2026 - 17.09.2026; 2026-04-29 13:19:19: Екатерина добавил(-а) тег PRO; 2026-04-29 13:19:23: Екатерина добавил(-а) тег координатор; 2026-04-29 13:19:25: Екатерина добавил(-а) тег страт-п-с-26-09; 2026-04-29 15:15:56: Екатерина изменил(-а) название на 3.44. Сформирован и оплачен окончательный заказ по площадке и подрядчикам, ВСЕМУ; 2026-04-30 10:42:21: Екатерина изменил(-а) название на 3.43. Сформирован и оплачен окончательный заказ по площадке и подрядчикам, ВСЕМУ | AB27: Лично сентябрь 2026 | AC27: =VLOOKUP(Y27,'впр данные'!A:B,2,1) -> координатор, страт-п-с-26-09 | AD27: =VLOOKUP(Y27,'впр данные'!A:C,3,1) -> координатор
A28: 408 | B28: ЛИЧНО сентябрь 24.09.2026 | C28: Дивизион Конференции | D28: К работе | G28: Екатерина | H28: 3.42. Техническая подготовка завершена | I28: 14.09.2026 03:00 | J28: 17.09.2026 | L28: Действие | M28: Низкий | N28: N | P28: 28.04.2026 16:56:20 | S28: Екатерина | V28: N | W28: N | Y28: PRO, координатор, страт-п-с-26-09 | AA28: 2026-04-28 16:56:20: Екатерина создал(-а) задачу; 2026-04-29 11:25:28: Екатерина изменил(-а) дату на 08.09.2026; 2026-04-29 11:25:37: Екатерина изменил(-а) дату на 08.09.2026 - 19.09.2026; 2026-04-29 11:25:46: Екатерина изменил(-а) дату на 19.09.2026; 2026-04-29 11:25:56: Екатерина изменил(-а) дату на 19.09.2026 - 22.09.2026; 2026-04-29 11:26:12: Екатерина изменил(-а) дату на 14.09.2026 - 22.09.2026; 2026-04-29 11:26:16: Екатерина изменил(-а) дату на 14.09.2026 - 17.09.2026; 2026-04-29 13:19:03: Екатерина добавил(-а) тег PRO; 2026-04-29 13:19:06: Екатерина добавил(-а) тег координатор; 2026-04-29 13:19:07: Екатерина добавил(-а) тег страт-п-с-26-09; 2026-04-29 15:15:49: Екатерина изменил(-а) название на 3.42. Техническая подготовка завершена | AB28: Лично сентябрь 2026 | AC28: =VLOOKUP(Y28,'впр данные'!A:B,2,1) -> координатор, страт-п-с-26-09 | AD28: =VLOOKUP(Y28,'впр данные'!A:C,3,1) -> координатор
... A110: 308 | B110: ЛИЧНО сентябрь 24.09.2026 | C110: Дивизион Конференции | D110: К работе | G110: Екатерина | H110: 2.06. Провести 40% глубинных интервью | I110: 01.06.2026 03:00 | J110: 04.06.2026 | L110: Действие | M110: Низкий | N110: N | P110: 28.04.2026 16:13:47 | S110: Екатерина | V110: N | W110: N | Y110: PRE, Продюсер, страт-п-с-26-09 | AA110: 2026-04-28 16:13:47: Екатерина создал(-а) задачу; 2026-04-28 17:14:48: Екатерина изменил(-а) название на 2.06. Провести 40% глубинных интервью; 2026-04-28 19:40:41: Екатерина добавил(-а) тег PRE; 2026-04-28 19:41:06: Екатерина добавил(-а) тег Продюсер; 2026-04-28 19:41:09: Екатерина добавил(-а) тег страт-п-с-26-09; 2026-04-28 19:46:16: Екатерина изменил(-а) дату на 04.06.2026 - 04.06.2026; 2026-04-28 19:46:16: Екатерина изменил(-а) дату на 01.06.2026 - 01.06.2026; 2026-04-28 19:46:32: Екатерина изменил(-а) дату на 01.06.2026 - 04.06.2026; 2026-04-28 19:46:34: Екатерина изменил(-а) дату на 04.06.2026 - 04.06.2026; 2026-04-28 19:46:52: Екатерина изменил(-а) дату на 01.06.2026 - 04.06.2026; 2026-04-28 19:46:54: Екатерина изменил(-а) дату на 04.06.2026 - 04.06.2026; 2026-04-28 19:47:08: Екатерина изменил(-а) дату на 01.06.2026 - 04.06.2026; 2026-04-29 10:35:45: Екатерина добавил(-а) подзадачу #307 2.05. Провести конкурентный анализ | AB110: Лично сентябрь 2026 | AC110: =VLOOKUP(Y110,'впр данные'!A:B,2,1) -> продюсер, страт-п-с-26-09 | AD110: =VLOOKUP(Y110,'впр данные'!A:C,3,1) -> продюсер
A111: 307 | B111: ЛИЧНО сентябрь 24.09.2026 | C111: Дивизион Конференции | D111: К работе | E111: 2.06. Провести 40% глубинных интервью | F111: 2.06. Провести 40% глубинных интервью | G111: Екатерина | H111: 2.05. Провести конкурентный анализ | I111: 01.06.2026 03:00 | J111: 04.06.2026 | L111: Действие | M111: Низкий | N111: N | P111: 28.04.2026 16:13:33 | S111: Екатерина | V111: N | W111: N | Y111: PRE, Продюсер, страт-п-с-26-09 | AA111: 2026-04-28 16:13:34: Екатерина создал(-а) задачу; 2026-04-28 17:14:26: Екатерина изменил(-а) название на 2.05. Провести конкурентный анализ; 2026-04-28 19:39:56: Екатерина добавил(-а) тег PRE; 2026-04-28 19:40:47: Екатерина добавил(-а) тег Продюсер; 2026-04-28 19:40:48: Екатерина добавил(-а) тег страт-п-с-26-09; 2026-04-28 19:46:09: Екатерина изменил(-а) дату на 01.06.2026 - 01.06.2026; 2026-04-28 19:46:09: Екатерина изменил(-а) дату на 04.06.2026 - 04.06.2026; 2026-04-28 19:46:25: Екатерина изменил(-а) дату на 01.06.2026 - 04.06.2026; 2026-04-29 10:35:45: Екатерина изменил(-а) родительскую задачу на #308 2.06. Провести 40% глубинных интервью | AB111: Лично сентябрь 2026 | AC111: =VLOOKUP(Y111,'впр данные'!A:B,2,1) -> продюсер, страт-п-с-26-09 | AD111: =VLOOKUP(Y111,'впр данные'!A:C,3,1) -> продюсер
A112: 306 | B112: ЛИЧНО сентябрь 24.09.2026 | C112: Дивизион Конференции | D112: К работе | G112: Екатерина | H112: 2.04. Провести кабинетное исследование | I112: 01.06.2026 03:00 | J112: 04.06.2026 | L112: Действие | M112: Низкий | N112: N | P112: 28.04.2026 16:13:25 | S112: Екатерина | V112: N | W112: N | Y112: PRE, Продюсер, страт-п-с-26-09 | AA112: 2026-04-28 16:13:25: Екатерина создал(-а) задачу; 2026-04-28 17:14:12: Екатерина изменил(-а) название на 2.04. Провести кабинетное исследование; 2026-04-28 19:39:53: Екатерина добавил(-а) тег PRE; 2026-04-28 19:40:25: Екатерина добавил(-а) тег Продюсер; 2026-04-28 19:40:26: Екатерина добавил(-а) тег страт-п-с-26-09; 2026-04-28 19:45:54: Екатерина изменил(-а) дату на 01.06.2026; 2026-04-28 19:45:54: Екатерина изменил(-а) дату на 04.06.2026; 2026-04-28 19:46:00: Екатерина изменил(-а) дату на 01.06.2026 - 04.06.2026 | AB112: Лично сентябрь 2026 | AC112: =VLOOKUP(Y112,'впр данные'!A:B,2,1) -> продюсер, страт-п-с-26-09 | AD112: =VLOOKUP(Y112,'впр данные'!A:C,3,1) -> продюсер
A113: 305 | B113: ЛИЧНО сентябрь 24.09.2026 | C113: Дивизион Конференции | D113: К работе | G113: Екатерина | H113: 2.03. Утвердить с ШП пакеты на возможность реализации на площадке | I113: 25.05.2026 03:00 | J113: 28.05.2026 | L113: Действие | M113: Низкий | N113: N | P113: 28.04.2026 16:12:56 | S113: Екатерина | V113: N | W113: N | Y113: PRE, Продюсер, страт-п-с-26-09 | AA113: 2026-04-28 16:12:58: Екатерина создал(-а) задачу; 2026-04-28 17:13:57: Екатерина изменил(-а) название на 2.03. Утвердить с ШП пакеты на возможность реализации на площадке; 2026-04-28 19:25:13: Екатерина добавил(-а) тег PRE; 2026-04-28 19:40:04: Екатерина добавил(-а) тег Продюсер; 2026-04-28 19:40:06: Екатерина добавил(-а) тег страт-п-с-26-09; 2026-04-28 19:45:35: Екатерина изменил(-а) дату на 25.05.2026; 2026-04-28 19:45:35: Екатерина изменил(-а) дату на 25.05.2026 - 25.05.2026; 2026-04-28 19:45:38: Екатерина изменил(-а) дату на 25.05.2026 - 28.05.2026 | AB113: Лично сентябрь 2026 | AC113: =VLOOKUP(Y113,'впр данные'!A:B,2,1) -> продюсер, страт-п-с-26-09 | AD113: =VLOOKUP(Y113,'впр данные'!A:C,3,1) -> продюсер
A114: 303 | B114: ЛИЧНО сентябрь 24.09.2026 | C114: Дивизион Конференции | D114: К работе | G114: Екатерина | H114: Страт-п-с-26-09 Финиш вехи Пост | I114: 28.09.2026 03:00 | J114: 01.10.2026 | L114: Действие | M114: Низкий | N114: N | P114: 28.04.2026 16:06:48 | R114: Елена | S114: Екатерина, Елена | V114: N | W114: N | Y114: страт-п-с-26-09, Операционный директор, финиш вехи Post | AA114: 2026-04-28 16:06:49: Екатерина создал(-а) задачу; 2026-04-28 16:07:27: Екатерина добавил(-а) тег страт-п-с-26-09; 2026-04-28 16:07:31: Екатерина добавил(-а) тег Операционный директор; 2026-04-28 16:07:47: Екатерина изменил(-а) дату на 28.09.2026; 2026-04-28 16:07:49: Екатерина изменил(-а) дату на 01.10.2026; 2026-04-28 16:07:53: Екатерина изменил(-а) дату на 28.09.2026 - 01.10.2026; 2026-04-28 16:08:28: Екатерина изменил(-а) название на Финиш вехи Пост; 2026-04-28 16:31:23: Екатерина добавил(-а) тег финиш вехи Post; 2026-04-28 16:35:26: Екатерина изменил(-а) название на СтратФиниш вехи Пост; 2026-04-28 16:35:31: Екатерина изменил(-а) название на Страт-пФиниш вехи Пост; 2026-04-28 16:35:34: Екатерина изменил(-а) название на Страт-п-сФиниш вехи Пост; 2026-04-28 16:35:40: Екатерина изменил(-а) название на Страт-п-с-26Финиш вехи Пост; 2026-04-28 16:35:44: Екатерина изменил(-а) название на Страт-п-с-26-09 Финиш вехи Пост; 2026-04-28 16:35:53: Екатерина изменил(-а) название на Лично Страт-п-с-26-09 Финиш вехи Пост; 2026-04-28 16:35:54: Екатерина изменил(-а) название на Лично сенСтрат-п-с-26-09 Финиш вехи Пост; 2026-04-28 16:35:57: Екатерина изменил(-а) название на Лично сентябрь 2026 Страт-п-с-26-09 Финиш вехи Пост; 2026-04-28 16:36:10: Екатерина изменил(-а) название на Страт-п-с-26-09 Финиш вехи Пост; 2026-04-30 10:51:34: Екатерина назначил(-а) Нелли исполнителем; 2026-04-30 10:51:44: Екатерина отстранил(-а) Нелли от задачи; 2026-04-30 10:52:03: Екатерина назначил(-а) Елена исполнителем | AB114: Лично сентябрь 2026 | AC114: =VLOOKUP(Y114,'впр данные'!A:B,2,1) -> страт-п-с-26-09, ШП, финиш вехи Post | AD114: =VLOOKUP(Y114,'впр данные'!A:C,3,1) -> Операцоинный директор
A115: 302 | B115: ЛИЧНО сентябрь 24.09.2026 | C115: Дивизион Конференции | D115: К работе | G115: Екатерина | H115: Страт-п-с-26-09 Старт вехи Pro | I115: 27.07.2026 03:00 | J115: 30.07.2026 | L115: Действие | M115: Низкий | N115: N | P115: 28.04.2026 15:53:36 | R115: Елена | S115: Екатерина, Елена | V115: N | W115: N | Y115: страт-п-с-26-09, Операционный директор, старт вехи Pro | AA115: 2026-04-28 15:53:36: Екатерина создал(-а) задачу; 2026-04-28 15:53:46: Екатерина добавил(-а) тег страт-п-с-26-09; 2026-04-28 15:53:49: Екатерина добавил(-а) тег Операционный директор; 2026-04-28 15:54:27: Екатерина изменил(-а) дату на 27.07.2026; 2026-04-28 15:54:32: Екатерина изменил(-а) дату на 27.07.2026 - 27.07.2026; 2026-04-28 15:54:36: Екатерина изменил(-а) дату на 27.07.2026 - 30.07.2026; 2026-04-28 15:54:48: Екатерина изменил(-а) название на 0Старт вехи Pro; 2026-04-28 15:54:50: Екатерина изменил(-а) название на 0.Старт вехи Pro; 2026-04-28 15:54:55: Екатерина изменил(-а) название на 0.2. Старт вехи Pro; 2026-04-28 15:54:56: Екатерина изменил(-а) название на 0.2.Старт вехи Pro; 2026-04-28 15:55:33: Екатерина изменил(-а) название на 0.2. Старт вехи Pro; 2026-04-28 16:08:16: Екатерина изменил(-а) название на Старт вехи Pro; 2026-04-28 16:30:32: Екатерина добавил(-а) тег старт вехи Pro; 2026-04-28 16:31:00: Екатерина добавил(-а) тег финиш вехи Post; 2026-04-28 16:31:17: Екатерина убрал(-а) тег финиш вехи Post; 2026-04-28 16:36:29: Екатерина изменил(-а) название на Страт-п-с-26-09Старт вехи Pro; 2026-04-28 16:36:30: Екатерина изменил(-а) название на Страт-п-с-26-09 Старт вехи Pro; 2026-04-30 10:52:02: Екатерина назначил(-а) Елена исполнителем | AB115: Лично сентябрь 2026 | AC115: =VLOOKUP(Y115,'впр данные'!A:B,2,1) -> страт-п-с-26-09, ШП, старт вехи Pro | AD115: =VLOOKUP(Y115,'впр данные'!A:C,3,1) -> Операцоинный директор
A116: 301 | B116: ЛИЧНО сентябрь 24.09.2026 | C116: Дивизион Конференции | D116: К работе | G116: Екатерина | H116: Страт-п-с-26-09 Старт вехи Pre | I116: 18.05.2026 03:00 | J116: 21.05.2026 | L116: Действие | M116: Низкий | N116: N | P116: 28.04.2026 15:47:42 | R116: Елена | S116: Екатерина, Елена | V116: N | W116: N | Y116: страт-п-с-26-09, Операционный директор, Старт вехи Pre | AA116: 2026-04-28 15:47:42: Екатерина создал(-а) задачу; 2026-04-28 15:47:57: Екатерина добавил(-а) тег страт-п-с-26-09; 2026-04-28 15:47:57: Екатерина добавил(-а) тег ШП; 2026-04-28 15:48:04: Екатерина убрал(-а) тег ШП; 2026-04-28 15:48:26: Екатерина добавил(-а) тег Операционный директор; 2026-04-28 15:49:18: Екатерина изменил(-а) дату на 18.05.2026; 2026-04-28 15:49:19: Екатерина изменил(-а) дату на 21.05.2026; 2026-04-28 15:49:20: Екатерина изменил(-а) дату на 18.05.2026; 2026-04-28 15:49:23: Екатерина изменил(-а) дату на 18.05.2026 - 18.05.2026; 2026-04-28 15:49:25: Екатерина изменил(-а) дату на 18.05.2026 - 21.05.2026; 2026-04-28 15:55:20: Екатерина изменил(-а) название на 0Старт вехи Pre; 2026-04-28 15:55:22: Екатерина изменил(-а) название на 0.1.Старт вехи Pre; 2026-04-28 15:55:25: Екатерина изменил(-а) название на 0.1. Старт вехи Pre; 2026-04-28 16:07:15: Екатерина изменил(-а) название на Старт вехи Pre; 2026-04-28 16:30:13: Екатерина добавил(-а) тег Старт вехи Pre; 2026-04-28 16:36:36: Екатерина изменил(-а) название на Страт-п-с-26-09Старт вехи Pre; 2026-04-28 16:36:36: Екатерина изменил(-а) название на Страт-п-с-26-09 Старт вехи Pre; 2026-04-30 10:51:58: Екатерина назначил(-а) Елена исполнителем | AB116: Лично сентябрь 2026 | AC116: =VLOOKUP(Y116,'впр данные'!A:B,2,1) -> страт-п-с-26-09, ШП, Старт вехи Pre | AD116: =VLOOKUP(Y116,'впр данные'!A:C,3,1) -> Операцоинный директор
A117: 300 | B117: ЛИЧНО сентябрь 24.09.2026 | E117: 2.01. Провести Презентацию проекта на Первичном совещании | F117: 2.01. Провести Презентацию проекта на Первичном совещании | G117: Екатерина | H117: 2.1.10. Произвести сверку наличия брони по площадке - сверяем с годовым планом по бронированию мест проведения | I117: 18.05.2026 03:00 | J117: 19.05.2026 | L117: Действие | M117: Низкий | N117: N | P117: 28.04.2026 15:43:55 | S117: Екатерина | V117: N | W117: N | AA117: 2026-04-28 15:43:55: Екатерина создал(-а) задачу; 2026-04-28 19:36:07: Екатерина изменил(-а) дату на 18.05.2026 - 18.05.2026; 2026-04-28 19:36:10: Екатерина изменил(-а) дату на 18.05.2026 - 19.05.2026; 2026-04-28 19:38:53: Екатерина добавил(-а) задачу в проект ЛИЧНО сентябрь 24.09.2026 | AB117: Лично сентябрь 2026 | AC117: =VLOOKUP(Y117,'впр данные'!A:B,2,1) -> #N/A | AD117: =VLOOKUP(Y117,'впр данные'!A:C,3,1) -> #N/A
A118: 299 | B118: ЛИЧНО сентябрь 24.09.2026 | E118: 2.01. Провести Презентацию проекта на Первичном совещании | F118: 2.01. Провести Презентацию проекта на Первичном совещании | G118: Екатерина | H118: 2.1.9. Просмотреть Маркетинговый отчет подготовленный лидгеном (включающий отчет по источникам и каналам и отчет по отказам), даны комментарии по подготовке списка каналов | I118: 18.05.2026 03:00 | J118: 19.05.2026 | L118: Действие | M118: Низкий | N118: N | P118: 28.04.2026 15:43:45 | S118: Екатерина | V118: N | W118: N | AA118: 2026-04-28 15:43:45: Екатерина создал(-а) задачу; 2026-04-28 19:35:55: Екатерина изменил(-а) дату на 18.05.2026; 2026-04-28 19:35:58: Екатерина изменил(-а) дату на 18.05.2026 - 18.05.2026; 2026-04-28 19:36:01: Екатерина изменил(-а) дату на 18.05.2026 - 19.05.2026; 2026-04-28 19:38:48: Екатерина добавил(-а) задачу в проект ЛИЧНО сентябрь 24.09.2026 | AB118: Лично сентябрь 2026 | AC118: =VLOOKUP(Y118,'впр данные'!A:B,2,1) -> #N/A | AD118: =VLOOKUP(Y118,'впр данные'!A:C,3,1) -> #N/A
A119: 298 | B119: ЛИЧНО сентябрь 24.09.2026 | E119: 2.01. Провести Презентацию проекта на Первичном совещании | F119: 2.01. Провести Презентацию проекта на Первичном совещании | G119: Екатерина | H119: 2.1.8. Проанализированы косяки предыдущего мероприятия | I119: 18.05.2026 03:00 | J119: 19.05.2026 | L119: Действие | M119: Низкий | N119: N | P119: 28.04.2026 15:43:34 | S119: Екатерина | V119: N | W119: N | AA119: 2026-04-28 15:43:34: Екатерина создал(-а) задачу; 2026-04-28 19:35:39: Екатерина изменил(-а) дату на 18.05.2026; 2026-04-28 19:35:43: Екатерина изменил(-а) дату на 18.05.2026 - 18.05.2026; 2026-04-28 19:35:46: Екатерина изменил(-а) дату на 18.05.2026 - 19.05.2026; 2026-04-28 19:38:44: Екатерина добавил(-а) задачу в проект ЛИЧНО сентябрь 24.09.2026 | AB119: Лично сентябрь 2026 | AC119: =VLOOKUP(Y119,'впр данные'!A:B,2,1) -> #N/A | AD119: =VLOOKUP(Y119,'впр данные'!A:C,3,1) -> #N/A
A120: 297 | B120: ЛИЧНО сентябрь 24.09.2026 | E120: 2.01. Провести Презентацию проекта на Первичном совещании | F120: 2.01. Провести Презентацию проекта на Первичном совещании | G120: Екатерина | H120: 2.1.7. Протокол совещания подписать с шеф-продюсером и положить в специальную папку, обозначенную именем проекта и годом проведения | I120: 18.05.2026 03:00 | J120: 19.05.2026 | L120: Действие | M120: Низкий | N120: N | P120: 28.04.2026 15:43:23 | S120: Екатерина | V120: N | W120: N | AA120: 2026-04-28 15:43:23: Екатерина создал(-а) задачу; 2026-04-28 19:33:52: Екатерина изменил(-а) дату на 18.05.2026; 2026-04-28 19:33:54: Екатерина изменил(-а) дату на 19.05.2026; 2026-04-28 19:33:56: Екатерина изменил(-а) дату на 18.05.2026 - 19.05.2026; 2026-04-28 19:38:40: Екатерина добавил(-а) задачу в проект ЛИЧНО сентябрь 24.09.2026 | AB120: Лично сентябрь 2026 | AC120: =VLOOKUP(Y120,'впр данные'!A:B,2,1) -> #N/A | AD120: =VLOOKUP(Y120,'впр данные'!A:C,3,1) -> #N/A
A121: 296 | B121: ЛИЧНО сентябрь 24.09.2026 | E121: 2.01. Провести Презентацию проекта на Первичном совещании | F121: 2.01. Провести Презентацию проекта на Первичном совещании | G121: Екатерина | H121: 2.1.6. Сформировать Протокол совещания, в котором подитожены все предыдущие пункты | I121: 18.05.2026 03:00 | J121: 19.05.2026 | L121: Действие | M121: Низкий | N121: N | P121: 28.04.2026 15:43:04 | S121: Екатерина | V121: N | W121: N | AA121: 2026-04-28 15:43:05: Екатерина создал(-а) задачу; 2026-04-28 19:33:27: Екатерина изменил(-а) дату на 18.05.2026; 2026-04-28 19:33:30: Екатерина изменил(-а) дату на 18.05.2026 - 18.05.2026; 2026-04-28 19:33:32: Екатерина изменил(-а) дату на 18.05.2026 - 19.05.2026; 2026-04-28 19:33:37: Екатерина изменил(-а) дату на 19.05.2026 - 19.05.2026; 2026-04-28 19:33:42: Екатерина изменил(-а) дату на 18.05.2026 - 19.05.2026; 2026-04-28 19:38:33: Екатерина добавил(-а) задачу в проект ЛИЧНО сентябрь 24.09.2026 | AB121: Лично сентябрь 2026 | AC121: =VLOOKUP(Y121,'впр данные'!A:B,2,1) -> #N/A | AD121: =VLOOKUP(Y121,'впр данные'!A:C,3,1) -> #N/A
A122: 295 | B122: ЛИЧНО сентябрь 24.09.2026 | E122: 2.01. Провести Презентацию проекта на Первичном совещании | F122: 2.01. Провести Презентацию проекта на Первичном совещании | G122: Екатерина | H122: 2.1.5. Определить Целевую аудитория мероприятия | I122: 18.05.2026 03:00 | J122: 19.05.2026 | L122: Действие | M122: Низкий | N122: N | P122: 28.04.2026 15:42:48 | S122: Екатерина | V122: N | W122: N | AA122: 2026-04-28 15:42:48: Екатерина создал(-а) задачу; 2026-04-28 19:33:02: Екатерина изменил(-а) дату на 18.05.2026; 2026-04-28 19:33:04: Екатерина изменил(-а) дату на 19.05.2026; 2026-04-28 19:33:05: Екатерина изменил(-а) дату на 18.05.2026; 2026-04-28 19:33:08: Екатерина изменил(-а) дату на 18.05.2026 - 18.05.2026; 2026-04-28 19:33:09: Екатерина изменил(-а) дату на 18.05.2026 - 19.05.2026; 2026-04-28 19:38:30: Екатерина добавил(-а) задачу в проект ЛИЧНО сентябрь 24.09.2026 | AB122: Лично сентябрь 2026 | AC122: =VLOOKUP(Y122,'впр данные'!A:B,2,1) -> #N/A | AD122: =VLOOKUP(Y122,'впр данные'!A:C,3,1) -> #N/A
A123: 294 | B123: ЛИЧНО сентябрь 24.09.2026 | E123: 2.01. Провести Презентацию проекта на Первичном совещании | F123: 2.01. Провести Презентацию проекта на Первичном совещании | G123: Екатерина | H123: 2.1.4. Провести Первичное совещание и зафиксировать 7 вводных по проекту согласно методичке продюсера : Название заказчика, Название мероприятия, дата, время и место проведения мероприятия, Количество человек-участников (включая бесплатных участников | I123: 18.05.2026 03:00 | J123: 19.05.2026 | L123: Действие | M123: Низкий | N123: N | P123: 28.04.2026 15:42:34 | S123: Екатерина | V123: N | W123: N | AA123: 2026-04-28 15:42:34: Екатерина создал(-а) задачу; 2026-04-28 19:32:47: Екатерина изменил(-а) дату на 18.05.2026; 2026-04-28 19:32:50: Екатерина изменил(-а) дату на 18.05.2026 - 18.05.2026; 2026-04-28 19:32:53: Екатерина изменил(-а) дату на 18.05.2026 - 19.05.2026; 2026-04-28 19:38:27: Екатерина добавил(-а) задачу в проект ЛИЧНО сентябрь 24.09.2026 | AB123: Лично сентябрь 2026 | AC123: =VLOOKUP(Y123,'впр данные'!A:B,2,1) -> #N/A | AD123: =VLOOKUP(Y123,'впр данные'!A:C,3,1) -> #N/A
A124: 293 | B124: ЛИЧНО сентябрь 24.09.2026 | E124: 2.01. Провести Презентацию проекта на Первичном совещании | F124: 2.01. Провести Презентацию проекта на Первичном совещании | G124: Екатерина | H124: 2.1.3. Согласовать дату совещания с участниками | I124: 18.05.2026 03:00 | J124: 19.05.2026 | L124: Действие | M124: Низкий | N124: N | P124: 28.04.2026 15:41:50 | S124: Екатерина | V124: N | W124: N | AA124: 2026-04-28 15:41:50: Екатерина создал(-а) задачу; 2026-04-28 19:24:09: Екатерина изменил(-а) дату на 18.05.2026; 2026-04-28 19:24:09: Екатерина изменил(-а) дату на 19.05.2026; 2026-04-28 19:24:13: Екатерина изменил(-а) дату на 18.05.2026 - 19.05.2026; 2026-04-28 19:38:23: Екатерина добавил(-а) задачу в проект ЛИЧНО сентябрь 24.09.2026; 2026-04-28 19:39:11: Екатерина переместил(-а) задачу в проекте ЛИЧНО сентябрь 24.09.2026 в колонку Дивизион Конференции / К работе; 2026-04-28 19:39:25: Екатерина снял(-а) задачу с доски в проекте ЛИЧНО сентябрь 24.09.2026 | AB124: Лично сентябрь 2026 | AC124: =VLOOKUP(Y124,'впр данные'!A:B,2,1) -> #N/A | AD124: =VLOOKUP(Y124,'впр данные'!A:C,3,1) -> #N/A
A125: 292 | B125: ЛИЧНО сентябрь 24.09.2026 | E125: 2.01. Провести Презентацию проекта на Первичном совещании | F125: 2.01. Провести Презентацию проекта на Первичном совещании | G125: Екатерина | H125: 2.1.2. Назначить дату совещания | I125: 18.05.2026 03:00 | J125: 19.05.2026 | L125: Действие | M125: Низкий | N125: N | P125: 28.04.2026 15:41:43 | S125: Екатерина | V125: N | W125: N | AA125: 2026-04-28 15:41:43: Екатерина создал(-а) задачу; 2026-04-28 16:28:32: Екатерина изменил(-а) дату на 20.06.2026; 2026-04-28 19:23:17: Екатерина изменил(-а) дату на 18.05.2026; 2026-04-28 19:23:20: Екатерина изменил(-а) дату на 18.05.2026 - 18.05.2026; 2026-04-28 19:23:22: Екатерина изменил(-а) дату на 18.05.2026 - 19.05.2026; 2026-04-28 19:38:17: Екатерина добавил(-а) задачу в проект ЛИЧНО сентябрь 24.09.2026; 2026-04-28 19:39:08: Екатерина переместил(-а) задачу в проекте ЛИЧНО сентябрь 24.09.2026 в колонку Дивизион Конференции / К работе; 2026-04-28 19:39:22: Екатерина снял(-а) задачу с доски в проекте ЛИЧНО сентябрь 24.09.2026 | AB125: Лично сентябрь 2026 | AC125: =VLOOKUP(Y125,'впр данные'!A:B,2,1) -> #N/A | AD125: =VLOOKUP(Y125,'впр данные'!A:C,3,1) -> #N/A
A126: 291 | B126: ЛИЧНО сентябрь 24.09.2026 | E126: 2.01. Провести Презентацию проекта на Первичном совещании | F126: 2.01. Провести Презентацию проекта на Первичном совещании | G126: Екатерина | H126: 0/10 2.1.1. Определить состав участников Совещания в зависимости от нового/старого формата - согласно инструкции, описанной в Методичке (от лидгена Рук и лидген) | I126: 18.05.2026 03:00 | J126: 19.05.2026 | L126: Действие | M126: Низкий | N126: N | P126: 28.04.2026 15:41:35 | S126: Екатерина | V126: N | W126: N | AA126: 2026-04-28 15:41:35: Екатерина создал(-а) задачу; 2026-04-28 19:22:57: Екатерина изменил(-а) дату на 19.05.2026; 2026-04-28 19:22:57: Екатерина изменил(-а) дату на 18.05.2026; 2026-04-28 19:23:00: Екатерина изменил(-а) дату на 18.05.2026 - 18.05.2026; 2026-04-28 19:23:02: Екатерина изменил(-а) дату на 18.05.2026 - 19.05.2026; 2026-04-28 19:38:14: Екатерина добавил(-а) задачу в проект ЛИЧНО сентябрь 24.09.2026; 2026-04-28 19:39:05: Екатерина переместил(-а) задачу в проекте ЛИЧНО сентябрь 24.09.2026 в колонку Дивизион Конференции / К работе; 2026-04-28 19:39:19: Екатерина снял(-а) задачу с доски в проекте ЛИЧНО сентябрь 24.09.2026 | AB126: Лично сентябрь 2026 | AC126: =VLOOKUP(Y126,'впр данные'!A:B,2,1) -> #N/A | AD126: =VLOOKUP(Y126,'впр данные'!A:C,3,1) -> #N/A
A127: 290 | B127: ЛИЧНО сентябрь 24.09.2026 | C127: Дивизион Конференции | D127: К работе | G127: Екатерина | H127: 2.01. Провести Презентацию проекта на Первичном совещании | I127: 18.05.2026 03:00 | J127: 19.05.2026 | L127: Действие | M127: Низкий | N127: N | P127: 28.04.2026 15:40:18 | S127: Екатерина | V127: N | W127: N | Y127: PRE, Продюсер, страт-п-с-26-09 | AA127: 2026-04-28 15:40:19: Екатерина создал(-а) задачу; 2026-04-28 15:41:35: Екатерина добавил(-а) подзадачу #291 0/10 2.1.1. Определить состав участников Совещания в зависимости от нового/старого формата - согласно инструкции, описанной в Методичке (от лидгена Рук и лидген); 2026-04-28 15:41:43: Екатерина добавил(-а) подзадачу #292 2.1.2. Назначить дату совещания; 2026-04-28 15:41:50: Екатерина добавил(-а) подзадачу #293 2.1.3. Согласовать дату совещания с участниками; 2026-04-28 15:42:34: Екатерина добавил(-а) подзадачу #294 2.1.4. Провести Первичное совещание и зафиксировать 7 вводных по проекту согласно методичке продюсера : Название заказчика, Название мероприятия, дата, время и место проведения мероприятия, Количество человек-участников (включая бесплатных участников; 2026-04-28 15:42:48: Екатерина добавил(-а) подзадачу #295 2.1.5. Определить Целевую аудитория мероприятия; 2026-04-28 15:43:05: Екатерина добавил(-а) подзадачу #296 2.1.6. Сформировать Протокол совещания, в котором подитожены все предыдущие пункты; 2026-04-28 15:43:23: Екатерина добавил(-а) подзадачу #297 2.1.7. Протокол совещания подписать с шеф-продюсером и положить в специальную папку, обозначенную именем проекта и годом проведения; 2026-04-28 15:43:34: Екатерина добавил(-а) подзадачу #298 2.1.8. Проанализированы косяки предыдущего мероприятия; 2026-04-28 15:43:45: Екатерина добавил(-а) подзадачу #299 2.1.9. Просмотреть Маркетинговый отчет подготовленный лидгеном (включающий отчет по источникам и каналам и отчет по отказам), даны комментарии по подготовке списка каналов; 2026-04-28 15:43:55: Екатерина добавил(-а) подзадачу #300 2.1.10. Произвести сверку наличия брони по площадке - сверяем с годовым планом по бронированию мест проведения; 2026-04-28 15:44:12: Екатерина добавил(-а) тег PRE; 2026-04-28 15:44:26: Екатерина добавил(-а) тег Продюсер; 2026-04-28 15:44:54: Екатерина добавил(-а) тег страт-п-с-26-09; 2026-04-28 15:45:02: Екатерина убрал(-а) тег страт-п-с-26-09; 2026-04-28 15:45:03: Екатерина добавил(-а) тег старт вехи Pro; 2026-04-28 15:45:57: Екатерина убрал(-а) тег старт вехи Pro; 2026-04-28 15:46:00: Екатерина добавил(-а) тег страт-п-с-26-09; 2026-04-28 16:11:32: Екатерина изменил(-а) дату на 18.05.2026; 2026-04-28 16:11:35: Екатерина изменил(-а) дату на 21.05.2026; 2026-04-28 16:11:38: Екатерина изменил(-а) дату на 18.05.2026; 2026-04-28 16:11:41: Екатерина изменил(-а) дату на 18.05.2026 - 18.05.2026; 2026-04-28 16:11:42: Екатерина изменил(-а) дату на 18.05.2026 - 19.05.2026; 2026-04-28 17:13:35: Екатерина изменил(-а) название на 2.01. Провести Презентацию проекта на Первичном совещании | AB127: Лично сентябрь 2026 | AC127: =VLOOKUP(Y127,'впр данные'!A:B,2,1) -> продюсер, страт-п-с-26-09 | AD127: =VLOOKUP(Y127,'впр данные'!A:C,3,1) -> продюсер
A128: 211 | B128: ЛИЧНО сентябрь 24.09.2026 | C128: Дивизион Конференции | D128: К работе | G128: Екатерина | H128: 4.02. Получить от продюсера Тизер на разработку сайта | I128: 25.05.2026 03:00 | J128: 28.05.2026 | L128: Действие | M128: Низкий | N128: N | P128: 28.04.2026 11:48:42 | S128: Екатерина | V128: N | W128: N | Y128: PRE, Лидген, страт-п-с-26-09 | AA128: 2026-04-28 11:48:42: Екатерина создал(-а) задачу; 2026-04-28 11:50:10: Екатерина изменил(-а) название на 4.2. Получить от продюсера Тизер на разработку сайта; 2026-04-28 17:29:59: Екатерина изменил(-а) статус на Выполнено; 2026-04-28 17:30:01: Екатерина изменил(-а) статус на Не выполнено; 2026-04-28 18:13:25: Екатерина изменил(-а) название на 4.02. Получить от продюсера Тизер на разработку сайта; 2026-04-28 18:42:31: Екатерина переместил(-а) задачу в проекте ЛИЧНО сентябрь 24.09.2026 в колонку Дивизион Конференции / К работе; 2026-04-29 11:31:00: Екатерина изменил(-а) дату на 22.05.2026; 2026-04-29 11:31:05: Екатерина изменил(-а) дату на 22.05.2026 - 29.05.2026; 2026-04-29 11:31:08: Екатерина изменил(-а) дату на 25.05.2026 - 29.05.2026; 2026-04-29 11:31:13: Екатерина изменил(-а) дату на 25.05.2026 - 28.05.2026; 2026-04-29 13:23:19: Екатерина добавил(-а) тег PRE; 2026-04-29 13:23:21: Екатерина добавил(-а) тег лидген; 2026-04-29 13:23:22: Екатерина добавил(-а) тег страт-п-с-26-09; 2026-04-30 14:43:51: Екатерина убрал(-а) тег лидген; 2026-04-30 14:43:52: Екатерина убрал(-а) тег страт-п-с-26-09; 2026-04-30 14:43:59: Екатерина добавил(-а) тег Лидген; 2026-04-30 14:44:00: Екатерина добавил(-а) тег страт-п-с-26-09 | AB128: Лично сентябрь 2026 | AC128: =VLOOKUP(Y128,'впр данные'!A:B,2,1) -> лидген, страт-п-с-26-09 | AD128: =VLOOKUP(Y128,'впр данные'!A:C,3,1) -> лидген
A129: 210 | B129: ЛИЧНО сентябрь 24.09.2026 | C129: Дивизион Конференции | D129: К работе | G129: Екатерина | H129: 4.03. Подготовить семантическое ядро | I129: 01.06.2026 03:00 | J129: 04.06.2026 | L129: Действие | M129: Низкий | N129: N | P129: 28.04.2026 11:48:28 | S129: Екатерина | V129: N | W129: N | Y129: PRE, Лидген, страт-п-с-26-09 | AA129: 2026-04-28 11:48:29: Екатерина создал(-а) задачу; 2026-04-28 11:50:18: Екатерина изменил(-а) название на 4.3. Для проведение маркетингового анализа и разработки семантического ядра изучить полученные от продюсеров результаты кабинетного исследования; 2026-04-28 18:18:15: Екатерина изменил(-а) название на 4.03. Для проведение маркетингового анализа и разработки семантического ядра изучить полученные от продюсеров результаты кабинетного исследования; 2026-04-28 18:18:21: Екатерина изменил(-а) название на 4.03.; 2026-04-28 18:18:23: Екатерина изменил(-а) название на 4.03. Подготовить; 2026-04-28 18:18:28: Екатерина изменил(-а) название на 4.03. Подготовить семантическое ядро; 2026-04-28 18:18:38: Екатерина добавил(-а) подзадачу #454 4.03.1. Для проведение маркетингового анализа и разработки семантического ядра изучить полученные от продюсеров результаты кабинетного исследования; 2026-04-28 18:42:45: Екатерина переместил(-а) задачу в проекте ЛИЧНО сентябрь 24.09.2026 в колонку Дивизион Конференции / К работе; 2026-04-29 11:31:29: Екатерина изменил(-а) дату на 30.05.2026; 2026-04-29 11:31:32: Екатерина изменил(-а) дату на 30.05.2026 - 02.06.2026; 2026-04-29 11:31:34: Екатерина изменил(-а) дату на 01.06.2026 - 02.06.2026; 2026-04-29 11:31:37: Екатерина изменил(-а) дату на 01.06.2026 - 04.06.2026; 2026-04-29 13:23:25: Екатерина добавил(-а) тег PRE; 2026-04-29 13:23:27: Екатерина добавил(-а) тег лидген; 2026-04-29 13:23:28: Екатерина добавил(-а) тег страт-п-с-26-09; 2026-04-30 14:44:05: Екатерина убрал(-а) тег лидген; 2026-04-30 14:44:09: Екатерина убрал(-а) тег страт-п-с-26-09; 2026-04-30 14:44:12: Екатерина добавил(-а) тег Лидген; 2026-04-30 14:44:13: Екатерина добавил(-а) тег страт-п-с-26-09 | AB129: Лично сентябрь 2026 | AC129: =VLOOKUP(Y129,'впр данные'!A:B,2,1) -> лидген, страт-п-с-26-09 | AD129: =VLOOKUP(Y129,'впр данные'!A:C,3,1) -> лидген
A130: 209 | B130: ЛИЧНО сентябрь 24.09.2026 | C130: Дивизион Конференции | D130: К работе | G130: Екатерина | H130: 4.04. Опубликовать утвержденный с ШП Тизер сайт, настроить лид-форму в календаре | I130: 01.06.2026 03:00 | J130: 04.06.2026 | L130: Действие | M130: Низкий | N130: N | P130: 28.04.2026 11:48:17 | S130: Екатерина | V130: N | W130: N | Y130: PRE, Лидген, страт-п-с-26-09 | AA130: 2026-04-28 11:48:17: Екатерина создал(-а) задачу; 2026-04-28 11:50:27: Екатерина изменил(-а) название на 4.4. Утвержденный с ШП Тизер сайт опубликовать, настроена лид-форма в календаре на соответствующем сайте компании; 2026-04-28 11:50:32: Екатерина изменил(-а) название на 4.4. ОпубликоватьУтвержденный с ШП Тизер сайт опубликовать, настроена лид-форма в календаре на соответствующем сайте компании; 2026-04-28 11:50:33: Екатерина изменил(-а) название на 4.4. Опубликовать Утвержденный с ШП Тизер сайт опубликовать, настроена лид-форма в календаре на соответствующем сайте компании; 2026-04-28 11:50:35: Екатерина изменил(-а) название на 4.4. Опубликовать утвержденный с ШП Тизер сайт опубликовать, настроена лид-форма в календаре на соответствующем сайте компании; 2026-04-28 11:50:40: Екатерина изменил(-а) название на 4.4. Опубликовать утвержденный с ШП Тизер сайт, настроена лид-форма в календаре на соответствующем сайте компании; 2026-04-28 11:50:42: Екатерина изменил(-а) название на 4.4. Опубликовать утвержденный с ШП Тизер сайт, настроить лид-форма в календаре на соответствующем сайте компании; 2026-04-28 11:50:46: Екатерина изменил(-а) название на 4.4. Опубликовать утвержденный с ШП Тизер сайт, настроить лид-форму в календаре на соответствующем сайте компании; 2026-04-28 18:19:28: Екатерина изменил(-а) название на 4.4. Опубликовать утвержденный с ШП Тизер сайт, настроить лид-форму в календаре; 2026-04-28 18:19:58: Екатерина изменил(-а) название на 4.04. Опубликовать утвержденный с ШП Тизер сайт, настроить лид-форму в календаре; 2026-04-28 18:38:00: Екатерина добавил(-а) подзадачу #208 4.05. Проанализировать полученные от продюсеров результаты глубинного исследования; 2026-04-28 18:39:24: Екатерина удалил(-а) подзадачу #208 4.05. Проанализировать полученные от продюсеров результаты глубинного исследования; 2026-04-28 18:42:50: Екатерина переместил(-а) задачу в проекте ЛИЧНО сентябрь 24.09.2026 в колонку Дивизион Конференции / К работе; 2026-04-29 11:31:46: Екатерина изменил(-а) дату на 02.06.2026; 2026-04-29 11:31:48: Екатерина изменил(-а) дату на 01.06.2026 - 02.06.2026; 2026-04-29 11:31:50: Екатерина изменил(-а) дату на 01.06.2026 - 04.06.2026; 2026-04-29 13:23:33: Екатерина добавил(-а) тег PRE; 2026-04-29 13:23:35: Екатерина добавил(-а) тег лидген; 2026-04-29 13:23:36: Екатерина добавил(-а) тег страт-п-с-26-09; 2026-04-29 13:24:19: Екатерина убрал(-а) тег лидген; 2026-04-29 13:24:22: Екатерина добавил(-а) тег Лидген; 2026-04-30 14:42:38: Екатерина убрал(-а) тег страт-п-с-26-09; 2026-04-30 14:42:41: Екатерина добавил(-а) тег страт-п-с-26-09 | AB130: Лично сентябрь 2026 | AC130: =VLOOKUP(Y130,'впр данные'!A:B,2,1) -> лидген, страт-п-с-26-09 | AD130: =VLOOKUP(Y130,'впр данные'!A:C,3,1) -> лидген
A131: 207 | B131: ЛИЧНО сентябрь 24.09.2026 | C131: Дивизион Конференции | D131: К работе | G131: Екатерина | H131: 4.06. Получить от продюсеров и проанализировать Концепцию и Программу | I131: 08.06.2026 03:00 | J131: 11.06.2026 | L131: Действие | M131: Низкий | N131: N | P131: 28.04.2026 11:47:45 | S131: Екатерина | V131: N | W131: N | Y131: PRE, Лидген, страт-п-с-26-09 | AA131: 2026-04-28 11:47:46: Екатерина создал(-а) задачу; 2026-04-28 11:52:11: Екатерина изменил(-а) название на 4.6. Получить от продюсеров и проанализирована Концепция и Програма, заданы вопросы по логике и получены ответы; 2026-04-28 11:52:15: Екатерина изменил(-а) название на 4.6. Получить от продюсеров и проанализировать Концепция и Програма, заданы вопросы по логике и получены ответы; 2026-04-28 11:52:18: Екатерина изменил(-а) название на 4.6. Получить от продюсеров и проанализировать Концепцию и Програма, заданы вопросы по логике и получены ответы; 2026-04-28 11:52:21: Екатерина изменил(-а) название на 4.6. Получить от продюсеров и проанализировать Концепцию и Программа, заданы вопросы по логике и получены ответы; 2026-04-28 11:52:24: Екатерина изменил(-а) название на 4.6. Получить от продюсеров и проанализировать Концепцию и Программу, заданы вопросы по логике и получены ответы; 2026-04-28 11:52:28: Екатерина изменил(-а) название на 4.6. Получить от продюсеров и проанализировать Концепцию и Программу, задать вопросы по логике и получены ответы; 2026-04-28 11:52:33: Екатерина изменил(-а) название на 4.6. Получить от продюсеров и проанализировать Концепцию и Программу, задать вопросы по логике и получить ответы; 2026-04-28 18:22:12: Екатерина изменил(-а) название на 4.06. Получить от продюсеров и проанализировать Концепцию и Программу, задать вопросы по логике и получить ответы; 2026-04-28 18:22:41: Екатерина добавил(-а) подзадачу #456 4.06.1. Получить от продюсеров и проанализировать Концепцию и Программу; 2026-04-28 18:22:59: Екатерина изменил(-а) название на 4.06. Получить от продюсеров и проанализировать Концепцию и Программу; 2026-04-28 18:42:53: Екатерина переместил(-а) задачу в проекте ЛИЧНО сентябрь 24.09.2026 в колонку Дивизион Конференции / К работе; 2026-04-29 11:31:57: Екатерина изменил(-а) дату на 01.06.2026; 2026-04-29 11:32:06: Екатерина изменил(-а) дату на 01.06.2026 - 14.06.2026; 2026-04-29 11:32:09: Екатерина изменил(-а) дату на 08.06.2026 - 14.06.2026; 2026-04-29 11:32:12: Екатерина изменил(-а) дату на 08.06.2026 - 11.06.2026; 2026-04-29 13:23:47: Екатерина добавил(-а) тег PRE; 2026-04-29 13:23:49: Екатерина добавил(-а) тег Лидген; 2026-04-29 13:23:50: Екатерина добавил(-а) тег страт-п-с-26-09 | AB131: Лично сентябрь 2026 | AC131: =VLOOKUP(Y131,'впр данные'!A:B,2,1) -> лидген, страт-п-с-26-09 | AD131: =VLOOKUP(Y131,'впр данные'!A:C,3,1) -> лидген
A132: 205 | B132: ЛИЧНО сентябрь 24.09.2026 | C132: Дивизион Конференции | D132: К работе | G132: Екатерина | H132: 4.07. Пройти Обучение по Программе продюсеров и определить ЦА, логику и взаимосвязи | I132: 15.06.2026 03:00 | J132: 18.06.2026 | L132: Действие | M132: Низкий | N132: N | P132: 28.04.2026 11:46:08 | S132: Екатерина | V132: N | W132: N | Y132: PRE, Лидген, страт-п-с-26-09 | AA132: 2026-04-28 11:46:08: Екатерина создал(-а) задачу; 2026-04-28 11:47:25: Екатерина добавил(-а) подзадачу #206 Благодаря анализу материалов полученных на предыдущих неделях лидгеном достигнуть погруженности в тему; 2026-04-28 11:52:51: Екатерина изменил(-а) название на 4.7. Пройти Обучение по Программе продюсеров; 2026-04-28 18:23:30: Екатерина изменил(-а) название на 4.07. Пройти Обучение по Программе продюсеров; 2026-04-28 18:23:39: Екатерина добавил(-а) подзадачу #457 4.07.1. Благодаря анализу материалов полученных на предыдущих неделях лидгеном достигнуть погруженности в тему; 2026-04-28 18:27:30: Екатерина удалил(-а) подзадачу #206 Благодаря анализу материалов полученных на предыдущих неделях лидгеном достигнуть погруженности в тему; 2026-04-28 18:27:42: Екатерина удалил(-а) подзадачу #457 4.07.1. Благодаря анализу материалов полученных на предыдущих неделях лидгеном достигнуть погруженности в тему; 2026-04-28 18:28:18: Екатерина изменил(-а) название на 4.07. Пройти Обучение по Программе продюсеров и определить; 2026-04-28 18:28:21: Екатерина изменил(-а) название на 4.07. Пройти Обучение по Программе продюсеров и определить ЦА, логику; 2026-04-28 18:28:25: Екатерина изменил(-а) название на 4.07. Пройти Обучение по Программе продюсеров и определить ЦА, логику и взаимосвязи; 2026-04-28 18:42:56: Екатерина переместил(-а) задачу в проекте ЛИЧНО сентябрь 24.09.2026 в колонку Дивизион Конференции / К работе; 2026-04-29 11:32:28: Екатерина изменил(-а) дату на 14.06.2026; 2026-04-29 11:32:31: Екатерина изменил(-а) дату на 14.06.2026 - 16.06.2026; 2026-04-29 11:32:33: Екатерина изменил(-а) дату на 15.06.2026 - 16.06.2026; 2026-04-29 11:32:34: Екатерина изменил(-а) дату на 15.06.2026 - 18.06.2026; 2026-04-29 13:24:06: Екатерина добавил(-а) тег PRE; 2026-04-29 13:24:10: Екатерина добавил(-а) тег Лидген; 2026-04-29 13:24:12: Екатерина добавил(-а) тег страт-п-с-26-09; 2026-04-30 14:41:54: Екатерина убрал(-а) тег страт-п-с-26-09; 2026-04-30 14:41:58: Екатерина добавил(-а) тег страт-п-с-26-09 | AB132: Лично сентябрь 2026 | AC132: =VLOOKUP(Y132,'впр данные'!A:B,2,1) -> лидген, страт-п-с-26-09 | AD132: =VLOOKUP(Y132,'впр данные'!A:C,3,1) -> лидген
A133: 204 | B133: ЛИЧНО сентябрь 24.09.2026 | C133: Дивизион Конференции | D133: К работе | G133: Екатерина | H133: 4.08. Согласовать и утвердить с ШП, продюсером и РГП Медиа-план Лидгена | I133: 22.06.2026 03:00 | J133: 25.06.2026 | L133: Действие | M133: Низкий | N133: N | P133: 28.04.2026 11:45:41 | S133: Екатерина | V133: N | W133: N | Y133: PRE, Лидген, страт-п-с-26-09 | AA133: 2026-04-28 11:45:41: Екатерина создал(-а) задачу; 2026-04-28 11:53:14: Екатерина изменил(-а) название на 4.8. На основе понимания Программы Обучения составить, согласован и утвержден с ШП, продюсером и РГП Медиа-план Лидгена; 2026-04-28 11:53:17: Екатерина изменил(-а) название на 4.8. На основе понимания Программы Обучения составить, согласован и утвержден с ШП, продюсером и РГП Медиа-план Лидгена; 2026-04-28 11:53:19: Екатерина изменил(-а) название на 4.8. На основе понимания Программы Обучения составить, согласовать и утвержден с ШП, продюсером и РГП Медиа-план Лидгена; 2026-04-28 11:53:23: Екатерина изменил(-а) название на 4.8. На основе понимания Программы Обучения составить, согласовать и утвердить с ШП, продюсером и РГП Медиа-план Лидгена; 2026-04-28 18:28:48: Екатерина изменил(-а) название на 4.8. согласовать и утвердить с ШП, продюсером и РГП Медиа-план Лидгена; 2026-04-28 18:28:49: Екатерина изменил(-а) название на 4.8. Согласовать и утвердить с ШП, продюсером и РГП Медиа-план Лидгена; 2026-04-28 18:43:05: Екатерина переместил(-а) задачу в проекте ЛИЧНО сентябрь 24.09.2026 в колонку Дивизион Конференции / К работе; 2026-04-28 19:20:56: Екатерина изменил(-а) название на 4.08. Согласовать и утвердить с ШП, продюсером и РГП Медиа-план Лидгена; 2026-04-29 11:32:42: Екатерина изменил(-а) дату на 21.06.2026; 2026-04-29 11:32:44: Екатерина изменил(-а) дату на 21.06.2026 - 25.06.2026; 2026-04-29 11:32:46: Екатерина изменил(-а) дату на 22.06.2026 - 25.06.2026; 2026-04-29 13:25:15: Екатерина добавил(-а) тег PRE; 2026-04-29 13:25:16: Екатерина добавил(-а) тег Операционный директор; 2026-04-29 13:25:18: Екатерина добавил(-а) тег страт-п-с-26-09; 2026-04-29 13:25:24: Екатерина убрал(-а) тег Операционный директор; 2026-04-29 13:25:24: Екатерина добавил(-а) тег Лидген; 2026-04-30 14:42:07: Екатерина убрал(-а) тег страт-п-с-26-09; 2026-04-30 14:42:11: Екатерина добавил(-а) тег ШП; 2026-04-30 14:42:16: Екатерина убрал(-а) тег ШП; 2026-04-30 14:42:19: Екатерина добавил(-а) тег страт-п-с-26-09 | AB133: Лично сентябрь 2026 | AC133: =VLOOKUP(Y133,'впр данные'!A:B,2,1) -> лидген, страт-п-с-26-09 | AD133: =VLOOKUP(Y133,'впр данные'!A:C,3,1) -> лидген
A134: 203 | B134: ЛИЧНО сентябрь 24.09.2026 | C134: Дивизион Конференции | D134: К работе | G134: Екатерина | H134: 4.09. Сделать распределение задач Плана по неделям проекта | I134: 22.06.2026 03:00 | J134: 25.06.2026 | L134: Действие | M134: Низкий | N134: N | P134: 28.04.2026 11:45:29 | S134: Екатерина | V134: N | W134: N | Y134: PRE, Лидген, страт-п-с-26-09 | AA134: 2026-04-28 11:45:30: Екатерина создал(-а) задачу; 2026-04-28 11:53:30: Екатерина изменил(-а) название на 4.9. Сделать распределение задач Плана по неделям проекта; 2026-04-28 18:43:08: Екатерина переместил(-а) задачу в проекте ЛИЧНО сентябрь 24.09.2026 в колонку Дивизион Конференции / К работе; 2026-04-28 19:21:00: Екатерина изменил(-а) название на 4.09. Сделать распределение задач Плана по неделям проекта; 2026-04-29 11:32:56: Екатерина изменил(-а) дату на 23.06.2026; 2026-04-29 11:32:58: Екатерина изменил(-а) дату на 22.06.2026 - 23.06.2026; 2026-04-29 11:33:00: Екатерина изменил(-а) дату на 22.06.2026 - 25.06.2026; 2026-04-29 13:25:28: Екатерина добавил(-а) тег PRE; 2026-04-29 13:25:31: Екатерина добавил(-а) тег Лидген; 2026-04-29 13:25:32: Екатерина добавил(-а) тег страт-п-с-26-09 | AB134: Лично сентябрь 2026 | AC134: =VLOOKUP(Y134,'впр данные'!A:B,2,1) -> лидген, страт-п-с-26-09 | AD134: =VLOOKUP(Y134,'впр данные'!A:C,3,1) -> лидген
A135: 202 | B135: ЛИЧНО сентябрь 24.09.2026 | C135: Дивизион Конференции | D135: К работе | G135: Екатерина | H135: 4.10. Сдать отчет по Плану лидгена: KPI - 10% выполнения | I135: 27.07.2026 03:00 | J135: 30.07.2026 | L135: Действие | M135: Низкий | N135: N | P135: 28.04.2026 11:42:59 | S135: Екатерина | V135: N | W135: N | Y135: PRO, Лидген, страт-п-с-26-09 | AA135: 2026-04-28 11:43:00: Екатерина создал(-а) задачу; 2026-04-28 11:43:27: Екатерина изменил(-а) название на 4.10. Сдан еженедельный отчет по всем активностям лидгена - сверка с планом; 2026-04-28 11:53:44: Екатерина изменил(-а) название на 4.10. Сдать еженедельный отчет по всем активностям лидгена - сверка с планом; 2026-04-28 11:53:48: Екатерина изменил(-а) название на 4.10. Сдать еженедельный отчет по всем активностям лидгена - сверка с планом -; 2026-04-28 11:53:54: Екатерина изменил(-а) название на 4.10. Сдать еженедельный отчет по всем активностям лидгена - сверка с планом; 2026-04-28 11:53:55: Екатерина изменил(-а) название на 4.10. Сдать еженедельный отчет по всем активностям лидгена - сверка с планом по; 2026-04-28 11:53:57: Екатерина изменил(-а) название на 4.10. Сдать еженедельный отчет по всем активностям лидгена - сверка с планом по KPI; 2026-04-28 11:54:01: Екатерина изменил(-а) название на 4.10. Сдать еженедельный отчет по всем активностям лидгена - сверка с планом по KPI - 10; 2026-04-28 11:54:03: Екатерина изменил(-а) название на 4.10. Сдать еженедельный отчет по всем активностям лидгена - сверка с планом по KPI - 10%; 2026-04-28 11:54:07: Екатерина изменил(-а) название на 4.10. Сдать еженедельный отчет по всем активностям лидгена - сверка с планом по KPI - 10% d; 2026-04-28 11:54:12: Екатерина изменил(-а) название на 4.10. Сдать еженедельный отчет по всем активностям лидгена - сверка с планом по KPI - 10%; 2026-04-28 11:54:12: Екатерина изменил(-а) название на 4.10. Сдать еженедельный отчет по всем активностям лидгена - сверка с планом по KPI - 10% от; 2026-04-28 11:54:13: Екатерина изменил(-а) название на 4.10. Сдать еженедельный отчет по всем активностям лидгена - сверка с планом по KPI - 10% о; 2026-04-28 11:54:15: Екатерина изменил(-а) название на 4.10. Сдать еженедельный отчет по всем активностям лидгена - сверка с планом по KPI - 10%; 2026-04-28 11:54:20: Екатерина изменил(-а) название на 4.10. Сдать еженедельный отчет по всем активностям лидгена - сверка с планом по KPI - выполненно 10%; 2026-04-28 11:54:21: Екатерина изменил(-а) название на 4.10. Сдать еженедельный отчет по всем активностям лидгена - сверка с планом по KPI - выполненн10%; 2026-04-28 11:54:22: Екатерина изменил(-а) название на 4.10. Сдать еженедельный отчет по всем активностям лидгена - сверка с планом по KPI - выполнен10%; 2026-04-28 11:54:23: Екатерина изменил(-а) название на 4.10. Сдать еженедельный отчет по всем активностям лидгена - сверка с планом по KPI - выполнено10%; 2026-04-28 11:54:24: Екатерина изменил(-а) название на 4.10. Сдать еженедельный отчет по всем активностям лидгена - сверка с планом по KPI - выполнено 10%; 2026-04-28 11:54:28: Екатерина изменил(-а) название на 4.10. Сдать еженедельный отчет по всем активностям лидгена - сверка с планом по KPI - выполнено 10% з; 2026-04-28 11:54:33: Екатерина изменил(-а) название на 4.10. Сдать еженедельный отчет по всем активностям лидгена - сверка с планом по KPI - выполнено 10% от всех запланированных; 2026-04-28 11:54:36: Екатерина изменил(-а) название на 4.10. Сдать еженедельный отчет по всем активностям лидгена - сверка с планом по KPI - выполнено 10% от всех запланированных активностей; 2026-04-28 18:13:43: Екатерина изменил(-а) название на 4.10. Сдатьотчет по всем активностям лидгена - сверка с планом по KPI - выполнено 10% от всех запланированных активностей; 2026-04-28 18:13:45: Екатерина изменил(-а) название на 4.10. Сдать отчет по всем активностям лидгена - сверка с планом по KPI - выполнено 10% от всех запланированных активностей; 2026-04-28 18:13:54: Екатерина изменил(-а) название на 4.10. Сдать отчет по KPI - выполнено 10% от всех запланированных активностей; 2026-04-28 18:13:57: Екатерина изменил(-а) название на 4.10. Сдать отчет по План улидгена KPI - выполнено 10% от всех запланированных активностей; 2026-04-28 18:14:01: Екатерина изменил(-а) название на 4.10. Сдать отчет по Планулидгена KPI - выполнено 10% от всех запланированных активностей; 2026-04-28 18:14:02: Екатерина изменил(-а) название на 4.10. Сдать отчет по Плану лидгена KPI - выполнено 10% от всех запланированных активностей; 2026-04-28 18:14:13: Екатерина изменил(-а) название на 4.10. Сдать отчет по Плану лидгена: KPI - выполнено 10% от всех запланированных активностей; 2026-04-28 18:14:19: Екатерина изменил(-а) название на 4.10. Сдать отчет по Плану лидгена: KPI - 10% от всех запланированных активностей; 2026-04-28 18:14:22: Екатерина изменил(-а) название на 4.10. Сдать отчет по Плану лидгена: KPI - 10% выполнения; 2026-04-28 18:35:25: Екатерина добавил(-а) тег PRO; 2026-04-28 18:35:34: Екатерина добавил(-а) тег страт-п-с-26-09; 2026-04-28 18:37:26: Екатерина добавил(-а) тег Лидген; 2026-04-28 18:43:11: Екатерина переместил(-а) задачу в проекте ЛИЧНО сентябрь 24.09.2026 в колонку Дивизион Конференции / К работе; 2026-04-29 11:13:39: Екатерина изменил(-а) дату на 27.07.2026; 2026-04-29 11:13:39: Екатерина изменил(-а) дату на 27.07.2026 - 30.07.2026; 2026-04-30 14:41:29: Екатерина убрал(-а) тег страт-п-с-26-09; 2026-04-30 14:41:33: Екатерина добавил(-а) тег страт-п-с-26-09 | AB135: Лично сентябрь 2026 | AC135: =VLOOKUP(Y135,'впр данные'!A:B,2,1) -> лидген, страт-п-с-26-09 | AD135: =VLOOKUP(Y135,'впр данные'!A:C,3,1) -> лидген
A136: 201 | B136: ЛИЧНО сентябрь 24.09.2026 | C136: Дивизион Конференции | D136: К работе | G136: Екатерина | H136: 4.11. Сдать отчет по Плану лидгена: KPI - 20% выполнения | I136: 03.08.2026 03:00 | J136: 06.08.2026 | L136: Действие | M136: Низкий | N136: N | P136: 28.04.2026 11:42:58 | S136: Екатерина | V136: N | W136: N | Y136: PRO, Лидген, страт-п-с-26-09 | AA136: 2026-04-28 11:42:58: Екатерина создал(-а) задачу; 2026-04-28 11:43:32: Екатерина изменил(-а) название на 4.11. Сдан еженедельный отчет по всем активностям лидгена - сверка с планом; 2026-04-28 11:54:47: Екатерина изменил(-а) название на 4.11. 4.10. Сдать еженедельный отчет по всем активностям лидгена - сверка с планом по KPI - выполнено 10% от всех запланированных активностей; 2026-04-28 11:54:52: Екатерина изменил(-а) название на 4.11. Сдать еженедельный отчет по всем активностям лидгена - сверка с планом по KPI - выполнено 10% от всех запланированных активностей; 2026-04-28 11:54:55: Екатерина изменил(-а) название на 4.11. Сдать еженедельный отчет по всем активностям лидгена - сверка с планом по KPI - выполнено 20% от всех запланированных активностей; 2026-04-28 18:14:32: Екатерина изменил(-а) название на 4.11. Сдать отчет по Плану лидгена: KPI - 10% выполнения; 2026-04-28 18:14:38: Екатерина изменил(-а) название на 4.11. Сдать отчет по Плану лидгена: KPI - 20% выполнения; 2026-04-28 18:43:14: Екатерина переместил(-а) задачу в проекте ЛИЧНО сентябрь 24.09.2026 в колонку Дивизион Конференции / К работе; 2026-04-29 11:13:50: Екатерина изменил(-а) дату на 03.08.2026; 2026-04-29 11:13:51: Екатерина изменил(-а) дату на 07.08.2026; 2026-04-29 11:13:54: Екатерина изменил(-а) дату на 03.08.2026 - 07.08.2026; 2026-04-29 11:13:56: Екатерина изменил(-а) дату на 03.08.2026 - 06.08.2026; 2026-04-29 13:25:37: Екатерина добавил(-а) тег PRO; 2026-04-29 13:25:41: Екатерина добавил(-а) тег страт-п-с-26-09; 2026-04-29 13:25:48: Екатерина добавил(-а) тег Лидген; 2026-04-30 14:41:40: Екатерина убрал(-а) тег страт-п-с-26-09; 2026-04-30 14:41:43: Екатерина добавил(-а) тег страт-п-с-26-09 | AB136: Лично сентябрь 2026 | AC136: =VLOOKUP(Y136,'впр данные'!A:B,2,1) -> лидген, страт-п-с-26-09 | AD136: =VLOOKUP(Y136,'впр данные'!A:C,3,1) -> лидген
A137: 200 | B137: ЛИЧНО сентябрь 24.09.2026 | C137: Дивизион Конференции | D137: К работе | G137: Екатерина | H137: 4.11. Сдать отчет по Плану лидгена: KPI - 30% выполнения | I137: 10.08.2026 03:00 | J137: 13.08.2026 | L137: Действие | M137: Низкий | N137: N | P137: 28.04.2026 11:42:57 | S137: Екатерина | V137: N | W137: N | Y137: PRO, Лидген, страт-п-с-26-09 | AA137: 2026-04-28 11:42:58: Екатерина создал(-а) задачу; 2026-04-28 11:43:37: Екатерина изменил(-а) название на 4.12. Сдан еженедельный отчет по всем активностям лидгена - сверка с планом; 2026-04-28 11:55:14: Екатерина изменил(-а) название на 4.11. Сдать еженедельный отчет по всем активностям лидгена - сверка с планом по KPI - выполнено 20% от всех запланированных активностей; 2026-04-28 11:55:17: Екатерина изменил(-а) название на 4.11. Сдать еженедельный отчет по всем активностям лидгена - сверка с планом по KPI - выполнено 30% от всех запланированных активностей; 2026-04-28 18:11:18: Екатерина изменил(-а) дату на 28.04.2026; 2026-04-28 18:11:29: Екатерина изменил(-а) дату на 06.05.2026 - 13.05.2026; 2026-04-28 18:14:44: Екатерина изменил(-а) название на 4.11. Сдать отчет по Плану лидгена: KPI - 10% выполнения; 2026-04-28 18:14:48: Екатерина изменил(-а) название на 4.11. Сдать отчет по Плану лидгена: KPI - 30% выполнения; 2026-04-28 18:43:19: Екатерина переместил(-а) задачу в проекте ЛИЧНО сентябрь 24.09.2026 в колонку Дивизион Конференции / К работе; 2026-04-29 11:14:21: Екатерина изменил(-а) дату на 13.05.2026 - 10.08.2026; 2026-04-29 11:14:21: Екатерина изменил(-а) дату на 13.05.2026 - 13.08.2026; 2026-04-29 11:14:24: Екатерина изменил(-а) дату на 10.08.2026 - 13.08.2026; 2026-04-29 13:25:51: Екатерина добавил(-а) тег PRO; 2026-04-29 13:25:55: Екатерина добавил(-а) тег Лидген; 2026-04-29 13:25:55: Екатерина добавил(-а) тег страт-п-с-26-09 | AB137: Лично сентябрь 2026 | AC137: =VLOOKUP(Y137,'впр данные'!A:B,2,1) -> лидген, страт-п-с-26-09 | AD137: =VLOOKUP(Y137,'впр данные'!A:C,3,1) -> лидген
A138: 199 | B138: ЛИЧНО сентябрь 24.09.2026 | C138: Дивизион Конференции | D138: К работе | G138: Екатерина | H138: 4.13. Сдать отчет по Плану лидгена: KPI - 40% выполнения | I138: 17.08.2026 03:00 | J138: 20.08.2026 | L138: Действие | M138: Низкий | N138: N | P138: 28.04.2026 11:42:56 | S138: Екатерина | V138: N | W138: N | Y138: PRO, Лидген, страт-п-с-26-09 | AA138: 2026-04-28 11:42:56: Екатерина создал(-а) задачу; 2026-04-28 11:43:41: Екатерина изменил(-а) название на 4.13. Сдан еженедельный отчет по всем активностям лидгена - сверка с планом; 2026-04-28 11:56:40: Екатерина изменил(-а) название на 4.13. Сдать еженедельный отчет по всем активностям лидгена - сверка с планом по KPI - выполнено 30% от всех запланированных активностей; 2026-04-28 18:14:55: Екатерина изменил(-а) название на 4.13. Сдать отчет по Плану лидгена: KPI - 10% выполнения; 2026-04-28 18:14:58: Екатерина изменил(-а) название на 4.13. Сдать отчет по Плану лидгена: KPI - 40% выполнения; 2026-04-28 18:43:20: Екатерина переместил(-а) задачу в проекте ЛИЧНО сентябрь 24.09.2026 в колонку Дивизион Конференции / К работе; 2026-04-29 11:14:39: Екатерина изменил(-а) дату на 17.08.2026 - 17.08.2026; 2026-04-29 11:14:40: Екатерина изменил(-а) дату на 17.08.2026 - 20.08.2026; 2026-04-29 13:25:58: Екатерина добавил(-а) тег PRO; 2026-04-29 13:26:01: Екатерина добавил(-а) тег Лидген; 2026-04-29 13:26:01: Екатерина добавил(-а) тег страт-п-с-26-09 | AB138: Лично сентябрь 2026 | AC138: =VLOOKUP(Y138,'впр данные'!A:B,2,1) -> лидген, страт-п-с-26-09 | AD138: =VLOOKUP(Y138,'впр данные'!A:C,3,1) -> лидген
A139: 198 | B139: ЛИЧНО сентябрь 24.09.2026 | C139: Дивизион Конференции | D139: К работе | G139: Екатерина | H139: 4.14. Сдать отчет по Плану лидгена: KPI - 50% выполнения | I139: 24.08.2026 03:00 | J139: 27.08.2026 | L139: Действие | M139: Низкий | N139: N | P139: 28.04.2026 11:42:55 | Q139: 1 | S139: Екатерина | V139: N | W139: N | Y139: PRO, Лидген, страт-п-с-26-09 | AA139: 2026-04-28 11:42:55: Екатерина создал(-а) задачу; 2026-04-28 11:43:53: Екатерина изменил(-а) название на 4.14. Сдан еженедельный отчет по всем активностям лидгена - сверка с планом; 2026-04-28 18:15:05: Екатерина изменил(-а) название на 4.14. Сдать отчет по Плану лидгена: KPI - 10% выполнения; 2026-04-28 18:15:08: Екатерина изменил(-а) название на 4.14. Сдать отчет по Плану лидгена: KPI - 50% выполнения; 2026-04-28 18:20:19: Екатерина изменил(-а) дату на 28.04.2026; 2026-04-28 18:43:25: Екатерина переместил(-а) задачу в проекте ЛИЧНО сентябрь 24.09.2026 в колонку Дивизион Конференции / К работе; 2026-04-29 11:14:57: Екатерина изменил(-а) дату на 29.04.2026 - 24.08.2026; 2026-04-29 11:14:59: Екатерина изменил(-а) дату на 29.04.2026 - 27.08.2026; 2026-04-29 11:15:14: Екатерина изменил(-а) дату на 24.08.2026 - 27.08.2026; 2026-04-29 13:26:03: Екатерина добавил(-а) тег PRO; 2026-04-29 13:26:07: Екатерина добавил(-а) тег Лидген; 2026-04-29 13:26:07: Екатерина добавил(-а) тег страт-п-с-26-09 | AB139: Лично сентябрь 2026 | AC139: =VLOOKUP(Y139,'впр данные'!A:B,2,1) -> лидген, страт-п-с-26-09 | AD139: =VLOOKUP(Y139,'впр данные'!A:C,3,1) -> лидген
A140: 197 | B140: ЛИЧНО сентябрь 24.09.2026 | C140: Дивизион Конференции | D140: К работе | G140: Екатерина | H140: 4.15. Сдать отчет по Плану лидгена: KPI - 60% выполнения | I140: 31.08.2026 03:00 | J140: 03.09.2026 | L140: Действие | M140: Низкий | N140: N | P140: 28.04.2026 11:42:52 | S140: Екатерина | V140: N | W140: N | Y140: PRO, Лидген, страт-п-с-26-09 | AA140: 2026-04-28 11:42:52: Екатерина создал(-а) задачу; 2026-04-28 11:44:08: Екатерина изменил(-а) название на 4.15. Сдан еженедельный отчет по всем активностям лидгена - сверка с планом; 2026-04-28 18:15:14: Екатерина изменил(-а) название на 4.15. Сдать отчет по Плану лидгена: KPI - 10% выполнения; 2026-04-28 18:15:17: Екатерина изменил(-а) название на 4.15. Сдать отчет по Плану лидгена: KPI - 60% выполнения; 2026-04-28 18:43:26: Екатерина переместил(-а) задачу в проекте ЛИЧНО сентябрь 24.09.2026 в колонку Дивизион Конференции / К работе; 2026-04-29 11:17:01: Екатерина изменил(-а) дату на 31.08.2026; 2026-04-29 11:17:03: Екатерина изменил(-а) дату на 03.09.2026; 2026-04-29 11:17:13: Екатерина изменил(-а) дату на 31.08.2026 - 03.09.2026; 2026-04-29 13:26:10: Екатерина добавил(-а) тег PRO; 2026-04-29 13:26:11: Екатерина добавил(-а) тег Лидген; 2026-04-29 13:26:13: Екатерина добавил(-а) тег страт-п-с-26-09 | AB140: Лично сентябрь 2026 | AC140: =VLOOKUP(Y140,'впр данные'!A:B,2,1) -> лидген, страт-п-с-26-09 | AD140: =VLOOKUP(Y140,'впр данные'!A:C,3,1) -> лидген
A141: 196 | B141: ЛИЧНО сентябрь 24.09.2026 | C141: Дивизион Конференции | D141: К работе | G141: Екатерина | H141: 4.16. Сдать отчет по Плану лидгена: KPI - 70% выполнения | I141: 07.09.2026 03:00 | J141: 10.09.2026 | L141: Действие | M141: Низкий | N141: N | P141: 28.04.2026 11:42:50 | S141: Екатерина | V141: N | W141: N | Y141: PRO, Лидген, страт-п-с-26-09 | AA141: 2026-04-28 11:42:51: Екатерина создал(-а) задачу; 2026-04-28 11:44:17: Екатерина изменил(-а) название на 4.16. Сдан еженедельный отчет по всем активностям лидгена - сверка с планом; 2026-04-28 18:15:25: Екатерина изменил(-а) название на 4.16. Сдать отчет по Плану лидгена: KPI - 10% выполнения; 2026-04-28 18:15:27: Екатерина изменил(-а) название на 4.16. Сдать отчет по Плану лидгена: KPI - 80% выполнения; 2026-04-28 18:15:29: Екатерина изменил(-а) название на 4.16. Сдать отчет по Плану лидгена: KPI - 70% выполнения; 2026-04-28 18:43:29: Екатерина переместил(-а) задачу в проекте ЛИЧНО сентябрь 24.09.2026 в колонку Дивизион Конференции / К работе; 2026-04-29 11:17:25: Екатерина изменил(-а) дату на 07.09.2026 - 07.09.2026; 2026-04-29 11:17:27: Екатерина изменил(-а) дату на 07.09.2026 - 10.09.2026; 2026-04-29 13:26:17: Екатерина добавил(-а) тег PRO; 2026-04-29 13:26:22: Екатерина добавил(-а) тег Лидген; 2026-04-29 13:26:22: Екатерина добавил(-а) тег страт-п-с-26-09 | AB141: Лично сентябрь 2026 | AC141: =VLOOKUP(Y141,'впр данные'!A:B,2,1) -> лидген, страт-п-с-26-09 | AD141: =VLOOKUP(Y141,'впр данные'!A:C,3,1) -> лидген
A142: 195 | B142: ЛИЧНО сентябрь 24.09.2026 | C142: Дивизион Конференции | D142: К работе | G142: Екатерина | H142: 4.17. Сдать отчет по Плану лидгена: KPI - 80-100% выполнения | I142: 14.09.2026 03:00 | J142: 17.09.2026 | L142: Действие | M142: Низкий | N142: N | P142: 28.04.2026 11:42:48 | S142: Екатерина | V142: N | W142: N | Y142: PRO, Лидген, страт-п-с-26-09 | AA142: 2026-04-28 11:42:48: Екатерина создал(-а) задачу; 2026-04-28 11:44:23: Екатерина изменил(-а) название на 4.17. Сдан еженедельный отчет по всем активностям лидгена - сверка с планом; 2026-04-28 18:15:35: Екатерина изменил(-а) название на 4.17. Сдать отчет по Плану лидгена: KPI - 10% выполнения; 2026-04-28 18:15:39: Екатерина изменил(-а) название на 4.17. Сдать отчет по Плану лидгена: KPI - 70% выполнения; 2026-04-28 18:16:11: Екатерина изменил(-а) название на 4.17. Сдать отчет по Плану лидгена: KPI - 80% выполнения; 2026-04-28 18:43:40: Екатерина переместил(-а) задачу в проекте ЛИЧНО сентябрь 24.09.2026 в колонку Дивизион Конференции / К работе; 2026-04-29 11:17:37: Екатерина изменил(-а) дату на 14.09.2026 - 14.09.2026; 2026-04-29 11:17:40: Екатерина изменил(-а) дату на 14.09.2026 - 17.09.2026; 2026-04-29 11:43:27: Екатерина изменил(-а) название на 4.17. Сдать отчет по Плану лидгена: KPI - 80-100% выполнения; 2026-04-29 13:26:25: Екатерина добавил(-а) тег PRO; 2026-04-29 13:26:28: Екатерина добавил(-а) тег Лидген; 2026-04-29 13:26:28: Екатерина добавил(-а) тег страт-п-с-26-09 | AB142: Лично сентябрь 2026 | AC142: =VLOOKUP(Y142,'впр данные'!A:B,2,1) -> лидген, страт-п-с-26-09 | AD142: =VLOOKUP(Y142,'впр данные'!A:C,3,1) -> лидген
A143: 194 | B143: ЛИЧНО сентябрь 24.09.2026 | C143: Дивизион Конференции | D143: К работе | G143: Екатерина | H143: 4.18. Сдать отчет по Плану лидгена: KPI - 90-100% выполнения | I143: 21.09.2026 03:00 | J143: 24.09.2026 | L143: Действие | M143: Низкий | N143: N | P143: 28.04.2026 11:42:44 | S143: Екатерина | V143: N | W143: N | Y143: D, Лидген, страт-п-с-26-09 | AA143: 2026-04-28 11:42:45: Екатерина создал(-а) задачу; 2026-04-28 11:44:36: Екатерина изменил(-а) название на 4.18. Сдан еженедельный отчет по всем активностям лидгена - сверка с планом; 2026-04-28 18:16:16: Екатерина изменил(-а) название на 4.18. Сдать отчет по Плану лидгена: KPI - 10% выполнения; 2026-04-28 18:16:18: Екатерина изменил(-а) название на 4.18. Сдать отчет по Плану лидгена: KPI - 90% выполнения; 2026-04-28 18:16:21: Екатерина изменил(-а) название на 4.18. Сдать отчет по Плану лидгена: KPI - 90-100% выполнения; 2026-04-28 18:43:43: Екатерина переместил(-а) задачу в проекте ЛИЧНО сентябрь 24.09.2026 в колонку Дивизион Конференции / К работе; 2026-04-29 11:16:20: Екатерина изменил(-а) дату на 24.09.2026; 2026-04-29 11:16:23: Екатерина изменил(-а) дату на 21.09.2026 - 24.09.2026; 2026-04-29 11:16:41: Екатерина добавил(-а) тег D; 2026-04-29 13:26:36: Екатерина добавил(-а) тег Лидген; 2026-04-29 13:26:36: Екатерина добавил(-а) тег страт-п-с-26-09 | AB143: Лично сентябрь 2026 | AC143: =VLOOKUP(Y143,'впр данные'!A:B,2,1) -> лидген, страт-п-с-26-09 | AD143: =VLOOKUP(Y143,'впр данные'!A:C,3,1) -> лидген
A144: 193 | B144: ЛИЧНО сентябрь 24.09.2026 | C144: Дивизион Конференции | D144: К работе | G144: Екатерина | H144: 4.19. Подготовлен Маркетинговый пост-отчет | I144: 28.09.2026 03:00 | J144: 01.10.2026 | L144: Действие | M144: Низкий | N144: N | P144: 28.04.2026 11:41:52 | S144: Екатерина | V144: N | W144: N | Y144: POST, Лидген, страт-п-с-26-09 | AA144: 2026-04-28 11:41:53: Екатерина создал(-а) задачу; 2026-04-28 11:44:47: Екатерина изменил(-а) название на 4.19. Подготовлен Маркетинговый пост-отчет, включая детализацию согласно структуре Медиа-план Лидгена, где каждый канал-источник - детализирован: по нему собран результат в количестве лидов и в сумме руб, которую принес каждый канал; 2026-04-28 18:16:32: Екатерина изменил(-а) название на 4.19. Подготовить Маркетинговый пост-отчет, включая детализацию согласно структуре Медиа-план Лидгена, где каждый канал-источник - детализирован: по нему собран результат в количестве лидов и в сумме руб, которую принес каждый канал; 2026-04-28 18:16:44: Екатерина изменил(-а) название на 4.19. Подготовлен Маркетинговый пост-отчет, включая детализацию согласно структуре Медиа-план Лидгена, где каждый канал-источник - детализирован: по нему собран результат в количестве лидов и в сумме руб, которую принес каждый канал; 2026-04-28 18:17:03: Екатерина изменил(-а) название на 4.19. Подготовлен Маркетинговый пост-отчет,; 2026-04-28 18:17:04: Екатерина изменил(-а) название на 4.19. Подготовлен Маркетинговый пост-отчет; 2026-04-28 18:43:45: Екатерина переместил(-а) задачу в проекте ЛИЧНО сентябрь 24.09.2026 в колонку Дивизион Конференции / К работе; 2026-04-29 11:16:43: Екатерина добавил(-а) тег POST; 2026-04-29 11:17:57: Екатерина изменил(-а) дату на 28.09.2026 - 28.09.2026; 2026-04-29 11:17:58: Екатерина изменил(-а) дату на 28.09.2026 - 01.10.2026; 2026-04-29 13:26:53: Екатерина добавил(-а) тег Лидген; 2026-04-29 13:26:54: Екатерина добавил(-а) тег Продюсер; 2026-04-29 13:26:56: Екатерина убрал(-а) тег Продюсер; 2026-04-29 13:26:58: Екатерина добавил(-а) тег страт-п-с-26-09 | AB144: Лично сентябрь 2026 | AC144: =VLOOKUP(Y144,'впр данные'!A:B,2,1) -> лидген, страт-п-с-26-09 | AD144: =VLOOKUP(Y144,'впр данные'!A:C,3,1) -> лидген
A145: 192 | B145: ЛИЧНО сентябрь 24.09.2026 | C145: Дивизион Конференции | D145: К работе | G145: Екатерина | H145: 4.20. Подготовить отчет по косякам | I145: 28.09.2026 03:00 | J145: 01.10.2026 | L145: Действие | M145: Низкий | N145: N | P145: 28.04.2026 11:41:33 | S145: Екатерина | V145: N | W145: N | Y145: POST, Лидген, страт-п-с-26-09 | AA145: 2026-04-28 11:41:33: Екатерина создал(-а) задачу; 2026-04-28 11:44:54: Екатерина изменил(-а) название на 4.20. Подготовлен отчет по косякам; 2026-04-28 18:18:03: Екатерина изменил(-а) название на 4.20. Подготовить отчет по косякам; 2026-04-28 18:43:48: Екатерина переместил(-а) задачу в проекте ЛИЧНО сентябрь 24.09.2026 в колонку Дивизион Конференции / К работе; 2026-04-29 11:16:47: Екатерина добавил(-а) тег POST; 2026-04-29 11:33:27: Екатерина изменил(-а) дату на 29.09.2026; 2026-04-29 11:33:32: Екатерина изменил(-а) дату на 27.09.2026 - 29.09.2026; 2026-04-29 11:33:36: Екатерина изменил(-а) дату на 27.09.2026 - 02.10.2026; 2026-04-29 11:33:39: Екатерина изменил(-а) дату на 28.09.2026 - 02.10.2026; 2026-04-29 11:33:39: Екатерина изменил(-а) дату на 28.09.2026 - 01.10.2026; 2026-04-29 13:27:03: Екатерина добавил(-а) тег Лидген; 2026-04-29 13:27:04: Екатерина добавил(-а) тег страт-п-с-26-09 | AB145: Лично сентябрь 2026 | AC145: =VLOOKUP(Y145,'впр данные'!A:B,2,1) -> лидген, страт-п-с-26-09 | AD145: =VLOOKUP(Y145,'впр данные'!A:C,3,1) -> лидген
A146: 191 | B146: ЛИЧНО сентябрь 24.09.2026 | C146: Дивизион Конференции | D146: К работе | G146: Екатерина | H146: 4.21. Опубликовать пост-релиз в блог, скрыта программа и добавлен анонс на следующее мероприятие | I146: 28.09.2026 03:00 | J146: 01.10.2026 | L146: Действие | M146: Низкий | N146: N | P146: 28.04.2026 11:41:22 | S146: Екатерина | V146: N | W146: N | Y146: POST, Лидген, страт-п-с-26-09 | AA146: 2026-04-28 11:41:23: Екатерина создал(-а) задачу; 2026-04-28 11:44:58: Екатерина изменил(-а) название на 4.21. Опубликован пост-релиз в блог, скрыта программа и добавлен анонс на следующее мероприятие; 2026-04-28 18:18:08: Екатерина изменил(-а) название на 4.21. Опубликовать пост-релиз в блог, скрыта программа и добавлен анонс на следующее мероприятие; 2026-04-28 18:43:51: Екатерина переместил(-а) задачу в проекте ЛИЧНО сентябрь 24.09.2026 в колонку Дивизион Конференции / К работе; 2026-04-29 11:16:51: Екатерина добавил(-а) тег POST; 2026-04-29 11:33:41: Екатерина изменил(-а) дату на 29.09.2026; 2026-04-29 11:33:43: Екатерина изменил(-а) дату на 29.09.2026 - 01.10.2026; 2026-04-29 11:33:44: Екатерина изменил(-а) дату на 28.09.2026 - 01.10.2026; 2026-04-29 13:27:09: Екатерина добавил(-а) тег Лидген; 2026-04-29 13:27:10: Екатерина добавил(-а) тег страт-п-с-26-09 | AB146: Лично сентябрь 2026 | AC146: =VLOOKUP(Y146,'впр данные'!A:B,2,1) -> лидген, страт-п-с-26-09 | AD146: =VLOOKUP(Y146,'впр данные'!A:C,3,1) -> лидген
A147: 190 | B147: ЛИЧНО сентябрь 24.09.2026 | C147: Дивизион Конференции | D147: К работе | G147: Екатерина | H147: 5.01. Получить вводные на Первичном совещании | I147: 18.05.2026 03:00 | J147: 19.05.2026 | L147: Действие | M147: Низкий | N147: N | P147: 28.04.2026 11:22:35 | Q147: 20 | R147: Нелли | S147: Екатерина, Нелли | V147: N | W147: N | Y147: PRE, РГП, страт-п-с-26-09 | AA147: 2026-04-28 11:22:36: Екатерина создал(-а) задачу; 2026-04-28 11:25:54: Екатерина добавил(-а) тег PRE; 2026-04-28 12:31:14: Екатерина изменил(-а) дату на 01.04.2026; 2026-04-28 12:31:16: Екатерина изменил(-а) дату на 05.04.2026; 2026-04-28 12:31:19: Екатерина изменил(-а) дату на 05.04.2026 - 09.04.2026; 2026-04-28 12:31:37: Екатерина назначил(-а) Нелли исполнителем; 2026-04-28 18:43:55: Екатерина переместил(-а) задачу в проекте ЛИЧНО сентябрь 24.09.2026 в колонку Дивизион Конференции / К работе; 2026-04-28 18:44:00: Екатерина изменил(-а) название на 5.01. Получить вводные на Первичном совещании; 2026-04-29 10:01:05: Екатерина добавил(-а) тег РГП; 2026-04-29 10:01:19: Екатерина добавил(-а) тег страт-п-с-26-09; 2026-04-29 11:34:37: Екатерина изменил(-а) дату на 28.04.2026 - 29.04.2026; 2026-04-29 11:34:37: Екатерина изменил(-а) дату на 28.04.2026 - 03.05.2026; 2026-04-29 11:34:42: Екатерина изменил(-а) дату на 02.05.2026 - 03.05.2026; 2026-04-29 11:34:43: Екатерина изменил(-а) дату на 02.05.2026 - 07.05.2026; 2026-04-29 11:34:46: Екатерина изменил(-а) дату на 07.05.2026; 2026-04-29 11:34:48: Екатерина изменил(-а) дату на 07.05.2026 - 11.05.2026; 2026-04-29 11:34:52: Екатерина изменил(-а) дату на 10.05.2026 - 11.05.2026; 2026-04-29 11:34:55: Екатерина изменил(-а) дату на 10.05.2026 - 18.05.2026; 2026-04-29 11:34:58: Екатерина изменил(-а) дату на 18.05.2026; 2026-04-29 11:34:59: Екатерина изменил(-а) дату на 18.05.2026 - 19.05.2026 | AB147: Лично сентябрь 2026 | AC147: =VLOOKUP(Y147,'впр данные'!A:B,2,1) -> РГП, страт-п-с-26-09 | AD147: =VLOOKUP(Y147,'впр данные'!A:C,3,1) -> РГП
A148: 189 | B148: ЛИЧНО сентябрь 24.09.2026 | C148: Дивизион Конференции | D148: К работе | G148: Екатерина | H148: 5.02. Утвердить Пакеты и график повышения цен | I148: 25.05.2026 03:00 | J148: 28.05.2026 | L148: Действие | M148: Низкий | N148: N | P148: 28.04.2026 11:22:22 | R148: Нелли | S148: Екатерина, Нелли | V148: N | W148: N | Y148: PRE, РГП, страт-п-с-26-09 | AA148: 2026-04-28 11:22:22: Екатерина создал(-а) задачу; 2026-04-28 11:26:43: Екатерина добавил(-а) тег PRE; 2026-04-28 18:44:05: Екатерина изменил(-а) название на 5.02. Утвердить Пакеты и график повышения цен; 2026-04-28 18:44:19: Екатерина переместил(-а) задачу в проекте ЛИЧНО сентябрь 24.09.2026 в колонку Дивизион Конференции / К работе; 2026-04-29 11:34:10: Екатерина изменил(-а) дату на 28.04.2026; 2026-04-29 11:34:10: Екатерина изменил(-а) дату на 28.04.2026; 2026-04-29 11:34:15: Екатерина изменил(-а) дату на 28.04.2026 - 01.05.2026; 2026-04-29 11:35:12: Екатерина изменил(-а) дату на 28.04.2026 - 27.05.2026; 2026-04-29 11:35:17: Екатерина изменил(-а) дату на 25.05.2026 - 27.05.2026; 2026-04-29 11:35:20: Екатерина изменил(-а) дату на 25.05.2026 - 28.05.2026; 2026-04-29 13:27:18: Екатерина добавил(-а) тег РГП; 2026-04-29 13:27:18: Екатерина добавил(-а) тег Продюсер; 2026-04-29 13:27:21: Екатерина убрал(-а) тег Продюсер; 2026-04-29 13:27:21: Екатерина добавил(-а) тег страт-п-с-26-09; 2026-04-30 10:33:48: Екатерина назначил(-а) Нелли исполнителем | AB148: Лично сентябрь 2026 | AC148: =VLOOKUP(Y148,'впр данные'!A:B,2,1) -> РГП, страт-п-с-26-09 | AD148: =VLOOKUP(Y148,'впр данные'!A:C,3,1) -> РГП
A149: 188 | B149: ЛИЧНО сентябрь 24.09.2026 | C149: Дивизион Конференции | D149: К работе | G149: Екатерина | H149: 5.03. Декомпозировать планы и занести в реестр | I149: 25.05.2026 03:00 | J149: 28.05.2026 | L149: Действие | M149: Низкий | N149: N | P149: 28.04.2026 11:21:55 | R149: Нелли | S149: Екатерина, Нелли | V149: N | W149: N | Y149: PRE, РГП, страт-п-с-26-09 | AA149: 2026-04-28 11:21:55: Екатерина создал(-а) задачу; 2026-04-28 11:26:48: Екатерина добавил(-а) тег PRE; 2026-04-28 18:44:09: Екатерина изменил(-а) название на 53. Декомпозировать планы и занести в реестр; 2026-04-28 18:44:12: Екатерина изменил(-а) название на 5.03. Декомпозировать планы и занести в реестр; 2026-04-28 18:44:21: Екатерина переместил(-а) задачу в проекте ЛИЧНО сентябрь 24.09.2026 в колонку Дивизион Конференции / К работе; 2026-04-29 11:35:25: Екатерина изменил(-а) дату на 26.05.2026; 2026-04-29 11:35:28: Екатерина изменил(-а) дату на 25.05.2026 - 26.05.2026; 2026-04-29 11:35:29: Екатерина изменил(-а) дату на 25.05.2026 - 28.05.2026; 2026-04-29 13:28:15: Екатерина добавил(-а) тег РГП; 2026-04-29 13:28:17: Екатерина добавил(-а) тег страт-п-с-26-09; 2026-04-30 10:33:54: Екатерина назначил(-а) Нелли исполнителем | AB149: Лично сентябрь 2026 | AC149: =VLOOKUP(Y149,'впр данные'!A:B,2,1) -> РГП, страт-п-с-26-09 | AD149: =VLOOKUP(Y149,'впр данные'!A:C,3,1) -> РГП
A150: 187 | B150: ЛИЧНО сентябрь 24.09.2026 | C150: Дивизион Конференции | D150: К работе | G150: Екатерина | H150: 5.04. Утвердить Мотивацию и занесети в документы | I150: 01.06.2026 03:00 | J150: 04.06.2026 | L150: Действие | M150: Низкий | N150: N | P150: 28.04.2026 11:21:41 | R150: Нелли | S150: Екатерина, Нелли | V150: N | W150: N | Y150: PRE, РГП, страт-п-с-26-09 | AA150: 2026-04-28 11:21:41: Екатерина создал(-а) задачу; 2026-04-28 11:26:53: Екатерина добавил(-а) тег PRE; 2026-04-28 17:35:58: Екатерина изменил(-а) название на 5.04. Утвердить Мотивацию и занесети в документы; 2026-04-28 18:44:24: Екатерина переместил(-а) задачу в проекте ЛИЧНО сентябрь 24.09.2026 в колонку Дивизион Конференции / К работе; 2026-04-29 12:37:22: Екатерина изменил(-а) дату на 30.05.2026; 2026-04-29 12:37:29: Екатерина изменил(-а) дату на 30.05.2026 - 04.06.2026; 2026-04-29 12:37:32: Екатерина изменил(-а) дату на 31.05.2026 - 04.06.2026; 2026-04-29 12:37:35: Екатерина изменил(-а) дату на 01.06.2026 - 04.06.2026; 2026-04-29 13:28:21: Екатерина добавил(-а) тег РГП; 2026-04-29 13:28:21: Екатерина добавил(-а) тег Продюсер; 2026-04-29 13:28:29: Екатерина убрал(-а) тег Продюсер; 2026-04-29 13:28:32: Екатерина добавил(-а) тег страт-п-с-26-09; 2026-04-30 10:33:57: Екатерина назначил(-а) Нелли исполнителем | AB150: Лично сентябрь 2026 | AC150: =VLOOKUP(Y150,'впр данные'!A:B,2,1) -> РГП, страт-п-с-26-09 | AD150: =VLOOKUP(Y150,'впр данные'!A:C,3,1) -> РГП
A151: 186 | B151: ЛИЧНО сентябрь 24.09.2026 | C151: Дивизион Конференции | D151: К работе | G151: Екатерина | H151: 5.05. Формулировки передать в 1С | I151: 01.06.2026 03:00 | J151: 04.06.2026 | L151: Действие | M151: Низкий | N151: N | P151: 28.04.2026 11:21:25 | R151: Нелли | S151: Екатерина, Нелли | V151: N | W151: N | Y151: PRE, РГП, страт-п-с-26-09 | AA151: 2026-04-28 11:21:26: Екатерина создал(-а) задачу; 2026-04-28 11:27:06: Екатерина добавил(-а) тег PRE; 2026-04-28 17:33:43: Екатерина изменил(-а) название на 5.05. Формулировки передать в 1С; 2026-04-28 18:44:28: Екатерина переместил(-а) задачу в проекте ЛИЧНО сентябрь 24.09.2026 в колонку Дивизион Конференции / К работе; 2026-04-29 12:37:39: Екатерина изменил(-а) дату на 17.06.2026; 2026-04-29 12:59:19: Екатерина изменил(-а) дату на 14.06.2026 - 17.06.2026; 2026-04-29 12:59:27: Екатерина изменил(-а) дату на 01.06.2026 - 17.06.2026; 2026-04-29 12:59:36: Екатерина изменил(-а) дату на 01.06.2026 - 09.06.2026; 2026-04-29 12:59:42: Екатерина изменил(-а) дату на 01.06.2026 - 04.06.2026; 2026-04-29 13:31:01: Екатерина добавил(-а) тег страт-п-с-26-09; 2026-04-29 13:31:01: Екатерина добавил(-а) тег РГП; 2026-04-30 10:34:01: Екатерина назначил(-а) Нелли исполнителем; 2026-04-30 14:41:03: Екатерина убрал(-а) тег страт-п-с-26-09; 2026-04-30 14:41:06: Екатерина добавил(-а) тег страт-п-с-26-09 | AB151: Лично сентябрь 2026 | AC151: =VLOOKUP(Y151,'впр данные'!A:B,2,1) -> РГП, страт-п-с-26-09 | AD151: =VLOOKUP(Y151,'впр данные'!A:C,3,1) -> РГП
A152: 185 | B152: ЛИЧНО сентябрь 24.09.2026 | C152: Дивизион Конференции | D152: К работе | G152: Екатерина | H152: 5.06. Создать Товары в CRM | I152: 01.06.2026 03:00 | J152: 04.06.2026 | L152: Действие | M152: Низкий | N152: N | P152: 28.04.2026 11:21:10 | R152: Нелли | S152: Екатерина, Нелли | V152: N | W152: N | Y152: PRE, РГП, страт-п-с-26-09 | AA152: 2026-04-28 11:21:10: Екатерина создал(-а) задачу; 2026-04-28 11:27:12: Екатерина добавил(-а) тег PRE; 2026-04-28 17:33:54: Екатерина изменил(-а) название на 5.06. Создать Товары в CRM; 2026-04-28 18:44:30: Екатерина переместил(-а) задачу в проекте ЛИЧНО сентябрь 24.09.2026 в колонку Дивизион Конференции / К работе; 2026-04-29 12:58:44: Екатерина изменил(-а) дату на 01.06.2026; 2026-04-29 12:58:47: Екатерина изменил(-а) дату на 01.06.2026 - 04.06.2026; 2026-04-29 13:31:10: Екатерина добавил(-а) тег РГП; 2026-04-29 13:31:11: Екатерина убрал(-а) тег РГП; 2026-04-29 13:31:11: Екатерина добавил(-а) тег страт-п-с-26-09; 2026-04-29 13:31:17: Екатерина добавил(-а) тег РГП; 2026-04-30 10:34:07: Екатерина назначил(-а) Нелли исполнителем; 2026-04-30 14:41:14: Екатерина убрал(-а) тег страт-п-с-26-09; 2026-04-30 14:41:16: Екатерина добавил(-а) тег страт-п-с-26-09 | AB152: Лично сентябрь 2026 | AC152: =VLOOKUP(Y152,'впр данные'!A:B,2,1) -> РГП, страт-п-с-26-09 | AD152: =VLOOKUP(Y152,'впр данные'!A:C,3,1) -> РГП
A153: 184 | B153: ЛИЧНО сентябрь 24.09.2026 | C153: Дивизион Конференции | D153: К работе | G153: Екатерина | H153: 5.07. Подготовить Воронку в CRM | I153: 08.06.2026 03:00 | J153: 11.06.2026 | L153: Действие | M153: Низкий | N153: N | P153: 28.04.2026 11:20:57 | R153: Нелли | S153: Екатерина, Нелли | V153: N | W153: N | Y153: PRE, РГП, страт-п-с-26-09 | AA153: 2026-04-28 11:20:57: Екатерина создал(-а) задачу; 2026-04-28 11:27:17: Екатерина добавил(-а) тег PRE; 2026-04-28 17:34:00: Екатерина изменил(-а) название на 5.07. Подготовить Воронку в CRM; 2026-04-28 18:44:33: Екатерина переместил(-а) задачу в проекте ЛИЧНО сентябрь 24.09.2026 в колонку Дивизион Конференции / К работе; 2026-04-29 12:59:54: Екатерина изменил(-а) дату на 08.06.2026; 2026-04-29 12:59:57: Екатерина изменил(-а) дату на 08.06.2026 - 11.06.2026; 2026-04-29 13:31:23: Екатерина добавил(-а) тег РГП; 2026-04-29 13:31:24: Екатерина добавил(-а) тег страт-п-с-26-09; 2026-04-30 10:34:11: Екатерина назначил(-а) Нелли исполнителем | AB153: Лично сентябрь 2026 | AC153: =VLOOKUP(Y153,'впр данные'!A:B,2,1) -> РГП, страт-п-с-26-09 | AD153: =VLOOKUP(Y153,'впр данные'!A:C,3,1) -> РГП
A154: 183 | B154: ЛИЧНО сентябрь 24.09.2026 | C154: Дивизион Конференции | D154: К работе | G154: Екатерина | H154: 5.08. Закреп с Сейл-китом выложить в рабочий чат | I154: 08.06.2026 03:00 | J154: 11.06.2026 | L154: Действие | M154: Низкий | N154: N | P154: 28.04.2026 11:20:42 | R154: Нелли | S154: Екатерина, Нелли | V154: N | W154: N | Y154: PRE, РГП, страт-п-с-26-09 | AA154: 2026-04-28 11:20:42: Екатерина создал(-а) задачу; 2026-04-28 11:27:22: Екатерина добавил(-а) тег PRE; 2026-04-28 17:34:11: Екатерина изменил(-а) название на 5.08. Закреп с Сейл-китом выложить в рабочий чат; 2026-04-28 18:44:41: Екатерина переместил(-а) задачу в проекте ЛИЧНО сентябрь 24.09.2026 в колонку Дивизион Конференции / К работе; 2026-04-29 13:00:00: Екатерина изменил(-а) дату на 08.06.2026; 2026-04-29 13:00:01: Екатерина изменил(-а) дату на 08.06.2026 - 11.06.2026; 2026-04-29 13:31:34: Екатерина добавил(-а) тег РГП; 2026-04-29 13:31:36: Екатерина добавил(-а) тег страт-п-с-26-09; 2026-04-30 10:34:14: Екатерина назначил(-а) Нелли исполнителем | AB154: Лично сентябрь 2026 | AC154: =VLOOKUP(Y154,'впр данные'!A:B,2,1) -> РГП, страт-п-с-26-09 | AD154: =VLOOKUP(Y154,'впр данные'!A:C,3,1) -> РГП
A155: 182 | B155: ЛИЧНО сентябрь 24.09.2026 | C155: Дивизион Конференции | D155: К работе | G155: Екатерина | H155: 5.09. Провести Обучение и тестирование менеджеров | I155: 15.06.2026 03:00 | J155: 18.06.2026 | L155: Действие | M155: Низкий | N155: N | P155: 28.04.2026 11:20:27 | R155: Нелли | S155: Екатерина, Нелли | V155: N | W155: N | Y155: PRE, РГП, страт-п-с-26-09 | AA155: 2026-04-28 11:20:27: Екатерина создал(-а) задачу; 2026-04-28 11:27:36: Екатерина добавил(-а) тег PRE; 2026-04-28 17:34:22: Екатерина изменил(-а) название на 5.09. Провести Обучение и тестирование менеджеров; 2026-04-28 18:44:44: Екатерина переместил(-а) задачу в проекте ЛИЧНО сентябрь 24.09.2026 в колонку Дивизион Конференции / К работе; 2026-04-29 13:00:02: Екатерина изменил(-а) дату на 08.06.2026; 2026-04-29 13:00:04: Екатерина изменил(-а) дату на 08.06.2026 - 11.06.2026; 2026-04-29 13:01:19: Екатерина изменил(-а) дату на 08.06.2026 - 14.06.2026; 2026-04-29 13:01:27: Екатерина изменил(-а) дату на 08.06.2026 - 18.06.2026; 2026-04-29 13:01:30: Екатерина изменил(-а) дату на 16.06.2026 - 18.06.2026; 2026-04-29 13:01:32: Екатерина изменил(-а) дату на 15.06.2026 - 18.06.2026; 2026-04-29 13:31:41: Екатерина добавил(-а) тег РГП; 2026-04-29 13:31:42: Екатерина добавил(-а) тег страт-п-с-26-09; 2026-04-30 10:34:17: Екатерина назначил(-а) Нелли исполнителем | AB155: Лично сентябрь 2026 | AC155: =VLOOKUP(Y155,'впр данные'!A:B,2,1) -> РГП, страт-п-с-26-09 | AD155: =VLOOKUP(Y155,'впр данные'!A:C,3,1) -> РГП
A156: 181 | B156: ЛИЧНО сентябрь 24.09.2026 | C156: Дивизион Конференции | D156: К работе | G156: Екатерина | H156: 5.10. Подготовить понедельный план набора | I156: 22.06.2026 03:00 | J156: 25.06.2026 | L156: Действие | M156: Низкий | N156: N | P156: 28.04.2026 11:20:15 | R156: Нелли | S156: Екатерина, Нелли | V156: N | W156: N | Y156: PRE, РГП, страт-п-с-26-09 | AA156: 2026-04-28 11:20:15: Екатерина создал(-а) задачу; 2026-04-28 11:26:29: Екатерина добавил(-а) тег PRE; 2026-04-28 18:44:48: Екатерина переместил(-а) задачу в проекте ЛИЧНО сентябрь 24.09.2026 в колонку Дивизион Конференции / К работе; 2026-04-29 13:01:41: Екатерина изменил(-а) дату на 22.06.2026; 2026-04-29 13:01:44: Екатерина изменил(-а) дату на 22.06.2026 - 26.06.2026; 2026-04-29 13:02:04: Екатерина изменил(-а) дату на 22.06.2026 - 25.06.2026; 2026-04-29 13:31:47: Екатерина добавил(-а) тег РГП; 2026-04-29 13:31:47: Екатерина добавил(-а) тег страт-п-с-26-09; 2026-04-30 10:34:20: Екатерина назначил(-а) Нелли исполнителем | AB156: Лично сентябрь 2026 | AC156: =VLOOKUP(Y156,'впр данные'!A:B,2,1) -> РГП, страт-п-с-26-09 | AD156: =VLOOKUP(Y156,'впр данные'!A:C,3,1) -> РГП
A157: 180 | B157: ЛИЧНО сентябрь 24.09.2026 | C157: Дивизион Конференции | D157: К работе | G157: Екатерина | H157: 5.11. Провести индивидуальный разбор воронки каждого менеджера | I157: 27.07.2026 03:00 | J157: 30.07.2026 | L157: Действие | M157: Низкий | N157: N | P157: 28.04.2026 11:19:56 | R157: Нелли | S157: Екатерина, Нелли | V157: N | W157: N | Y157: PRO, РГП, страт-п-с-26-09 | AA157: 2026-04-28 11:19:56: Екатерина создал(-а) задачу; 2026-04-28 11:26:23: Екатерина добавил(-а) тег PRO; 2026-04-28 18:44:51: Екатерина переместил(-а) задачу в проекте ЛИЧНО сентябрь 24.09.2026 в колонку Дивизион Конференции / К работе; 2026-04-29 13:03:02: Екатерина изменил(-а) дату на 27.07.2026; 2026-04-29 13:03:08: Екатерина изменил(-а) дату на 27.07.2026 - 30.07.2026; 2026-04-29 13:31:53: Екатерина добавил(-а) тег РГП; 2026-04-29 13:31:54: Екатерина добавил(-а) тег страт-п-с-26-09; 2026-04-30 10:34:22: Екатерина назначил(-а) Нелли исполнителем | AB157: Лично сентябрь 2026 | AC157: =VLOOKUP(Y157,'впр данные'!A:B,2,1) -> РГП, страт-п-с-26-09 | AD157: =VLOOKUP(Y157,'впр данные'!A:C,3,1) -> РГП
A158: 179 | B158: ЛИЧНО сентябрь 24.09.2026 | C158: Дивизион Конференции | D158: К работе | G158: Екатерина | H158: 5.12. Провести летучку с менеджерами | I158: 27.07.2026 03:00 | J158: 30.07.2026 | L158: Действие | M158: Низкий | N158: N | P158: 28.04.2026 11:19:43 | R158: Нелли | S158: Екатерина, Нелли | V158: N | W158: N | Y158: PRO, РГП, страт-п-с-26-09 | AA158: 2026-04-28 11:19:44: Екатерина создал(-а) задачу; 2026-04-28 11:26:34: Екатерина добавил(-а) тег PRO; 2026-04-28 18:44:56: Екатерина переместил(-а) задачу в проекте ЛИЧНО сентябрь 24.09.2026 в колонку Дивизион Конференции / К работе; 2026-04-29 13:03:11: Екатерина изменил(-а) дату на 27.07.2026; 2026-04-29 13:03:14: Екатерина изменил(-а) дату на 27.07.2026 - 30.07.2026; 2026-04-29 13:32:02: Екатерина добавил(-а) тег РГП; 2026-04-29 13:32:03: Екатерина добавил(-а) тег страт-п-с-26-09; 2026-04-30 10:34:28: Екатерина назначил(-а) Нелли исполнителем | AB158: Лично сентябрь 2026 | AC158: =VLOOKUP(Y158,'впр данные'!A:B,2,1) -> РГП, страт-п-с-26-09 | AD158: =VLOOKUP(Y158,'впр данные'!A:C,3,1) -> РГП
A159: 178 | B159: ЛИЧНО сентябрь 24.09.2026 | C159: Дивизион Конференции | D159: К работе | G159: Екатерина | H159: 5.13. Проконтролировать выполнение отчета по отказам | I159: 27.07.2026 03:00 | J159: 30.07.2026 | L159: Действие | M159: Низкий | N159: N | P159: 28.04.2026 11:19:27 | R159: Нелли | S159: Екатерина, Нелли | V159: N | W159: N | Y159: PRO, РГП, страт-п-с-26-09 | AA159: 2026-04-28 11:19:28: Екатерина создал(-а) задачу; 2026-04-28 11:27:45: Екатерина добавил(-а) тег PRO; 2026-04-28 18:45:51: Екатерина переместил(-а) задачу в проекте ЛИЧНО сентябрь 24.09.2026 в колонку Дивизион Конференции / К работе; 2026-04-29 13:03:17: Екатерина изменил(-а) дату на 27.07.2026; 2026-04-29 13:03:19: Екатерина изменил(-а) дату на 27.07.2026 - 30.07.2026; 2026-04-29 13:32:09: Екатерина добавил(-а) тег РГП; 2026-04-29 13:32:10: Екатерина добавил(-а) тег страт-п-с-26-09; 2026-04-30 10:34:35: Екатерина назначил(-а) Нелли исполнителем | AB159: Лично сентябрь 2026 | AC159: =VLOOKUP(Y159,'впр данные'!A:B,2,1) -> РГП, страт-п-с-26-09 | AD159: =VLOOKUP(Y159,'впр данные'!A:C,3,1) -> РГП
... A187: 150 | B187: ЛИЧНО сентябрь 24.09.2026 | C187: Дивизион Конференции | D187: К работе | G187: Екатерина | H187: 5.41. Актуализировать Мастердату | I187: 28.09.2026 03:00 | J187: 01.10.2026 | L187: Действие | M187: Низкий | N187: N | P187: 28.04.2026 11:10:03 | R187: Нелли | S187: Екатерина, Нелли | V187: N | W187: N | Y187: POST, РГП, страт-п-с-26-09 | AA187: 2026-04-28 11:10:03: Екатерина создал(-а) задачу; 2026-04-28 11:23:58: Екатерина добавил(-а) тег POST; 2026-04-28 18:47:21: Екатерина переместил(-а) задачу в проекте ЛИЧНО сентябрь 24.09.2026 в колонку Дивизион Конференции / К работе; 2026-04-29 13:13:51: Екатерина изменил(-а) дату на 28.09.2026; 2026-04-29 13:13:53: Екатерина изменил(-а) дату на 28.09.2026 - 01.10.2026; 2026-04-29 13:32:42: Екатерина добавил(-а) тег РГП; 2026-04-29 13:32:44: Екатерина добавил(-а) тег страт-п-с-26-09; 2026-04-30 10:34:47: Екатерина назначил(-а) Нелли исполнителем | AB187: Лично сентябрь 2026 | AC187: =VLOOKUP(Y187,'впр данные'!A:B,2,1) -> РГП, страт-п-с-26-09 | AD187: =VLOOKUP(Y187,'впр данные'!A:C,3,1) -> РГП
A188: 149 | G188: Екатерина | H188: 2.6.2. Провести 40% телефонные интервью с целью выявления актуальной проблематики. Оптимальное количество завершенных интервью - 40. Протяженность интервью - не менее 10-15 минут. | L188: Действие | M188: Низкий | N188: N | P188: 27.04.2026 17:58:52 | S188: Екатерина | V188: N | W188: N | AA188: 2026-04-27 17:58:53: Екатерина создал(-а) задачу; 2026-04-28 18:58:50: Екатерина убрал(-а) родительскую задачу | AB188: Лично сентябрь 2026 | AC188: =VLOOKUP(Y188,'впр данные'!A:B,2,1) -> #N/A | AD188: =VLOOKUP(Y188,'впр данные'!A:C,3,1) -> #N/A
A189: 148 | E189: 2.06. Провести 40% глубинных интервью | F189: 2.06. Провести 40% глубинных интервью | G189: Екатерина | H189: 2.6.1. Запросить базу данных КВК Империя у отдела лидогенерации для проведения телефонного интервью. | J189: 01.06.2026 | L189: Действие | M189: Низкий | N189: N | P189: 27.04.2026 17:58:25 | S189: Екатерина | V189: N | W189: N | AA189: 2026-04-27 17:58:26: Екатерина создал(-а) задачу; 2026-04-28 19:47:01: Екатерина изменил(-а) дату на 01.06.2026 | AB189: Лично сентябрь 2026 | AC189: =VLOOKUP(Y189,'впр данные'!A:B,2,1) -> #N/A | AD189: =VLOOKUP(Y189,'впр данные'!A:C,3,1) -> #N/A
A190: 147 | B190: ЛИЧНО сентябрь 24.09.2026 | E190: 2.02. Отдать лидгенам ТЗ на Тизер-сайт и согласовать колонтитул мероприятия для печатных материалов | F190: 2.02. Отдать лидгенам ТЗ на Тизер-сайт и согласовать колонтитул мероприятия для печатных материалов | G190: Екатерина | H190: 2.2.4. С руководителем отдела лидогенерации согласовать ответственного за разработку тизер-сайта и зафиксировать сроки разработки | L190: Действие | M190: Низкий | N190: N | P190: 27.04.2026 17:55:54 | S190: Екатерина | V190: N | W190: N | Y190: PRE, Продюсер, страт-п-с-26-09 | AA190: 2026-04-27 17:55:54: Екатерина создал(-а) задачу; 2026-04-28 19:25:08: Екатерина добавил(-а) тег PRE; 2026-04-28 19:28:59: Екатерина добавил(-а) тег Продюсер; 2026-04-28 19:28:59: Екатерина добавил(-а) тег страт-п-с-26-09; 2026-04-28 19:38:10: Екатерина добавил(-а) задачу в проект ЛИЧНО сентябрь 24.09.2026 | AB190: Лично сентябрь 2026 | AC190: =VLOOKUP(Y190,'впр данные'!A:B,2,1) -> продюсер, страт-п-с-26-09 | AD190: =VLOOKUP(Y190,'впр данные'!A:C,3,1) -> продюсер
A191: 146 | B191: ЛИЧНО сентябрь 24.09.2026 | E191: 2.02. Отдать лидгенам ТЗ на Тизер-сайт и согласовать колонтитул мероприятия для печатных материалов | F191: 2.02. Отдать лидгенам ТЗ на Тизер-сайт и согласовать колонтитул мероприятия для печатных материалов | G191: Екатерина | H191: 2.2.3. Согласовать колонтитул, сделанный дизайнером | L191: Действие | M191: Низкий | N191: N | P191: 27.04.2026 17:54:50 | S191: Екатерина | V191: N | W191: N | Y191: PRE, Продюсер, страт-п-с-26-09 | AA191: 2026-04-27 17:54:50: Екатерина создал(-а) задачу; 2026-04-27 17:55:13: Екатерина изменил(-а) название на 2.2.3. Согласовать колонтитул,; 2026-04-27 17:55:14: Екатерина изменил(-а) название на 2.2.3. Согласовать колонтитул, л сделанный дизайнером; 2026-04-27 17:55:17: Екатерина изменил(-а) название на 2.2.3. Согласовать колонтитул, сделанный дизайнером; 2026-04-28 19:25:05: Екатерина добавил(-а) тег PRE; 2026-04-28 19:28:46: Екатерина добавил(-а) тег Продюсер; 2026-04-28 19:28:47: Екатерина добавил(-а) тег страт-п-с-26-09; 2026-04-28 19:38:04: Екатерина добавил(-а) задачу в проект ЛИЧНО сентябрь 24.09.2026 | AB191: Лично сентябрь 2026 | AC191: =VLOOKUP(Y191,'впр данные'!A:B,2,1) -> продюсер, страт-п-с-26-09 | AD191: =VLOOKUP(Y191,'впр данные'!A:C,3,1) -> продюсер
A192: 145 | B192: ЛИЧНО сентябрь 24.09.2026 | E192: 2.02. Отдать лидгенам ТЗ на Тизер-сайт и согласовать колонтитул мероприятия для печатных материалов | F192: 2.02. Отдать лидгенам ТЗ на Тизер-сайт и согласовать колонтитул мероприятия для печатных материалов | G192: Екатерина | H192: 2.2.2. Сделать ТЗ на колонтитул мероприятия в формате Word (по шаблону от дизайнера) и отправить дизайнеру | L192: Действие | M192: Низкий | N192: N | P192: 27.04.2026 17:54:47 | S192: Екатерина | V192: N | W192: N | Y192: PRE, Продюсер, страт-п-с-26-09 | AA192: 2026-04-27 17:54:47: Екатерина создал(-а) задачу; 2026-04-28 19:25:02: Екатерина добавил(-а) тег PRE; 2026-04-28 19:26:25: Екатерина добавил(-а) тег Продюсер; 2026-04-28 19:26:28: Екатерина добавил(-а) тег страт-п-с-26-09; 2026-04-28 19:37:59: Екатерина добавил(-а) задачу в проект ЛИЧНО сентябрь 24.09.2026 | AB192: Лично сентябрь 2026 | AC192: =VLOOKUP(Y192,'впр данные'!A:B,2,1) -> продюсер, страт-п-с-26-09 | AD192: =VLOOKUP(Y192,'впр данные'!A:C,3,1) -> продюсер
A193: 144 | B193: ЛИЧНО сентябрь 24.09.2026 | E193: 2.02. Отдать лидгенам ТЗ на Тизер-сайт и согласовать колонтитул мероприятия для печатных материалов | F193: 2.02. Отдать лидгенам ТЗ на Тизер-сайт и согласовать колонтитул мероприятия для печатных материалов | G193: Екатерина | H193: 2.2.1. Согласно ТЗ создать и заполнить Word-документ "Тизер-сайт" по форме, утвержденной в методичке Продюсинга. | L193: Действие | M193: Низкий | N193: N | P193: 27.04.2026 17:54:40 | S193: Екатерина | V193: N | W193: N | Y193: PRE, Продюсер, страт-п-с-26-09 | AA193: 2026-04-27 17:54:40: Екатерина создал(-а) задачу; 2026-04-28 19:25:00: Екатерина добавил(-а) тег PRE; 2026-04-28 19:26:16: Екатерина добавил(-а) тег Продюсер; 2026-04-28 19:26:19: Екатерина добавил(-а) тег страт-п-с-26-09; 2026-04-28 19:37:56: Екатерина добавил(-а) задачу в проект ЛИЧНО сентябрь 24.09.2026 | AB193: Лично сентябрь 2026 | AC193: =VLOOKUP(Y193,'впр данные'!A:B,2,1) -> продюсер, страт-п-с-26-09 | AD193: =VLOOKUP(Y193,'впр данные'!A:C,3,1) -> продюсер
A194: 133 | B194: ЛИЧНО сентябрь 24.09.2026 | C194: Дивизион Конференции | D194: К работе | G194: Екатерина | H194: 2.02. Отдать лидгенам ТЗ на Тизер-сайт и согласовать колонтитул мероприятия для печатных материалов | I194: 18.05.2026 03:00 | J194: 21.05.2026 | L194: Действие | M194: Низкий | N194: N | P194: 27.04.2026 16:59:06 | S194: Екатерина | V194: N | W194: N | Y194: PRE, Продюсер, страт-п-с-26-09 | AA194: 2026-04-27 16:59:06: Екатерина создал(-а) задачу; 2026-04-27 16:59:30: Екатерина изменил(-а) название на 2.2. Отдать ТЗ лидгенам на Тизер-сайт и согласован колонтитул мероприятия для печатных материалов; 2026-04-27 16:59:39: Екатерина изменил(-а) название на 2.2. Отдать лидгенам ТЗ лидгенам на Тизер-сайт и согласован колонтитул мероприятия для печатных материалов; 2026-04-27 16:59:44: Екатерина изменил(-а) название на 2.2. Отдать лидгенам ТЗ на Тизер-сайт и согласован колонтитул мероприятия для печатных материалов; 2026-04-27 16:59:48: Екатерина изменил(-а) название на 2.2. Отдать лидгенам ТЗ на Тизер-сайт и согласовать колонтитул мероприятия для печатных материалов; 2026-04-27 17:00:41: Екатерина изменил(-а) название на 2.2.Отдать лидгенам ТЗ на Тизер-сайт и согласовать колонтитул мероприятия для печатных материалов; 2026-04-27 17:00:42: Екатерина изменил(-а) название на 2.2Отдать лидгенам ТЗ на Тизер-сайт и согласовать колонтитул мероприятия для печатных материалов; 2026-04-27 17:00:43: Екатерина изменил(-а) название на 2.2.Отдать лидгенам ТЗ на Тизер-сайт и согласовать колонтитул мероприятия для печатных материалов; 2026-04-27 17:00:43: Екатерина изменил(-а) название на 2.2. Отдать лидгенам ТЗ на Тизер-сайт и согласовать колонтитул мероприятия для печатных материалов; 2026-04-27 17:01:38: Екатерина изменил(-а) дату на 22.05.2026; 2026-04-27 17:02:47: Екатерина добавил(-а) тег PRE; 2026-04-27 17:54:40: Екатерина добавил(-а) подзадачу #144 2.2.1. Согласно ТЗ создать и заполнить Word-документ "Тизер-сайт" по форме, утвержденной в методичке Продюсинга.; 2026-04-27 17:54:47: Екатерина добавил(-а) подзадачу #145 2.2.2. Сделать ТЗ на колонтитул мероприятия в формате Word (по шаблону от дизайнера) и отправить дизайнеру; 2026-04-27 17:54:50: Екатерина добавил(-а) подзадачу #146 2.2.3. Согласовать колонтитул, сделанный дизайнером; 2026-04-27 17:55:54: Екатерина добавил(-а) подзадачу #147 2.2.4. С руководителем отдела лидогенерации согласовать ответственного за разработку тизер-сайта и зафиксировать сроки разработки; 2026-04-28 18:47:26: Екатерина переместил(-а) задачу в проекте ЛИЧНО сентябрь 24.09.2026 в колонку Дивизион Конференции / К работе; 2026-04-28 19:04:20: Екатерина изменил(-а) название на 2.02. Отдать лидгенам ТЗ на Тизер-сайт и согласовать колонтитул мероприятия для печатных материалов; 2026-04-28 19:25:32: Екатерина добавил(-а) тег Продюсер; 2026-04-28 19:25:58: Екатерина добавил(-а) тег страт-п-с-26-09; 2026-04-28 19:37:40: Екатерина изменил(-а) дату на 18.05.2026; 2026-04-28 19:37:43: Екатерина изменил(-а) дату на 18.05.2026 - 18.05.2026; 2026-04-28 19:37:44: Екатерина изменил(-а) дату на 18.05.2026 - 21.05.2026 | AB194: Лично сентябрь 2026 | AC194: =VLOOKUP(Y194,'впр данные'!A:B,2,1) -> продюсер, страт-п-с-26-09 | AD194: =VLOOKUP(Y194,'впр данные'!A:C,3,1) -> продюсер
A195: 128 | B195: ЛИЧНО сентябрь 24.09.2026 | C195: Дивизион Конференции | D195: К работе | G195: Екатерина | H195: 2.07. Сдать и утвердить с лидгеном Тизер сайт и проконтрол. его публикацию в календаре на соотв. сайте компании | I195: 01.06.2026 03:00 | J195: 04.06.2026 | L195: Действие | M195: Низкий | N195: N | P195: 27.04.2026 16:58:00 | S195: Екатерина | V195: N | W195: N | Y195: PRE, Продюсер, страт-п-с-26-09 | AA195: 2026-04-27 16:58:01: Екатерина создал(-а) задачу; 2026-04-27 16:58:05: Екатерина изменил(-а) название на 2.7. Сдать и утвердить с лидгеном Тизер сайт и проконтрол. его публикацию в календаре на соотв. сайте компании; 2026-04-27 17:04:21: Екатерина изменил(-а) дату на 05.06.2026; 2026-04-27 17:04:25: Екатерина добавил(-а) тег PRE; 2026-04-28 18:47:56: Екатерина переместил(-а) задачу в проекте ЛИЧНО сентябрь 24.09.2026 в колонку Дивизион Конференции / К работе; 2026-04-28 18:57:17: Екатерина изменил(-а) название на 2.07. Сдать и утвердить с лидгеном Тизер сайт и проконтрол. его публикацию в календаре на соотв. сайте компании; 2026-04-28 19:44:27: Екатерина добавил(-а) тег Продюсер; 2026-04-28 19:44:27: Екатерина убрал(-а) тег Продюсер; 2026-04-28 19:44:27: Екатерина добавил(-а) тег страт-п-с-26-09; 2026-04-28 19:44:32: Екатерина добавил(-а) тег Продюсер; 2026-04-28 19:47:25: Екатерина изменил(-а) дату на 01.06.2026; 2026-04-28 19:47:28: Екатерина изменил(-а) дату на 01.06.2026 - 01.06.2026; 2026-04-28 19:47:28: Екатерина изменил(-а) дату на 01.06.2026 - 04.06.2026; 2026-04-30 14:34:29: Екатерина убрал(-а) тег страт-п-с-26-09; 2026-04-30 14:34:35: Екатерина добавил(-а) тег страт-п-с-26-09 | AB195: Лично сентябрь 2026 | AC195: =VLOOKUP(Y195,'впр данные'!A:B,2,1) -> продюсер, страт-п-с-26-09 | AD195: =VLOOKUP(Y195,'впр данные'!A:C,3,1) -> продюсер
A196: 127 | B196: ЛИЧНО сентябрь 24.09.2026 | C196: Дивизион Конференции | D196: К работе | G196: Екатерина | H196: 2.08. Провести 100% глубинных интервью | I196: 08.06.2026 03:00 | J196: 11.06.2026 | L196: Действие | M196: Низкий | N196: N | P196: 27.04.2026 16:57:38 | S196: Екатерина | V196: N | W196: N | Y196: PRE, Продюсер, страт-п-с-26-09 | AA196: 2026-04-27 16:57:38: Екатерина создал(-а) задачу; 2026-04-27 17:07:44: Екатерина изменил(-а) дату на 12.06.2026; 2026-04-27 17:07:47: Екатерина добавил(-а) тег PRE; 2026-04-28 18:48:02: Екатерина переместил(-а) задачу в проекте ЛИЧНО сентябрь 24.09.2026 в колонку Дивизион Конференции / К работе; 2026-04-28 18:57:21: Екатерина изменил(-а) название на 2.08. Провести 100% глубинных интервью; 2026-04-28 19:44:41: Екатерина добавил(-а) тег страт-п-с-26-09; 2026-04-28 19:44:42: Екатерина добавил(-а) тег Продюсер; 2026-04-28 19:44:43: Екатерина добавил(-а) тег ШП; 2026-04-28 19:44:45: Екатерина убрал(-а) тег ШП; 2026-04-28 19:47:40: Екатерина изменил(-а) дату на 08.06.2026 - 12.06.2026; 2026-04-28 19:47:40: Екатерина изменил(-а) дату на 11.06.2026 - 12.06.2026; 2026-04-28 19:47:43: Екатерина изменил(-а) дату на 08.06.2026 - 12.06.2026; 2026-04-28 19:47:44: Екатерина изменил(-а) дату на 11.06.2026 - 12.06.2026; 2026-04-28 19:47:48: Екатерина изменил(-а) дату на 11.06.2026 - 11.06.2026; 2026-04-28 19:47:50: Екатерина изменил(-а) дату на 08.06.2026 - 11.06.2026; 2026-04-30 14:34:44: Екатерина убрал(-а) тег страт-п-с-26-09; 2026-04-30 14:35:20: Екатерина добавил(-а) тег страт-п-с-26-09 | AB196: Лично сентябрь 2026 | AC196: =VLOOKUP(Y196,'впр данные'!A:B,2,1) -> продюсер, страт-п-с-26-09 | AD196: =VLOOKUP(Y196,'впр данные'!A:C,3,1) -> продюсер
A197: 124 | B197: ЛИЧНО сентябрь 24.09.2026 | C197: Дивизион Конференции | D197: К работе | G197: Екатерина | H197: 2.11 Сдать Концепцию и Программу | I197: 15.06.2026 03:00 | J197: 18.06.2026 | L197: Действие | M197: Низкий | N197: N | P197: 27.04.2026 16:52:37 | S197: Екатерина | V197: N | W197: N | Y197: PRE, Продюсер, старт вехи Pro | AA197: 2026-04-27 16:52:39: Екатерина создал(-а) задачу; 2026-04-27 17:08:26: Екатерина изменил(-а) дату на 19.06.2026; 2026-04-27 17:08:31: Екатерина добавил(-а) тег PRE; 2026-04-28 18:48:11: Екатерина переместил(-а) задачу в проекте ЛИЧНО сентябрь 24.09.2026 в колонку Дивизион Конференции / К работе; 2026-04-29 09:52:01: Екатерина добавил(-а) тег страт-п-с-26-09; 2026-04-29 09:52:13: Екатерина добавил(-а) тег Продюсер; 2026-04-29 10:19:53: Екатерина изменил(-а) дату на 15.06.2026 - 19.06.2026; 2026-04-29 10:19:55: Екатерина изменил(-а) дату на 15.06.2026 - 18.06.2026; 2026-04-30 14:35:59: Екатерина убрал(-а) тег страт-п-с-26-09; 2026-04-30 14:36:03: Екатерина добавил(-а) тег старт вехи Pro | AB197: Лично сентябрь 2026 | AC197: =VLOOKUP(Y197,'впр данные'!A:B,2,1) -> продюсер, страт-п-с-26-09 | AD197: =VLOOKUP(Y197,'впр данные'!A:C,3,1) -> продюсер
A198: 123 | B198: ЛИЧНО сентябрь 24.09.2026 | C198: Дивизион Конференции | D198: К работе | G198: Екатерина | H198: 2.12. Проверить публикацию на сайте Программы с надписью "планируемые спикеры" | I198: 15.06.2026 03:00 | J198: 18.06.2026 | L198: Действие | M198: Низкий | N198: N | P198: 27.04.2026 16:52:28 | S198: Екатерина | V198: N | W198: N | Y198: PRE, Продюсер, страт-п-с-26-09 | AA198: 2026-04-27 16:52:29: Екатерина создал(-а) задачу; 2026-04-27 17:08:40: Екатерина изменил(-а) дату на 12.06.2026; 2026-04-27 17:08:44: Екатерина добавил(-а) тег PRE; 2026-04-27 17:09:33: Екатерина изменил(-а) дату на 19.06.2026; 2026-04-28 16:14:54: Екатерина очистил(-а) название; 2026-04-28 16:14:55: Екатерина изменил(-а) название на 2.12. Проверить публикацию на сайте Программы с надписью "планируемые спикеры"; 2026-04-28 18:48:14: Екатерина переместил(-а) задачу в проекте ЛИЧНО сентябрь 24.09.2026 в колонку Дивизион Конференции / К работе; 2026-04-29 09:52:26: Екатерина добавил(-а) тег страт-п-с-26-09; 2026-04-29 09:52:30: Екатерина добавил(-а) тег Продюсер; 2026-04-29 10:20:04: Екатерина изменил(-а) дату на 15.06.2026 - 19.06.2026; 2026-04-29 10:20:04: Екатерина изменил(-а) дату на 15.06.2026 - 18.06.2026; 2026-04-30 14:36:08: Екатерина убрал(-а) тег страт-п-с-26-09; 2026-04-30 14:36:13: Екатерина добавил(-а) тег страт-п-с-26-09 | AB198: Лично сентябрь 2026 | AC198: =VLOOKUP(Y198,'впр данные'!A:B,2,1) -> продюсер, страт-п-с-26-09 | AD198: =VLOOKUP(Y198,'впр данные'!A:C,3,1) -> продюсер
A199: 122 | B199: ЛИЧНО сентябрь 24.09.2026 | C199: Дивизион Конференции | D199: К работе | G199: Екатерина | H199: 2.13. Провести Обучение по Программе мероприятия | I199: 22.06.2026 03:00 | J199: 25.06.2026 | L199: Действие | M199: Низкий | N199: N | P199: 27.04.2026 16:51:11 | S199: Екатерина | V199: N | W199: N | Y199: PRE, Продюсер, страт-п-с-26-09 | AA199: 2026-04-27 16:51:11: Екатерина создал(-а) задачу; 2026-04-27 16:51:17: Екатерина изменил(-а) название на 2.13. Провести Обучение по Программе мероприятия; 2026-04-27 17:27:31: Екатерина изменил(-а) дату на 26.06.2026; 2026-04-27 17:27:35: Екатерина добавил(-а) тег PRE; 2026-04-28 18:48:30: Екатерина переместил(-а) задачу в проекте ЛИЧНО сентябрь 24.09.2026 в колонку Дивизион Конференции / К работе; 2026-04-29 09:53:15: Екатерина добавил(-а) тег страт-п-с-26-09; 2026-04-29 09:53:15: Екатерина добавил(-а) тег Продюсер; 2026-04-29 10:20:35: Екатерина изменил(-а) дату на 22.06.2026 - 26.06.2026; 2026-04-29 10:20:36: Екатерина изменил(-а) дату на 22.06.2026 - 25.06.2026; 2026-04-30 14:36:21: Екатерина убрал(-а) тег страт-п-с-26-09; 2026-04-30 14:36:24: Екатерина добавил(-а) тег страт-п-с-26-09 | AB199: Лично сентябрь 2026 | AC199: =VLOOKUP(Y199,'впр данные'!A:B,2,1) -> продюсер, страт-п-с-26-09 | AD199: =VLOOKUP(Y199,'впр данные'!A:C,3,1) -> продюсер
A200: 121 | B200: ЛИЧНО сентябрь 24.09.2026 | C200: Дивизион Конференции | D200: К работе | G200: Екатерина | H200: 2.14. Разослать приглашения всем спикерам по программе | I200: 22.06.2026 03:00 | J200: 25.06.2026 | L200: Действие | M200: Низкий | N200: N | P200: 27.04.2026 16:51:09 | S200: Екатерина | V200: N | W200: N | Y200: PRE, Продюсер, страт-п-с-26-09 | AA200: 2026-04-27 16:51:09: Екатерина создал(-а) задачу; 2026-04-27 16:51:21: Екатерина изменил(-а) название на 2.14. Разослать приглашения всем спикерам по прогамме; 2026-04-27 17:27:47: Екатерина изменил(-а) дату на 26.06.2026; 2026-04-27 17:27:53: Екатерина добавил(-а) тег PRE; 2026-04-28 16:15:33: Екатерина изменил(-а) название на 2.14. Разослать приглашения всем спикерам по программе; 2026-04-28 18:48:57: Екатерина переместил(-а) задачу в проекте ЛИЧНО сентябрь 24.09.2026 в колонку Дивизион Конференции / К работе; 2026-04-29 09:53:20: Екатерина добавил(-а) тег страт-п-с-26-09; 2026-04-29 09:53:21: Екатерина добавил(-а) тег Продюсер; 2026-04-29 10:20:43: Екатерина изменил(-а) дату на 22.06.2026 - 26.06.2026; 2026-04-29 10:20:44: Екатерина изменил(-а) дату на 22.06.2026 - 25.06.2026; 2026-04-30 14:36:31: Екатерина убрал(-а) тег страт-п-с-26-09; 2026-04-30 14:36:34: Екатерина добавил(-а) тег страт-п-с-26-09 | AB200: Лично сентябрь 2026 | AC200: =VLOOKUP(Y200,'впр данные'!A:B,2,1) -> продюсер, страт-п-с-26-09 | AD200: =VLOOKUP(Y200,'впр данные'!A:C,3,1) -> продюсер
A201: 120 | B201: ЛИЧНО сентябрь 24.09.2026 | C201: Дивизион Конференции | D201: К работе | G201: Екатерина | H201: 2.15. Провести промеж. согласование схемы зала/залов с ШП | I201: 22.06.2026 03:00 | J201: 25.06.2026 | L201: Действие | M201: Низкий | N201: N | P201: 27.04.2026 16:51:03 | S201: Екатерина | V201: N | W201: N | Y201: PRE, Продюсер, страт-п-с-26-09 | AA201: 2026-04-27 16:51:03: Екатерина создал(-а) задачу; 2026-04-27 16:51:28: Екатерина изменил(-а) название на 2.15. Провести промеж. согласование схемы зала/залов с ШП; 2026-04-27 17:28:59: Екатерина изменил(-а) дату на 26.06.2026; 2026-04-27 17:29:13: Екатерина добавил(-а) тег PRE; 2026-04-28 18:49:00: Екатерина переместил(-а) задачу в проекте ЛИЧНО сентябрь 24.09.2026 в колонку Дивизион Конференции / К работе; 2026-04-29 09:53:25: Екатерина добавил(-а) тег страт-п-с-26-09; 2026-04-29 09:53:27: Екатерина добавил(-а) тег Продюсер; 2026-04-29 10:21:15: Екатерина изменил(-а) дату на 22.06.2026 - 26.06.2026; 2026-04-29 10:21:17: Екатерина изменил(-а) дату на 22.06.2026 - 25.06.2026; 2026-04-30 14:36:43: Екатерина убрал(-а) тег страт-п-с-26-09; 2026-04-30 14:36:46: Екатерина добавил(-а) тег страт-п-с-26-09 | AB201: Лично сентябрь 2026 | AC201: =VLOOKUP(Y201,'впр данные'!A:B,2,1) -> продюсер, страт-п-с-26-09 | AD201: =VLOOKUP(Y201,'впр данные'!A:C,3,1) -> продюсер
A202: 117 | B202: ЛИЧНО сентябрь 24.09.2026 | C202: Дивизион Конференции | D202: К работе | G202: Екатерина | H202: 2.18. Получить от спикеров не менее 90% подтверждений о прочтении сообщений | I202: 03.08.2026 03:00 | J202: 06.08.2026 | L202: Действие | M202: Низкий | N202: N | P202: 27.04.2026 16:50:33 | S202: Екатерина | V202: N | W202: N | Y202: PRO, Продюсер, страт-п-с-26-09 | AA202: 2026-04-27 16:50:33: Екатерина создал(-а) задачу; 2026-04-27 17:31:56: Екатерина изменил(-а) дату на 07.08.2026; 2026-04-27 17:32:01: Екатерина добавил(-а) тег PRE; 2026-04-27 17:34:59: Екатерина убрал(-а) тег PRE; 2026-04-27 17:35:01: Екатерина добавил(-а) тег PRO; 2026-04-28 18:49:15: Екатерина переместил(-а) задачу в проекте ЛИЧНО сентябрь 24.09.2026 в колонку Дивизион Конференции / К работе; 2026-04-29 09:55:23: Екатерина добавил(-а) тег страт-п-с-26-09; 2026-04-29 09:55:24: Екатерина добавил(-а) тег Продюсер; 2026-04-29 10:22:07: Екатерина изменил(-а) дату на 03.08.2026; 2026-04-29 10:22:10: Екатерина изменил(-а) дату на 03.08.2026 - 03.08.2026; 2026-04-29 10:22:10: Екатерина изменил(-а) дату на 03.08.2026 - 06.08.2026; 2026-04-30 14:40:08: Екатерина убрал(-а) тег страт-п-с-26-09; 2026-04-30 14:40:11: Екатерина добавил(-а) тег страт-п-с-26-09 | AB202: Лично сентябрь 2026 | AC202: =VLOOKUP(Y202,'впр данные'!A:B,2,1) -> продюсер, страт-п-с-26-09 | AD202: =VLOOKUP(Y202,'впр данные'!A:C,3,1) -> продюсер
A203: 113 | B203: ЛИЧНО сентябрь 24.09.2026 | C203: Дивизион Конференции | D203: К работе | G203: Екатерина | H203: 2.22. Написать ТЗ дизайнеру для подготовки презентации спикера - 3 слайда в гугл-документах: | I203: 03.08.2026 03:00 | J203: 06.08.2026 | L203: Действие | M203: Низкий | N203: N | P203: 27.04.2026 16:49:12 | S203: Екатерина | V203: N | W203: N | Y203: PRO, Продюсер, страт-п-с-26-09 | AA203: 2026-04-27 16:49:13: Екатерина создал(-а) задачу; 2026-04-27 16:49:19: Екатерина изменил(-а) название на 2.22. Написать ТЗ дизайнеру для подготовки презентации спикера - 3 слайда в гугл-документах:; 2026-04-27 17:32:58: Екатерина изменил(-а) дату на 07.08.2026; 2026-04-27 17:33:03: Екатерина добавил(-а) тег PRE; 2026-04-27 17:35:29: Екатерина убрал(-а) тег PRE; 2026-04-27 17:35:32: Екатерина добавил(-а) тег PRO; 2026-04-28 16:17:19: Екатерина изменил(-а) название на х:; 2026-04-28 16:17:21: Екатерина изменил(-а) название на 2.22. Написать ТЗ дизайнеру для подготовки презентации спикера - 3 слайда в гугл-документах:; 2026-04-28 18:49:28: Екатерина переместил(-а) задачу в проекте ЛИЧНО сентябрь 24.09.2026 в колонку Дивизион Конференции / К работе; 2026-04-29 09:55:51: Екатерина добавил(-а) тег страт-п-с-26-09; 2026-04-29 09:55:52: Екатерина добавил(-а) тег Продюсер; 2026-04-29 10:23:02: Екатерина изменил(-а) дату на 03.08.2026 - 07.08.2026; 2026-04-29 10:23:05: Екатерина изменил(-а) дату на 03.08.2026 - 06.08.2026; 2026-04-30 14:45:04: Екатерина убрал(-а) тег страт-п-с-26-09; 2026-04-30 14:45:10: Екатерина добавил(-а) тег страт-п-с-26-09 | AB203: Лично сентябрь 2026 | AC203: =VLOOKUP(Y203,'впр данные'!A:B,2,1) -> продюсер, страт-п-с-26-09 | AD203: =VLOOKUP(Y203,'впр данные'!A:C,3,1) -> продюсер
A204: 112 | B204: ЛИЧНО сентябрь 24.09.2026 | C204: Дивизион Конференции | D204: К работе | G204: Екатерина | H204: 2.23. К проведению еженед. совещания выполнено не менее 90% задач пред и текущ. спринтов + еженедельный отчет опубликовать в чате | I204: 10.08.2026 03:00 | J204: 13.08.2026 | L204: Действие | M204: Низкий | N204: N | P204: 27.04.2026 16:48:32 | S204: Екатерина | V204: N | W204: N | Y204: PRO, Продюсер, страт-п-с-26-09 | AA204: 2026-04-27 16:48:32: Екатерина создал(-а) задачу; 2026-04-27 16:48:49: Екатерина изменил(-а) название на 2.23. К проведению еженед. совещания выполнено не менее 90% задач пред и текущ. спринтов + еженедельный отчет по задачам, протокол опубликован в чате; 2026-04-27 16:48:51: Екатерина изменил(-а) название на 2.23. К проведению еженед. совещания выполнено не менее 90% задач пред и текущ. спринтов + еженедельный отчет по задачам, протокол опубликован в чате; 2026-04-27 16:48:54: Екатерина изменил(-а) название на 2.23. К проведению еженед. совещания выполнено не менее 90% задач пред и текущ. спринтов + еженедельный отчет опубликован в чате; 2026-04-27 16:48:57: Екатерина изменил(-а) название на 2.23. К проведению еженед. совещания выполнено не менее 90% задач пред и текущ. спринтов + еженедельный отчет опубликовать в чате; 2026-04-27 17:33:28: Екатерина изменил(-а) дату на 14.08.2026; 2026-04-27 17:33:31: Екатерина добавил(-а) тег PRE; 2026-04-27 17:35:37: Екатерина убрал(-а) тег PRE; 2026-04-27 17:35:39: Екатерина добавил(-а) тег PRO; 2026-04-28 18:49:36: Екатерина переместил(-а) задачу в проекте ЛИЧНО сентябрь 24.09.2026 в колонку Дивизион Конференции / К работе; 2026-04-29 09:56:54: Екатерина добавил(-а) тег страт-п-с-26-09; 2026-04-29 09:56:59: Екатерина добавил(-а) тег Продюсер; 2026-04-29 10:23:20: Екатерина изменил(-а) дату на 10.08.2026 - 14.08.2026; 2026-04-29 10:23:22: Екатерина изменил(-а) дату на 10.08.2026 - 13.08.2026; 2026-04-30 14:45:29: Екатерина убрал(-а) тег страт-п-с-26-09; 2026-04-30 14:45:31: Екатерина добавил(-а) тег страт-п-с-26-09 | AB204: Лично сентябрь 2026 | AC204: =VLOOKUP(Y204,'впр данные'!A:B,2,1) -> продюсер, страт-п-с-26-09 | AD204: =VLOOKUP(Y204,'впр данные'!A:C,3,1) -> продюсер
A205: 111 | B205: ЛИЧНО сентябрь 24.09.2026 | C205: Дивизион Конференции | D205: К работе | G205: Екатерина | H205: 2.24. Подписать со спикерами не менее 15-35% договоров | I205: 10.08.2026 03:00 | J205: 13.08.2026 | L205: Действие | M205: Низкий | N205: N | P205: 27.04.2026 16:48:30 | S205: Екатерина | V205: N | W205: N | Y205: PRO, Продюсер, страт-п-с-26-09 | AA205: 2026-04-27 16:48:30: Екатерина создал(-а) задачу; 2026-04-27 16:48:38: Екатерина изменил(-а) название на 2.24. Подписать со спикерами не менее 15-35% договоров; 2026-04-27 17:33:41: Екатерина изменил(-а) дату на 14.08.2026; 2026-04-27 17:33:47: Екатерина добавил(-а) тег PRE; 2026-04-27 17:35:43: Екатерина убрал(-а) тег PRE; 2026-04-27 17:35:45: Екатерина добавил(-а) тег PRO; 2026-04-28 18:49:39: Екатерина переместил(-а) задачу в проекте ЛИЧНО сентябрь 24.09.2026 в колонку Дивизион Конференции / К работе; 2026-04-29 09:57:09: Екатерина добавил(-а) тег страт-п-с-26-09; 2026-04-29 09:57:12: Екатерина добавил(-а) тег Продюсер; 2026-04-29 10:23:32: Екатерина изменил(-а) дату на 10.08.2026 - 14.08.2026; 2026-04-29 10:23:33: Екатерина изменил(-а) дату на 10.08.2026 - 13.08.2026; 2026-04-30 14:45:45: Екатерина убрал(-а) тег страт-п-с-26-09; 2026-04-30 14:45:52: Екатерина добавил(-а) тег страт-п-с-26-09 | AB205: Лично сентябрь 2026 | AC205: =VLOOKUP(Y205,'впр данные'!A:B,2,1) -> продюсер, страт-п-с-26-09 | AD205: =VLOOKUP(Y205,'впр данные'!A:C,3,1) -> продюсер
... A208: 95 | B208: ЛИЧНО сентябрь 24.09.2026 | C208: Дивизион Конференции | D208: К работе | G208: Екатерина | H208: 2.40. Получить презентации от70% подтвержденных спикеров | I208: 31.08.2026 03:00 | J208: 03.09.2026 | L208: Действие | M208: Низкий | N208: N | P208: 27.04.2026 16:34:14 | S208: Екатерина | V208: N | W208: N | Y208: PRO, Продюсер, страт-п-с-26-09 | AA208: 2026-04-27 16:34:15: Екатерина создал(-а) задачу; 2026-04-27 16:34:31: Екатерина изменил(-а) название на 2.40. Получены презентации от70% подтвержденных спикеров; 2026-04-27 16:36:15: Екатерина изменил(-а) название на 2.40. Получить презентации от70% подтвержденных спикеров; 2026-04-27 17:38:48: Екатерина добавил(-а) тег PRO; 2026-04-28 18:50:50: Екатерина переместил(-а) задачу в проекте ЛИЧНО сентябрь 24.09.2026 в колонку Дивизион Конференции / К работе; 2026-04-29 10:36:15: Екатерина изменил(-а) дату на 31.08.2026 - 31.08.2026; 2026-04-29 10:36:16: Екатерина изменил(-а) дату на 31.08.2026 - 03.09.2026; 2026-04-29 11:07:17: Екатерина добавил(-а) тег страт-п-с-26-09; 2026-04-29 11:07:18: Екатерина добавил(-а) тег Продюсер; 2026-04-30 14:49:24: Екатерина убрал(-а) тег страт-п-с-26-09; 2026-04-30 14:49:26: Екатерина добавил(-а) тег страт-п-с-26-09 | AB208: Лично сентябрь 2026 | AC208: =VLOOKUP(Y208,'впр данные'!A:B,2,1) -> продюсер, страт-п-с-26-09 | AD208: =VLOOKUP(Y208,'впр данные'!A:C,3,1) -> продюсер
A209: 79 | B209: ЛИЧНО сентябрь 24.09.2026 | C209: Дивизион Конференции | D209: К работе | E209: 2.54. Провести модерацию мероприятия | F209: 2.54. Провести модерацию мероприятия | G209: Екатерина | H209: 2.61. Проконтролировать выставление счета | I209: 28.09.2026 03:00 | J209: 01.10.2026 | L209: Действие | M209: Низкий | N209: N | P209: 27.04.2026 16:24:29 | S209: Екатерина | V209: N | W209: N | Y209: POST, Продюсер, страт-п-с-26-09 | AA209: 2026-04-27 16:24:29: Екатерина создал(-а) задачу; 2026-04-27 16:33:17: Екатерина изменил(-а) название на 2.61. Проконтролировано выставление счета; 2026-04-27 16:40:28: Екатерина изменил(-а) название на 2.61. Проконтролировать выставление счета; 2026-04-27 17:37:27: Екатерина добавил(-а) тег POST; 2026-04-27 17:44:06: Екатерина изменил(-а) дату на 02.10.2026; 2026-04-28 18:52:25: Екатерина переместил(-а) задачу в проекте ЛИЧНО сентябрь 24.09.2026 в колонку Дивизион Конференции / К работе; 2026-04-28 18:53:48: Екатерина изменил(-а) родительскую задачу на #81 2.54. Провести модерацию мероприятия; 2026-04-29 10:19:06: Екатерина изменил(-а) дату на 28.09.2026 - 02.10.2026; 2026-04-29 10:19:07: Екатерина изменил(-а) дату на 28.09.2026 - 01.10.2026; 2026-04-29 11:09:39: Екатерина добавил(-а) тег страт-п-с-26-09; 2026-04-29 11:09:39: Екатерина добавил(-а) тег Продюсер; 2026-04-30 14:55:09: Екатерина убрал(-а) тег страт-п-с-26-09; 2026-04-30 14:55:11: Екатерина добавил(-а) тег страт-п-с-26-09 | AB209: Лично сентябрь 2026 | AC209: =VLOOKUP(Y209,'впр данные'!A:B,2,1) -> продюсер, страт-п-с-26-09 | AD209: =VLOOKUP(Y209,'впр данные'!A:C,3,1) -> продюсер
A210: 78 | B210: ЛИЧНО сентябрь 24.09.2026 | C210: Дивизион Конференции | D210: К работе | G210: Екатерина | H210: 2.56. Подготовить отчет к Итоговому совещанию для рабочей группы | I210: 28.09.2026 03:00 | J210: 01.10.2026 | L210: Действие | M210: Низкий | N210: N | P210: 27.04.2026 16:24:17 | S210: Екатерина | V210: N | W210: N | Y210: POST, Продюсер, страт-п-с-26-09 | AA210: 2026-04-27 16:24:17: Екатерина создал(-а) задачу; 2026-04-27 16:32:32: Екатерина изменил(-а) название на 2.56. Подготовлен отчет к Итоговому совещанию для рабочей группы; 2026-04-27 16:39:57: Екатерина изменил(-а) название на 2.56. Подготовить отчет к Итоговому совещанию для рабочей группы; 2026-04-27 17:36:55: Екатерина добавил(-а) тег POST; 2026-04-27 17:42:28: Екатерина изменил(-а) дату на 02.10.2026; 2026-04-27 17:43:16: Екатерина переместил(-а) задачу в проекте ЛИЧНО сентябрь 24.09.2026 в колонку 2. Продюсер Лично сентябрь / В работе; 2026-04-27 17:43:25: Екатерина переместил(-а) задачу в проекте ЛИЧНО сентябрь 24.09.2026 в колонку 2. Продюсер Лично сентябрь / К работе; 2026-04-28 18:52:29: Екатерина переместил(-а) задачу в проекте ЛИЧНО сентябрь 24.09.2026 в колонку Дивизион Конференции / К работе; 2026-04-29 10:17:28: Екатерина изменил(-а) дату на 28.09.2026 - 02.10.2026; 2026-04-29 10:17:29: Екатерина изменил(-а) дату на 04.09.2026 - 02.10.2026; 2026-04-29 10:17:34: Екатерина изменил(-а) дату на 28.09.2026 - 02.10.2026; 2026-04-29 10:17:37: Екатерина изменил(-а) дату на 28.09.2026 - 01.10.2026; 2026-04-29 11:09:15: Екатерина добавил(-а) тег страт-п-с-26-09; 2026-04-29 11:09:16: Екатерина добавил(-а) тег Продюсер; 2026-04-30 14:54:12: Екатерина убрал(-а) тег страт-п-с-26-09; 2026-04-30 14:54:14: Екатерина добавил(-а) тег страт-п-с-26-09 | AB210: Лично сентябрь 2026 | AC210: =VLOOKUP(Y210,'впр данные'!A:B,2,1) -> продюсер, страт-п-с-26-09 | AD210: =VLOOKUP(Y210,'впр данные'!A:C,3,1) -> продюсер
...

Sheet впр данные
A1: теги | B1: роль и мероприятие | C1: роль
A2: D, координатор, страт-п-с-26-09 | B2: координатор, страт-п-с-26-09 | C2: координатор
A3: D, Лидген, страт-п-с-26-09 | B3: лидген, страт-п-с-26-09 | C3: лидген
A4: D, Продюсер, страт-п-с-26-09 | B4: продюсер, страт-п-с-26-09 | C4: продюсер
A5: D, ШП, страт-п-с-26-09 | B5: ШП, страт-п-с-26-09 | C5: ШП
A6: POST, координатор, страт-п-с-26-09 | B6: координатор, страт-п-с-26-09 | C6: координатор
A7: POST, Лидген, страт-п-с-26-09 | B7: лидген, страт-п-с-26-09 | C7: лидген
A8: POST, Продюсер, страт-п-с-26-09 | B8: продюсер, страт-п-с-26-09 | C8: продюсер
A9: POST, РГП, страт-п-с-26-09 | B9: РГП, страт-п-с-26-09 | C9: РГП
A10: POST, ШП, страт-п-с-26-09 | B10: ШП, страт-п-с-26-09 | C10: ШП
A11: PRE, координатор, страт-п-с-26-09 | B11: координатор, страт-п-с-26-09 | C11: координатор
A12: PRE, Лидген, страт-п-с-26-09 | B12: лидген, страт-п-с-26-09 | C12: лидген
... A24: страт-п-с-26-09, Операционный директор, финиш вехи Post | B24: страт-п-с-26-09, ШП, финиш вехи Post | C24: Операцоинный директор

Sheet прогрессбар заданий 
B1: недельный номер спринта | C1: 14 pre | D1: 13 pre | E1: 12 pre | F1: 11 pre | G1: 10 pre | H1: 9 pre | I1: 8 pro | J1: 7 pro | K1: 6 pro | L1: 5 pro | M1: 4 pro | N1: 3 pro | O1: 2 pro | P1: 1 pro | Q1: 0 D | R1: 1 post | T1: просроченность задач | U1: цвет светофора | V1: 18 - 22 мая | W1: 25-29 мая | X1: 1-5 июня | Y1: 8-12 июня | Z1: 15-19 июня | AA1: 22-26 июня | AB1: 27 июля - 31 июля | AC1: 3-7 августа | AD1: 10-14 августа | AE1: 17-21 августа | AF1: 24-28 августа | AG1: 31 августа - 4 сентября | AH1: 7-11 сентября | AI1: 14-18 сентября | AJ1: 21-25 сентября | AK1: 28 сентября - 2 октября | AM1: выполнение задач | AN1: цвет светофора | AO1: 18 - 22 мая | AP1: 25-29 мая | AQ1: 1-5 июня | AR1: 8-12 июня | AS1: 15-19 июня | AT1: 22-26 июня | AU1: 27 июля - 31 июля | AV1: 3-7 августа | AW1: 10-14 августа | AX1: 17-21 августа | AY1: 24-28 августа | AZ1: 31 августа - 4 сентября | BA1: 7-11 сентября | BB1: 14-18 сентября | BC1: 21-25 сентября | BD1: 28 сентября - 2 октября | BF1: просроченность задач | BG1: цвет светофора | BH1: 18 - 22 мая | BI1: 25-29 мая | BJ1: 1-5 июня | BK1: 8-12 июня | BL1: 15-19 июня | BM1: 22-26 июня | BN1: 27 июля - 31 июля | BO1: 3-7 августа | BP1: 10-14 августа | BQ1: 17-21 августа | BR1: 24-28 августа | BS1: 31 августа - 4 сентября | BT1: 7-11 сентября | BU1: 14-18 сентября | BV1: 21-25 сентября | BW1: 28 сентября - 2 октября | BY1: выполнение задач | BZ1: цвет светофора | CA1: 18 - 22 мая | CB1: 25-29 мая | CC1: 1-5 июня | CD1: 8-12 июня | CE1: 15-19 июня | CF1: 22-26 июня | CG1: 27 июля - 31 июля | CH1: 3-7 августа | CI1: 10-14 августа | CJ1: 17-21 августа | CK1: 24-28 августа | CL1: 31 августа - 4 сентября | CM1: 7-11 сентября | CN1: 14-18 сентября | CO1: 21-25 сентября | CP1: 28 сентября - 2 октября | CS1: отклонение по просрочке | CT1: цвет светофора просрочки задач | CV1: выполнение | CW1: цвет светофора по выполнению задач
C2: 18 - 22 мая | D2: 25-29 мая | E2: 1-5 июня | F2: 8-12 июня | G2: 15-19 июня | H2: 22-26 июня | I2: 27 июля - 31 июля | J2: 3-7 августа | K2: 10-14 августа | L2: 17-21 августа | M2: 24-28 августа | N2: 31 августа - 4 сентября | O2: 7-11 сентября | P2: 14-18 сентября | Q2: 21-25 сентября | R2: 28 сентября - 2 октября | T2: меньше 20% | U2: зеленый | V2: 0 | W2: 0 | X2: 0 | Y2: 0 | Z2: 0 | AA2: 0 | AB2: 0 | AC2: 0 | AD2: 0 | AE2: 0 | AF2: 0 | AG2: 0 | AH2: 0 | AI2: 0 | AJ2: 0 | AK2: 0 | AM2: меньше 60% | AN2: красный | AO2: 0 | AP2: 0 | AQ2: 0 | AR2: 0 | AS2: 0 | AT2: 0 | AU2: 0 | AV2: 0 | AW2: 0 | AX2: 0 | AY2: 0 | AZ2: 0 | BA2: 0 | BB2: 0 | BC2: 0 | BD2: 0 | BF2: ШП, страт-п-с-26-09 | BG2: зеленый | BH2: 0 | BI2: 0 | BJ2: 0 | BK2: 0 | BL2: 0 | BM2: 0 | BN2: 0 | BO2: 0 | BP2: 0 | BQ2: 0 | BR2: 0 | BS2: 0 | BT2: 0 | BU2: 0 | BV2: 0 | BW2: 0 | BY2: ШП, страт-п-с-26-09 | BZ2: красный | CA2: 0 | CB2: 0 | CC2: 0 | CD2: 0 | CE2: 0 | CF2: 0 | CG2: 0 | CH2: 0 | CI2: 0 | CJ2: 0 | CK2: 0 | CL2: 0 | CM2: 0 | CN2: 0 | CO2: 0 | CP2: 0 | CS2: 0 | CT2: зеленый | CV2: 0 | CW2: красный
A3: 1 | B3: ШП, страт-п-с-26-09 | C3: 2 | D3: 3 | E3: 5 | F3: 5 | G3: 8 | H3: 8 | I3: 10 | J3: 11 | K3: 13 | L3: 14 | M3: 16 | N3: 17 | O3: 22 | P3: 27 | Q3: 29 | R3: 35 | T3: 20-40% | U3: желтый | V3: =C8/100*20 -> 1.2 | W3: =D8/100*20 -> 2.8 | X3: =E8/100*20 -> 6 | Y3: =F8/100*20 -> 7.6 | Z3: =G8/100*20 -> 9.2 | AA3: =H8/100*20 -> 10.8 | AB3: =I8/100*20 -> 13 | AC3: =J8/100*20 -> 15.4 | ... AK3: =R8/100*20 -> 43.8 | AM3: (60-80%) | AN3: желтый | AO3: 3.6 | AP3: 8.4 | AQ3: 18 | AR3: 22.8 | AS3: 27.6 | AT3: 32.4 | AU3: 39 | AV3: 46.2 | AW3: 54 | AX3: 61.8 | AY3: 71.4 | AZ3: 81 | BA3: 96 | BB3: 111.6 | BC3: 117 | BD3: 131.4 | BF3: продюсер, страт-п-с-26-09 | BG3: зеленый | BH3: 0 | BI3: 0 | BJ3: 0 | BK3: 0 | BL3: 0 | BM3: 0 | BN3: 0 | BO3: 0 | BP3: 0 | BQ3: 0 | BR3: 0 | BS3: 0 | BT3: 0 | BU3: 0 | BV3: 0 | BW3: 0 | BY3: продюсер, страт-п-с-26-09 | BZ3: красный | CA3: 0 | CB3: 0 | CC3: 0 | CD3: 0 | CE3: 0 | CF3: 0 | CG3: 0 | CH3: 0 | CI3: 0 | CJ3: 0 | CK3: 0 | CL3: 0 | CM3: 0 | CN3: 0 | CO3: 0 | CP3: 0 | CS3: 0.2 | CT3: желтый | CV3: 0.601 | CW3: желтый
A4: 2 | B4: продюсер, страт-п-с-26-09 | C4: 1 | D4: 3 | E4: 7 | F4: 10 | G4: 12 | H4: 15 | I4: 17 | J4: 22 | K4: 26 | L4: 30 | M4: 36 | N4: 41 | O4: 47 | P4: 52 | Q4: 55 | R4: 61 | T4: больше 40% | U4: красный | V4: =C8/100*40 -> 2.4 | W4: =D8/100*40 -> 5.6 | X4: =E8/100*40 -> 12 | Y4: =F8/100*40 -> 15.2 | Z4: =G8/100*40 -> 18.4 | AA4: =H8/100*40 -> 21.6 | AB4: =I8/100*40 -> 26 | AC4: =J8/100*40 -> 30.8 | ... AK4: =R8/100*40 -> 87.6 | AM4: (больше 80%) | AN4: зеленый | AO4: 4.8 | AP4: 11.2 | AQ4: 24 | AR4: 30.4 | AS4: 36.8 | AT4: 43.2 | AU4: 52 | AV4: 61.6 | AW4: 72 | AX4: 82.4 | AY4: 95.2 | AZ4: 108 | BA4: 128 | BB4: 148.8 | BC4: 156 | BD4: 175.2 | BF4: координатор, страт-п-с-26-09 | BG4: зеленый | BH4: 0 | BI4: 0 | BJ4: 0 | BK4: 0 | BL4: 0 | BM4: 0 | BN4: 0 | BO4: 0 | BP4: 0 | BQ4: 0 | BR4: 0 | BS4: 0 | BT4: 0 | BU4: 0 | BV4: 0 | BW4: 0 | BY4: координатор, страт-п-с-26-09 | BZ4: красный | CA4: 0 | CB4: 0 | CC4: 0 | CD4: 0 | CE4: 0 | CF4: 0 | CG4: 0 | CH4: 0 | CI4: 0 | CJ4: 0 | CK4: 0 | CL4: 0 | CM4: 0 | CN4: 0 | CO4: 0 | CP4: 0 | CS4: 0.4 | CT4: красный | CV4: 0.8 | CW4: зеленый
A5: 3 | B5: координатор, страт-п-с-26-09 | C5: 1 | D5: 4 | E5: 7 | F5: 9 | G5: 10 | H5: 12 | I5: 14 | J5: 16 | K5: 18 | L5: 21 | M5: 25 | N5: 31 | O5: 41 | P5: 53 | Q5: 56 | R5: 61 | BF5: лидген, страт-п-с-26-09 | BG5: зеленый | BH5: 0 | BI5: 0 | BJ5: 0 | BK5: 0 | BL5: 0 | BM5: 0 | BN5: 0 | BO5: 0 | BP5: 0 | BQ5: 0 | BR5: 0 | BS5: 0 | BT5: 0 | BU5: 0 | BV5: 0 | BW5: 0 | BY5: лидген, страт-п-с-26-09 | BZ5: красный | CA5: 0 | CB5: 0 | CC5: 0 | CD5: 0 | CE5: 0 | CF5: 0 | CG5: 0 | CH5: 0 | CI5: 0 | CJ5: 0 | CK5: 0 | CL5: 0 | CM5: 0 | CN5: 0 | CO5: 0 | CP5: 0
A6: 4 | B6: лидген, страт-п-с-26-09 | C6: 1 | D6: 2 | E6: 5 | F6: 6 | G6: 7 | H6: 9 | I6: 10 | J6: 11 | K6: 12 | L6: 13 | M6: 14 | N6: 15 | O6: 16 | P6: 17 | Q6: 18 | R6: 21 | BF6: РГП, страт-п-с-26-09 | BG6: зеленый | BH6: 0 | BI6: 0 | BJ6: 0 | BK6: 0 | BL6: 0 | BM6: 0 | BN6: 0 | BO6: 0 | BP6: 0 | BQ6: 0 | BR6: 0 | BS6: 0 | BT6: 0 | BU6: 0 | BV6: 0 | BW6: 0 | BY6: РГП, страт-п-с-26-09 | BZ6: красный | CA6: 0 | CB6: 0 | CC6: 0 | CD6: 0 | CE6: 0 | CF6: 0 | CG6: 0 | CH6: 0 | CI6: 0 | CJ6: 0 | CK6: 0 | CL6: 0 | CM6: 0 | CN6: 0 | CO6: 0 | CP6: 0
A7: 5 | B7: РГП, страт-п-с-26-09 | C7: 1 | D7: 2 | E7: 6 | F7: 8 | G7: 9 | H7: 10 | I7: 14 | J7: 17 | K7: 21 | L7: 25 | M7: 28 | N7: 31 | O7: 34 | P7: 37 | Q7: 37 | R7: 41 | BF7: ШП, страт-п-с-26-09 | BG7: желтый | BH7: =C3/100*20 -> 0.4 | BI7: =D3/100*20 -> 0.6 | BJ7: =E3/100*20 -> 1 | BK7: =F3/100*20 -> 1 | BL7: =G3/100*20 -> 1.6 | BM7: =H3/100*20 -> 1.6 | BN7: =I3/100*20 -> 2 | BO7: =J3/100*20 -> 2.2 | ... BW7: =R3/100*20 -> 7 | BY7: ШП, страт-п-с-26-09 | BZ7: желтый | CA7: =C3/100*60 -> 1.2 | CB7: =D3/100*60 -> 1.8 | CC7: =E3/100*60 -> 3 | CD7: =F3/100*60 -> 3 | CE7: =G3/100*60 -> 4.8 | CF7: =H3/100*60 -> 4.8 | CG7: =I3/100*60 -> 6 | CH7: =J3/100*60 -> 6.6 | ... CP7: =R3/100*60 -> 21
C8: =SUM(C3:C7) -> 6 | D8: =SUM(D3:D7) -> 14 | E8: =SUM(E3:E7) -> 30 | F8: =SUM(F3:F7) -> 38 | G8: =SUM(G3:G7) -> 46 | H8: =SUM(H3:H7) -> 54 | I8: =SUM(I3:I7) -> 65 | J8: =SUM(J3:J7) -> 77 | ... R8: =SUM(R3:R7) -> 219 | BF8: продюсер, страт-п-с-26-09 | BG8: желтый | BH8: =C4/100*20 -> 0.2 | BI8: =D4/100*20 -> 0.6 | BJ8: =E4/100*20 -> 1.4 | BK8: =F4/100*20 -> 2 | BL8: =G4/100*20 -> 2.4 | BM8: =H4/100*20 -> 3 | BN8: =I4/100*20 -> 3.4 | BO8: =J4/100*20 -> 4.4 | ... BW8: =R4/100*20 -> 12.2 | BY8: продюсер, страт-п-с-26-09 | BZ8: желтый | CA8: =C4/100*60 -> 0.6 | CB8: =D4/100*60 -> 1.8 | CC8: =E4/100*60 -> 4.2 | CD8: =F4/100*60 -> 6 | CE8: =G4/100*60 -> 7.2 | CF8: =H4/100*60 -> 9 | CG8: =I4/100*60 -> 10.2 | CH8: =J4/100*60 -> 13.2 | ... CP8: =R4/100*60 -> 36.6
BF9: координатор, страт-п-с-26-09 | BG9: желтый | BH9: =C5/100*20 -> 0.2 | BI9: =D5/100*20 -> 0.8 | BJ9: =E5/100*20 -> 1.4 | BK9: =F5/100*20 -> 1.8 | BL9: =G5/100*20 -> 2 | BM9: =H5/100*20 -> 2.4 | BN9: =I5/100*20 -> 2.8 | BO9: =J5/100*20 -> 3.2 | ... BW9: =R5/100*20 -> 12.2 | BY9: координатор, страт-п-с-26-09 | BZ9: желтый | CA9: =C5/100*60 -> 0.6 | CB9: =D5/100*60 -> 2.4 | CC9: =E5/100*60 -> 4.2 | CD9: =F5/100*60 -> 5.4 | CE9: =G5/100*60 -> 6 | CF9: =H5/100*60 -> 7.2 | CG9: =I5/100*60 -> 8.4 | CH9: =J5/100*60 -> 9.6 | ... CP9: =R5/100*60 -> 36.6
C10: =C8/$R$8 -> 0.02739726 | D10: =D8/$R$8 -> 0.063926941 | E10: =E8/$R$8 -> 0.1369863 | F10: =F8/$R$8 -> 0.17351598 | G10: =G8/$R$8 -> 0.21004566 | H10: =H8/$R$8 -> 0.24657534 | I10: =I8/$R$8 -> 0.29680365 | J10: =J8/$R$8 -> 0.35159817 | ... R10: =R8/$R$8 -> 1 | BF10: лидген, страт-п-с-26-09 | BG10: желтый | BH10: =C6/100*20 -> 0.2 | BI10: =D6/100*20 -> 0.4 | BJ10: =E6/100*20 -> 1 | BK10: =F6/100*20 -> 1.2 | BL10: =G6/100*20 -> 1.4 | BM10: =H6/100*20 -> 1.8 | BN10: =I6/100*20 -> 2 | BO10: =J6/100*20 -> 2.2 | ... BW10: =R6/100*20 -> 4.2 | BY10: лидген, страт-п-с-26-09 | BZ10: желтый | CA10: =C6/100*60 -> 0.6 | CB10: =D6/100*60 -> 1.2 | CC10: =E6/100*60 -> 3 | CD10: =F6/100*60 -> 3.6 | CE10: =G6/100*60 -> 4.2 | CF10: =H6/100*60 -> 5.4 | CG10: =I6/100*60 -> 6 | CH10: =J6/100*60 -> 6.6 | ... CP10: =R6/100*60 -> 12.6
BF11: РГП, страт-п-с-26-09 | BG11: желтый | BH11: =C7/100*20 -> 0.2 | BI11: =D7/100*20 -> 0.4 | BJ11: =E7/100*20 -> 1.2 | BK11: =F7/100*20 -> 1.6 | BL11: =G7/100*20 -> 1.8 | BM11: =H7/100*20 -> 2 | BN11: =I7/100*20 -> 2.8 | BO11: =J7/100*20 -> 3.4 | ... BW11: =R7/100*20 -> 8.2 | BY11: РГП, страт-п-с-26-09 | BZ11: желтый | CA11: =C7/100*60 -> 0.6 | CB11: =D7/100*60 -> 1.2 | CC11: =E7/100*60 -> 3.6 | CD11: =F7/100*60 -> 4.8 | CE11: =G7/100*60 -> 5.4 | CF11: =H7/100*60 -> 6 | CG11: =I7/100*60 -> 8.4 | CH11: =J7/100*60 -> 10.2 | ... CP11: =R7/100*60 -> 24.6
BF12: РГП, страт-п-с-26-09 | BG12: желтый | BH12: =C7/100*20 -> 0.2 | BI12: =D7/100*20 -> 0.4 | BJ12: =E7/100*20 -> 1.2 | BK12: =F7/100*20 -> 1.6 | BL12: =G7/100*20 -> 1.8 | BM12: =H7/100*20 -> 2 | BN12: =I7/100*20 -> 2.8 | BO12: =J7/100*20 -> 3.4 | ... BW12: =R7/100*20 -> 8.2 | BY12: рГП, страт-п-с-26-09 | BZ12: желтый | CA12: =C7/100*60 -> 0.6 | CB12: =D7/100*60 -> 1.2 | CC12: =E7/100*60 -> 3.6 | CD12: =F7/100*60 -> 4.8 | CE12: =G7/100*60 -> 5.4 | CF12: =H7/100*60 -> 6 | CG12: =I7/100*60 -> 8.4 | CH12: =J7/100*60 -> 10.2 | ... CP12: =R7/100*60 -> 24.6
BF13: ШП, страт-п-с-26-09 | BG13: красный | BH13: =C3/100*40 -> 0.8 | BI13: =D3/100*40 -> 1.2 | BJ13: =E3/100*40 -> 2 | BK13: =F3/100*40 -> 2 | BL13: =G3/100*40 -> 3.2 | BM13: =H3/100*40 -> 3.2 | BN13: =I3/100*40 -> 4 | BO13: =J3/100*40 -> 4.4 | ... BW13: =R3/100*40 -> 14 | BY13: ШП, страт-п-с-26-09 | BZ13: зеленый | CA13: =C3/100*80 -> 1.6 | CB13: =D3/100*80 -> 2.4 | CC13: =E3/100*80 -> 4 | CD13: =F3/100*80 -> 4 | CE13: =G3/100*80 -> 6.4 | CF13: =H3/100*80 -> 6.4 | CG13: =I3/100*80 -> 8 | CH13: =J3/100*80 -> 8.8 | ... CP13: =R3/100*80 -> 28
BF14: продюсер, страт-п-с-26-09 | BG14: красный | BH14: =C4/100*40 -> 0.4 | BI14: =D4/100*40 -> 1.2 | BJ14: =E4/100*40 -> 2.8 | BK14: =F4/100*40 -> 4 | BL14: =G4/100*40 -> 4.8 | BM14: =H4/100*40 -> 6 | BN14: =I4/100*40 -> 6.8 | BO14: =J4/100*40 -> 8.8 | ... BW14: =R4/100*40 -> 24.4 | BY14: продюсер, страт-п-с-26-09 | BZ14: зеленый | CA14: =C4/100*80 -> 0.8 | CB14: =D4/100*80 -> 2.4 | CC14: =E4/100*80 -> 5.6 | CD14: =F4/100*80 -> 8 | CE14: =G4/100*80 -> 9.6 | CF14: =H4/100*80 -> 12 | CG14: =I4/100*80 -> 13.6 | CH14: =J4/100*80 -> 17.6 | ... CP14: =R4/100*80 -> 48.8
BF15: координатор, страт-п-с-26-09 | BG15: красный | BH15: =C5/100*40 -> 0.4 | BI15: =D5/100*40 -> 1.6 | BJ15: =E5/100*40 -> 2.8 | BK15: =F5/100*40 -> 3.6 | BL15: =G5/100*40 -> 4 | BM15: =H5/100*40 -> 4.8 | BN15: =I5/100*40 -> 5.6 | BO15: =J5/100*40 -> 6.4 | ... BW15: =R5/100*40 -> 24.4 | BY15: координатор, страт-п-с-26-09 | BZ15: зеленый | CA15: =C5/100*80 -> 0.8 | CB15: =D5/100*80 -> 3.2 | CC15: =E5/100*80 -> 5.6 | CD15: =F5/100*80 -> 7.2 | CE15: =G5/100*80 -> 8 | CF15: =H5/100*80 -> 9.6 | CG15: =I5/100*80 -> 11.2 | CH15: =J5/100*80 -> 12.8 | ... CP15: =R5/100*80 -> 48.8
BF16: лидген, страт-п-с-26-09 | BG16: красный | BH16: =C6/100*40 -> 0.4 | BI16: =D6/100*40 -> 0.8 | BJ16: =E6/100*40 -> 2 | BK16: =F6/100*40 -> 2.4 | BL16: =G6/100*40 -> 2.8 | BM16: =H6/100*40 -> 3.6 | BN16: =I6/100*40 -> 4 | BO16: =J6/100*40 -> 4.4 | ... BW16: =R6/100*40 -> 8.4 | BY16: лидген, страт-п-с-26-09 | BZ16: зеленый | CA16: =C6/100*80 -> 0.8 | CB16: =D6/100*80 -> 1.6 | CC16: =E6/100*80 -> 4 | CD16: =F6/100*80 -> 4.8 | CE16: =G6/100*80 -> 5.6 | CF16: =H6/100*80 -> 7.2 | CG16: =I6/100*80 -> 8 | CH16: =J6/100*80 -> 8.8 | ... CP16: =R6/100*80 -> 16.8
BF17: РГП, страт-п-с-26-09 | BG17: красный | BH17: =C7/100*40 -> 0.4 | BI17: =D7/100*40 -> 0.8 | BJ17: =E7/100*40 -> 2.4 | BK17: =F7/100*40 -> 3.2 | BL17: =G7/100*40 -> 3.6 | BM17: =H7/100*40 -> 4 | BN17: =I7/100*40 -> 5.6 | BO17: =J7/100*40 -> 6.8 | ... BW17: =R7/100*40 -> 16.4 | BY17: РГП, страт-п-с-26-09 | BZ17: зеленый | CA17: =C7/100*80 -> 0.8 | CB17: =D7/100*80 -> 1.6 | CC17: =E7/100*80 -> 4.8 | CD17: =F7/100*80 -> 6.4 | CE17: =G7/100*80 -> 7.2 | CF17: =H7/100*80 -> 8 | CG17: =I7/100*80 -> 11.2 | CH17: =J7/100*80 -> 13.6 | ... CP17: =R7/100*80 -> 32.8

Sheet пример раскрашивания
B1: план по выполнению задач к 28 сент - 4 окт | C1: выполнено к 28 сент-4 окт | D1: % выполнения | E1: цвет светофора | H1: план по выполнению задач к 28 сент - 4 окт | I1: просрочено к 28 сент-4 окт | J1: % просрочки | K1: цвет светофора
A2: ШП, страт-п-с-26-09 | B2: 35 | C2: 21 | D2: =C2/B2 -> 0.6 | E2: =VLOOKUP('пример раскрашивания'!D2,'прогрессбар заданий '!CV:CW,2,1) -> красный | G2: ШП, страт-п-с-26-09 | H2: 35 | I2: =B2-C2 -> 14 | J2: =I2/H2 -> 0.4 | K2: =VLOOKUP(J2,'прогрессбар заданий '!CS:CT,2,1) -> красный
A3: продюсер, страт-п-с-26-09 | B3: 61 | C3: 24 | D3: =C3/B3 -> 0.39344262 | E3: =VLOOKUP('пример раскрашивания'!D3,'прогрессбар заданий '!CV:CW,2,1) -> красный | G3: продюсер, страт-п-с-26-09 | H3: 61 | I3: =B3-C3 -> 37 | J3: =I3/H3 -> 0.60655738 | K3: =VLOOKUP(J3,'прогрессбар заданий '!CS:CT,2,1) -> красный
A4: координатор, страт-п-с-26-09 | B4: 61 | C4: 30 | D4: =C4/B4 -> 0.49180328 | E4: =VLOOKUP('пример раскрашивания'!D4,'прогрессбар заданий '!CV:CW,2,1) -> красный | G4: координатор, страт-п-с-26-09 | H4: 61 | I4: =B4-C4 -> 31 | J4: =I4/H4 -> 0.50819672 | K4: =VLOOKUP(J4,'прогрессбар заданий '!CS:CT,2,1) -> красный
A5: лидген, страт-п-с-26-09 | B5: 21 | C5: 18 | D5: =C5/B5 -> 0.85714286 | E5: =VLOOKUP('пример раскрашивания'!D5,'прогрессбар заданий '!CV:CW,2,1) -> зеленый | G5: лидген, страт-п-с-26-09 | H5: 21 | I5: =B5-C5 -> 3 | J5: =I5/H5 -> 0.14285714 | K5: =VLOOKUP(J5,'прогрессбар заданий '!CS:CT,2,1) -> зеленый
A6: РГП, страт-п-с-26-09 | B6: 41 | C6: 40 | D6: =C6/B6 -> 0.97560976 | E6: =VLOOKUP('пример раскрашивания'!D6,'прогрессбар заданий '!CV:CW,2,1) -> зеленый | G6: РГП, страт-п-с-26-09 | H6: 41 | I6: =B6-C6 -> 1 | J6: =I6/H6 -> 0.024390244 | K6: =VLOOKUP(J6,'прогрессбар заданий '!CS:CT,2,1) -> зеленый

Sheet задание
A1: Задача
A3: 1. Выгрузка - столбец Просроченные дни и Прогрессбар заданий - отклонение - сравнить и посчитать есть ли отклонение и сколько % оно составляет и раскрасить в нужный цвет внутри дашборда
A5: отклонение по просрочке | B5: цвет светофора просрочки задач
A6: 0 | B6: зеленый
A7: 0.2 | B7: желтый
A8: 0.4 | B8: красный
A14: № | B14: Название проекта | C14: D | D14: Выполнение на текущий недельный спринт
D15: кол-во выполненных вех | F15: кол-во выполненных задач
D17: план | E17: факт | F17: план | G17: факт | H17: не выполнено к 08.05 | I17: % невыполнения | J17: цвет
A18: 1 | B18: Лично сентябрь 2026 | C18: 08.05.2026 | D18: - | E18: - | F18: 2 | G18: 0 (0%) | H18: 2 | I18: 100,0% | J18: красный
A19: 1.1. | B19: Без роли | F19: 2 | G19: 0 (0%) | H19: 2 | I19: 100,0% | J19: красный
A20: Итого | B20: Задачи к 08.05.2026 | F20: 2 | G20: 0 (0%) | H20: 2 | I20: 100,0% | J20: красный
